Workbook

Sheet LEGGIMI
A1: Fonti sul mercato e sulla spesa in cybersecurity in UE e Regno Unito
A3: Scopo | B3: Censimento delle fonti pubblicate sulla dimensione del mercato e sulla spesa in cybersecurity per i 27 Stati membri, il Regno Unito e l'UE nel suo insieme. Il file serve a confrontare e ancorare un modello bottom-up della spesa cyber delle imprese basato sul fatturato Eurostat SBS. Non contiene una nuova stima.
A4: Data della ricerca | B4: 08/10/2026
A5: Contenuto | B5: 1215 righe in Dati, 406 fonti in Fonti_Metodologie, 158 ricerche registrate in Ricerche_senza_esito. I conteggi aggiornati per paese sono nel foglio Copertura_Paesi.
A6: Fogli | B6: Dati riporta un numero per riga. Fonti_Metodologie riporta una scheda per ID_Fonte. Copertura_Paesi calcola con formule la copertura di ciascuno dei 29 ambiti. Ricerche_senza_esito registra le ricerche che non hanno prodotto dati. Cambi riporta le medie annue BCE e i fattori di conversione delle unità.
A7: ID_Fonte | B7: Schema ENTE-PRODOTTO-ANNOEDIZIONE. Le pagine paese di un editore multi-paese portano il codice paese nel prodotto, per esempio MORDOR-CYBERDE-2025.
A8: Valore in Mln € | B8: Formula viva. Valore originale per il fattore dell'unità diviso per il cambio BCE medio dell'anno di riferimento. Vuota per le percentuali. Per gli anni senza media annua si usa l'ultima media disponibile, evidenziata in giallo nel foglio Cambi.
A10: Definizioni
A11: Lato della stima | B11: Domanda (end user) se il numero nasce da dati raccolti presso chi acquista o usa la sicurezza. Offerta (fornitori) se nasce dai ricavi di chi vende. Misto se la fonte dichiara di combinare i due lati per quel numero, oppure se esiste solo un testo generico dell'editore (in tal caso Trasparenza C). Non determinabile se non c'è alcun elemento per classificare. La classificazione segue la costruzione del numero, non il nome che gli dà la fonte.
A12: Base della classificazione | B12: Dichiarata dalla fonte, oppure Dedotta con motivazione in una frase. Le celle dedotte sono in arancio.
A13: Approccio di calcolo | B13: Bottom-up, Top-down, Survey riportata all'universo, Modello previsionale o econometrico, Ripreso da altra fonte, Non dichiarato.
A14: Oggetto della misura | B14: Mercato domestico (acquisti di clienti nel paese), Spesa o budget delle organizzazioni, Ricavi dell'industria nazionale (incluso export), Rapporto di spesa, Budget pubblico dedicato.
A15: Tipo di valore | B15: Totale aggregato, Media per organizzazione, Mediana per organizzazione, Quota percentuale, Variazione percentuale. I valori per organizzazione, come le mediane ENISA NIS Investments, non vanno mai moltiplicati per il numero di imprese.
A16: Trasparenza | B16: A metodologia specifica per quel dato con campione o universo, perimetro e passaggi. B metodologia specifica ma sintetica. C solo testo metodologico generico dell'editore. D nessuna metodologia reperibile.
A17: Natura | B17: Consuntivo, Stima dell'anno in corso, Previsione. Un anno per riga.
A19: Codice colori
A20: Dato da fonte | B20: Testo blu su sfondo azzurro
A21: Formula | B21: Testo nero
A22: Collegamento tra fogli | B22: Testo verde, formule che leggono un altro foglio
A23: Parametro modificabile | B23: Sfondo giallo
A24: Classificazione dedotta | B24: Sfondo arancio
A26: Limiti noti
A27: Accesso alle pagine | B27: L'ambiente di esecuzione bloccava l'apertura diretta delle pagine web. Ogni valore è stato letto nell'estratto testuale della pagina o del PDF indicato in URL, restituito da un motore di ricerca che indicizza il contenuto della pagina. Le righe lette così riportano nelle Note la dicitura «Letto da estratto indicizzato della pagina». Valori letti da grafici o tabelle complesse vanno ricontrollati sul documento prima dell'uso.
A28: Report a pagamento | B28: Per i report a pagamento sono stati usati solo comunicati stampa, sintesi ed estratti gratuiti. Il tipo di accesso è registrato per ogni riga.
A29: Perimetri | B29: Fonti con numeri simili misurano perimetri diversi. Prima di confrontare due righe controllare Oggetto della misura, Clienti inclusi, Personale interno incluso, Segmenti inclusi e Lato della stima.
A30: Editori di ricerche di mercato | B30: Le pagine paese di molti editori multi-paese riportano valori senza metodologia specifica e spesso incoerenti tra editori. Sono registrate per completezza con trasparenza C o D.
A31: Cambi | B31: Medie annue dei tassi di riferimento BCE in unità di valuta per 1 euro, lette nelle serie Bundesbank «Euro foreign exchange reference rates of the ECB» e nella tabella OeNB «ECB reference rates, period average». Per gli anni senza media annua disponibile si usa l'ultima media annua, con cella gialla.
A32: Verifica finale | B32: Sono state riaperte le fonti di 565 righe, cioè tutti i totali aggregati dell'ultimo anno disponibile per area, fonte e indicatore, un campione casuale del 20% delle altre righe e le righe aggiunte dopo il campionamento. Esiti 545 confermate, 8 corrette, 10 non ritrovate o non rileggibili, 2 rimosse perché fuori perimetro. L'esito è riportato nelle Note di ogni riga verificata. Le righe non ritrovate restano nel foglio con l'indicazione di ricontrollo.
A33: Esclusioni | B33: Le spese IT complessive per organizzazione pubblicate da ENISA NIS Investments sono escluse perché prive di componente cyber. Restano le quote della spesa di sicurezza sul budget IT.
A34: Budget pubblici | B34: Per i budget pubblici la natura Consuntivo indica lo stanziamento di un anno passato, non la spesa effettiva. Alcune dotazioni pluriennali sono registrate in un solo anno, di norma quello di chiusura, con il periodo nelle Note.
A35: Statista | B35: Le pagine paese di Statista Market Insights mostrano i valori oscurati senza abbonamento. I valori Statista presenti sono letti da pagine pubbliche di Statista o da terzi che li citano, con Accesso e Fonte primaria indicati.
A36: Aggregati geografici | B36: L'Europa degli editori include di norma Regno Unito, Svizzera e Norvegia. DACH include la Svizzera, i Paesi nordici includono Norvegia e Islanda, la CEE di alcuni analisti include paesi extra UE. Il perimetro è indicato nelle Note.
A37: Copertura_Paesi | B37: Minimo e massimo in Mln € sono calcolati sui soli totali aggregati senza scomposizione, con oggetto Mercato domestico o Spesa o budget delle organizzazioni, natura Consuntivo, nell'ultimo anno di consuntivo disponibile per quei totali. Mettono a confronto perimetri diversi e servono solo a mostrare la dispersione.

Sheet Dati
A1: ID_Dato | B1: ID_Fonte | C1: Codice area | D1: Paese o area | E1: Livello geografico | F1: Ente | G1: Tipo di ente | H1: Titolo ed edizione | I1: Data di pubblicazione | J1: URL | K1: Fonte primaria | L1: Indicatore originale | M1: Descrizione | N1: Oggetto della misura | O1: Tipo di valore | P1: Scomposizione | Q1: Voce | R1: Valore originale | S1: Unità originale | T1: Valuta originale | U1: Anno di riferimento | V1: Natura | W1: Crescita dichiarata | X1: Valore in Mln € | Y1: Clienti inclusi | Z1: Personale interno incluso | AA1: Segmenti inclusi | AB1: Lato della stima | AC1: Base della classificazione | AD1: Approccio di calcolo | AE1: Metodologia in sintesi | AF1: Evidenza | AG1: Trasparenza | AH1: Accesso | AI1: Verificato su fonte primaria | AJ1: Note | AK1: Data di consultazione
A2: 1 | B2: EC-CSA2-2026 | C2: EU27 | D2: Unione europea (UE27) | E2: UE | F2: Commissione europea | G2: Istituzione UE | H2: Proposta di regolamento Cybersecurity Act 2, COM(2026) 11, scheda finanziaria (documento del Consiglio 5611/26) | I2: 20/01/2026 | J2: https://data.consilium.europa.eu/doc/document/ST-5611-2026-INIT/en/pdf | L2: ENISA yearly average budget (projection 2028-2034) | M2: Bilancio annuo medio previsto di ENISA nel periodo 2028-2034 secondo la proposta di Cybersecurity Act 2. | N2: Budget pubblico dedicato | O2: Totale aggregato | P2: Nessuna | Q2: Totale | R2: 49 | S2: milioni | T2: EUR | U2: 2028 | V2: Previsione | X2: =IF(OR($S2="%",$R2=""),"",$R2*INDEX(Cambi!$J$2:$J$5,MATCH($S2,Cambi!$I$2:$I$5,0))/IF($T2="EUR",1,INDEX(Cambi!$D:$D,MATCH($T2&"|"&$U2,Cambi!$C:$C,0)))) -> 49 | Y2: PA | Z2: Non specificato | AA2: Non specificato | AB2: Non determinabile | AC2: Dedotta. Dotazione di bilancio pubblico, non stima di mercato. | AD2: Non dichiarato | AE2: Dotazione di bilancio programmata, nessuna stima statistica. | AF2: estimated at EUR 341 million for 7 years or yearly average budget of EUR 49 million (projection for 2028 to 2034). | AG2: B | AH2: Pubblico | AI2: Sì | AJ2: Letto da estratto indicizzato della pagina. Media annua 2028-2034 registrata sul primo anno del periodo. | AK2: 08/10/2026
A3: 2 | B3: EC-CSA2-2026 | C3: EU27 | D3: Unione europea (UE27) | E3: UE | F3: Commissione europea | G3: Istituzione UE | H3: Proposta di regolamento Cybersecurity Act 2, COM(2026) 11, scheda finanziaria (documento del Consiglio 5611/26) | I3: 20/01/2026 | J3: https://data.consilium.europa.eu/doc/document/ST-5611-2026-INIT/en/pdf | L3: Estimated budget of the EU Cybersecurity Agency (ENISA), 2028-2034 | M3: Bilancio stimato di ENISA per i sette anni 2028-2034 nella proposta di Cybersecurity Act 2, pari a 49 milioni annui in media. | N3: Budget pubblico dedicato | O3: Totale aggregato | P3: Nessuna | Q3: Totale | R3: 341 | S3: milioni | T3: EUR | U3: 2034 | V3: Previsione | X3: =IF(OR($S3="%",$R3=""),"",$R3*INDEX(Cambi!$J$2:$J$5,MATCH($S3,Cambi!$I$2:$I$5,0))/IF($T3="EUR",1,INDEX(Cambi!$D:$D,MATCH($T3&"|"&$U3,Cambi!$C:$C,0)))) -> 341 | Y3: PA | Z3: Non specificato | AA3: Non specificato | AB3: Non determinabile | AC3: Dedotta. Dotazione di bilancio pubblico, non stima di mercato. | AD3: Non dichiarato | AE3: Dotazione di bilancio programmata, nessuna stima statistica. | AF3: budget of the EU Cybersecurity Agency (ENISA) ... was estimated at EUR 341 million for 7 years or yearly average budget of EUR 49 million | AG3: B | AH3: Pubblico | AI3: Sì | AJ3: Letto da estratto indicizzato della pagina. Totale settennale registrato sull'anno di chiusura. Aumento dell'81,5% rispetto al bilancio 2025. | AK3: 08/10/2026
A4: 3 | B4: EC-CYBERSOLIDARITY-2023 | C4: EU27 | D4: Unione europea (UE27) | E4: UE | F4: Commissione europea | G4: Istituzione UE | H4: Comunicato stampa IP/23/2243, Cyber Solidarity Act | I4: 18/04/2023 | J4: https://ec.europa.eu/commission/presscorner/api/files/document/print/en/ip_23_2243/IP_23_2243_EN.pdf | L4: Total budget for all actions under the EU Cyber Solidarity Act | M4: Bilancio complessivo delle azioni del Cyber Solidarity Act, finanziato per circa due terzi dal programma Europa digitale. | N4: Budget pubblico dedicato | O4: Totale aggregato | P4: Nessuna | Q4: Totale | R4: 1.1 | S4: miliardi | T4: EUR | U4: 2027 | V4: Previsione | X4: =IF(OR($S4="%",$R4=""),"",$R4*INDEX(Cambi!$J$2:$J$5,MATCH($S4,Cambi!$I$2:$I$5,0))/IF($T4="EUR",1,INDEX(Cambi!$D:$D,MATCH($T4&"|"&$U4,Cambi!$C:$C,0)))) -> 1100 | Y4: Imprese e PA | Z4: Non specificato | AA4: Non specificato | AB4: Non determinabile | AC4: Dedotta. Dotazione di bilancio pubblico, non stima di mercato. | AD4: Non dichiarato | AE4: Dotazione di bilancio programmata, nessuna stima statistica. | AF4: total budget for all actions under the EU Cyber Solidarity Act is of EUR 1.1 billion, of which about 2/3 | AG4: B | AH4: Pubblico | AI4: Sì | AJ4: Letto da estratto indicizzato della pagina. Include contributi degli Stati membri. Periodo fino al 2027 dedotto dal quadro finanziario pluriennale. | AK4: 08/10/2026
A5: 4 | B5: EC-DEPBROCHURE-2019 | C5: EU27 | D5: Unione europea (UE27) | E5: UE | F5: Commissione europea | G5: Istituzione UE | H5: Digital Europe for a more competitive, autonomous and sustainable Europe, brochure | I5: 23/09/2019 | J5: https://digital-strategy.ec.europa.eu/en/library/digital-europe-more-competitive-autonomous-and-sustainable-europe-brochure | L5: Digital Europe programme budget 2021-2027, Cybersecurity | M5: Quota cybersecurity della dotazione proposta del programma Europa digitale 2021-2027 pari a 7,58 miliardi. | N5: Budget pubblico dedicato | O5: Totale aggregato | P5: Nessuna | Q5: Totale | R5: 1.6 | S5: miliardi | T5: EUR | U5: 2027 | V5: Previsione | X5: =IF(OR($S5="%",$R5=""),"",$R5*INDEX(Cambi!$J$2:$J$5,MATCH($S5,Cambi!$I$2:$I$5,0))/IF($T5="EUR",1,INDEX(Cambi!$D:$D,MATCH($T5&"|"&$U5,Cambi!$C:$C,0)))) -> 1600 | Y5: Imprese e PA | Z5: Non specificato | AA5: Non specificato | AB5: Non determinabile | AC5: Dedotta. Dotazione di bilancio pubblico, non stima di mercato. | AD5: Non dichiarato | AE5: Dotazione di bilancio programmata, nessuna stima statistica. | AF5: €7.58 billion for High Performance Computing (€2.2 billion) Artificial Intelligence (€2 billion) Cybersecurity (€1.6 billion) | AG5: B | AH5: Pubblico | AI5: Sì | AJ5: Letto da estratto indicizzato della pagina. Dotazione proposta 2021-2027, registrata sull'anno di chiusura del periodo. Verifica finale 08/10/2026, valore confermato sulla fonte. Dotazione proposta nel 2019 per il periodo 2021-2027 confermata. | AK5: 08/10/2026
A6: 5 | B6: EC-DEPCYBER-2026 | C6: EU27 | D6: Unione europea (UE27) | E6: UE | F6: Commissione europea | G6: Istituzione UE | H6: EU cybersecurity policies, pagina Shaping Europe's digital future | I6: 30/09/2026 | J6: https://digital-strategy.ec.europa.eu/en/policies/cybersecurity-policies | L6: Digital Europe Programme investment into cybersecurity capacity | M6: Dotazione del programma Europa digitale 2021-2027 per capacità e infrastrutture di cybersecurity per PA, imprese e cittadini. | N6: Budget pubblico dedicato | O6: Totale aggregato | P6: Nessuna | Q6: Totale | R6: 1.9 | S6: miliardi | T6: EUR | U6: 2027 | V6: Previsione | X6: =IF(OR($S6="%",$R6=""),"",$R6*INDEX(Cambi!$J$2:$J$5,MATCH($S6,Cambi!$I$2:$I$5,0))/IF($T6="EUR",1,INDEX(Cambi!$D:$D,MATCH($T6&"|"&$U6,Cambi!$C:$C,0)))) -> 1900 | Y6: Imprese e PA | Z6: Non specificato | AA6: Non specificato | AB6: Non determinabile | AC6: Dedotta. Dotazione di bilancio pubblico, non stima di mercato. | AD6: Non dichiarato | AE6: Dotazione di bilancio programmata, nessuna stima statistica. | AF6: plans to invest €1.9 billion into cybersecurity capacity and the wide deployment of cybersecurity infrastructures and tools across the EU | AG6: B | AH6: Pubblico | AI6: Sì | AJ6: Letto da estratto indicizzato della pagina. Dotazione pluriennale 2021-2027, registrata sull'anno di chiusura del periodo. Valore diverso da 1,6 miliardi della proposta 2019 e da 2 miliardi della proposta 2018. | AK6: 08/10/2026
A7: 6 | B7: EC-DEPNEWS-2025 | C7: EU27 | D7: Unione europea (UE27) | E7: UE | F7: Commissione europea | G7: Istituzione UE | H7: Digital Europe Programme fuels digital transformation and skills development across Europe | I7: 18/12/2025 | J7: https://digital-strategy.ec.europa.eu/en/news/digital-europe-programme-fuels-digital-transformation-and-skills-development-across-europe | L7: DIGITAL funding for Security Operations Centres (Cyber Hubs) 2021-2024 | M7: Fondi del programma Europa digitale destinati tra 2021 e 2024 alla creazione e gestione di centri operativi di sicurezza (Cyber Hubs). | N7: Budget pubblico dedicato | O7: Totale aggregato | P7: Segmento di offerta | Q7: Centri operativi di sicurezza (SOC) | R7: 194 | S7: milioni | T7: EUR | U7: 2024 | V7: Consuntivo | X7: =IF(OR($S7="%",$R7=""),"",$R7*INDEX(Cambi!$J$2:$J$5,MATCH($S7,Cambi!$I$2:$I$5,0))/IF($T7="EUR",1,INDEX(Cambi!$D:$D,MATCH($T7&"|"&$U7,Cambi!$C:$C,0)))) -> 194 | Y7: Imprese e PA | Z7: Non specificato | AA7: Non specificato | AB7: Non determinabile | AC7: Dedotta. Dotazione di bilancio pubblico, non stima di mercato. | AD7: Non dichiarato | AE7: Dotazione di bilancio programmata, nessuna stima statistica. | AF7: Between 2021 and 2024 over €194 million was dedicated towards the creation and operation of Security Operations Centres | AG7: B | AH7: Pubblico | AI7: Sì | AJ7: Letto da estratto indicizzato della pagina. Cumulato 2021-2024, pubblicato come oltre 194 milioni. | AK7: 08/10/2026
A8: 7 | B8: EC-DIGITALDECADE-2024 | C8: EU27 | D8: Unione europea (UE27) | E8: UE | F8: Commissione europea | G8: Istituzione UE | H8: State of the Digital Decade 2024, COM(2024) 260 (copia IPEX) | I8: 02/07/2024 | J8: https://secure.ipex.eu/IPEXL-WEB/download/file/082d29089070f71e019072c2e24e0036 | L8: National roadmaps measures addressing cybersecurity, public budget | M8: Bilancio pubblico delle misure delle prime roadmap nazionali del Decennio digitale riferite all'obiettivo cybersecurity. | N8: Budget pubblico dedicato | O8: Totale aggregato | P8: Nessuna | Q8: Totale | R8: 5.9 | S8: miliardi | T8: EUR | U8: 2024 | V8: Previsione | X8: =IF(OR($S8="%",$R8=""),"",$R8*INDEX(Cambi!$J$2:$J$5,MATCH($S8,Cambi!$I$2:$I$5,0))/IF($T8="EUR",1,INDEX(Cambi!$D:$D,MATCH($T8&"|"&$U8,Cambi!$C:$C,0)))) -> 5900 | Y8: Imprese e PA | Z8: Non specificato | AA8: Non specificato | AB8: Non determinabile | AC8: Dedotta. Dotazione di bilancio pubblico, non stima di mercato. | AD8: Bottom-up | AE8: Somma del bilancio pubblico delle misure delle roadmap nazionali riferite all'obiettivo generale cybersecurity. | AF8: they still encompass 414 measures addressing competitiveness (public budget EUR 56.8 billion), technological leadership (EUR 22.3 billion), and cybersecurity (EUR 5.9 billion). | AG8: B | AH8: Pubblico | AI8: Sì | AJ8: Letto da estratto indicizzato della pagina. Periodo di spesa non specificato, registrato sull'anno della relazione. Diverso dal valore 2025 (0,8 miliardi solo per misure esclusivamente cyber) per perimetro delle misure. | AK8: 08/10/2026
A9: 8 | B9: EC-DIGITALDECADE-2025 | C9: EU27 | D9: Unione europea (UE27) | E9: UE | F9: Commissione europea | G9: Istituzione UE | H9: State of the Digital Decade 2025, allegato COM(2025) 290 | I9: 16/06/2025 | J9: https://www.europarl.europa.eu/RegData/docs_autres_institutions/commission_europeenne/com/2025/0290/COM_COM(2025)0290(ANN)_EN.pdf | L9: National Roadmaps measures dedicated exclusively to cybersecurity, total budget | M9: Bilancio complessivo delle misure delle roadmap nazionali del Decennio digitale dedicate esclusivamente alla cybersecurity. | N9: Budget pubblico dedicato | O9: Totale aggregato | P9: Nessuna | Q9: Totale | R9: 0.8 | S9: miliardi | T9: EUR | U9: 2025 | V9: Previsione | X9: =IF(OR($S9="%",$R9=""),"",$R9*INDEX(Cambi!$J$2:$J$5,MATCH($S9,Cambi!$I$2:$I$5,0))/IF($T9="EUR",1,INDEX(Cambi!$D:$D,MATCH($T9&"|"&$U9,Cambi!$C:$C,0)))) -> 800 | Y9: Imprese e PA | Z9: Non specificato | AA9: Non specificato | AB9: Non determinabile | AC9: Dedotta. Dotazione di bilancio pubblico, non stima di mercato. | AD9: Non dichiarato | AE9: Somma dei bilanci delle misure cyber dichiarate dagli Stati membri nelle roadmap nazionali del Decennio digitale. | AF9: Almost half of these measures are dedicated exclusively to cybersecurity, with a total budget of EUR 0.8 billion. | AG9: B | AH9: Pubblico | AI9: Sì | AJ9: Letto da estratto indicizzato della pagina. Le altre misure a portata più ampia valgono 6 miliardi. Periodo di spesa non specificato, registrato sull'anno della relazione. | AK9: 08/10/2026
A10: 9 | B10: EC-HEWP-2025 | C10: EU27 | D10: Unione europea (UE27) | E10: UE | F10: Commissione europea | G10: Istituzione UE | H10: Horizon Europe Work Programme 2025, 6. Civil Security for Society | I10: 2025 | J10: https://ec.europa.eu/info/funding-tenders/opportunities/docs/2021-2027/horizon/wp-call/2025/wp-6-civil-security-for-society_horizon-2025_en.pdf | L10: Indirectly managed action by the ECCC, Increased Cybersecurity call, indicative budget | M10: Bilancio indicativo 2025 del bando Horizon Europe Increased Cybersecurity gestito dall'ECCC. | N10: Budget pubblico dedicato | O10: Totale aggregato | P10: Segmento di offerta | Q10: Ricerca e innovazione (Horizon Europe) | R10: 90.55 | S10: milioni | T10: EUR | U10: 2025 | V10: Previsione | X10: =IF(OR($S10="%",$R10=""),"",$R10*INDEX(Cambi!$J$2:$J$5,MATCH($S10,Cambi!$I$2:$I$5,0))/IF($T10="EUR",1,INDEX(Cambi!$D:$D,MATCH($T10&"|"&$U10,Cambi!$C:$C,0)))) -> 90.55 | Y10: Imprese e PA | Z10: Non specificato | AA10: Non specificato | AB10: Non determinabile | AC10: Dedotta. Dotazione di bilancio pubblico, non stima di mercato. | AD10: Non dichiarato | AE10: Dotazione di bilancio programmata, nessuna stima statistica. | AF10: Indicative budget: EUR 90.55 million from the 2025 budget APPENDIX - Indirectly managed action by the ECCC | AG10: B | AH10: Pubblico | AI10: Sì | AJ10: Letto da estratto indicizzato della pagina. Solo il bando cyber ECCC del 2025, non l'intero impegno Horizon Europe sulla cybersecurity. | AK10: 08/10/2026
A11: 10 | B11: EC-IANIS2-2020 | C11: EU27 | D11: Unione europea (UE27) | E11: UE | F11: Commissione europea | G11: Istituzione UE | H11: SWD(2020) 345 final, Impact assessment report revisione direttiva NIS (allegati) | I11: 16/12/2020 | J11: https://www.eerstekamer.nl/bijlage/20210114/swd_2020_345_impact_assessment_7/document3/f=/vlfghch5jfhz.pdf | K11: Gartner, previsioni 2012-2020 sulla quota di spesa di sicurezza ICT e dati settoriali, citate dalla Commissione | L11: Average ICT security spending of the total turnover per sector | M11: Ipotesi della Commissione sulla spesa media di sicurezza ICT dei settori NIS nel 2020 in rapporto al fatturato. | N11: Rapporto di spesa | O11: Quota percentuale | P11: Nessuna | Q11: Totale | R11: 0.52 | S11: % | U11: 2020 | V11: Stima dell'anno in corso | X11: =IF(OR($S11="%",$R11=""),"",$R11*INDEX(Cambi!$J$2:$J$5,MATCH($S11,Cambi!$I$2:$I$5,0))/IF($T11="EUR",1,INDEX(Cambi!$D:$D,MATCH($T11&"|"&$U11,Cambi!$C:$C,0)))) | Y11: Imprese e PA | Z11: Non specificato | AA11: Spesa di sicurezza ICT (perimetro Gartner) | AB11: Non determinabile | AC11: Dedotta. Ipotesi della Commissione costruita su rapporti Gartner globali, non su dati di acquirenti o fornitori UE. | AD11: Modello previsionale o econometrico | AE11: Ipotesi di lavoro della valutazione d'impatto basata su previsioni Gartner 2012-2020 della spesa di sicurezza ICT in rapporto alla spesa ICT e al fatturato, aggiustabile di più o meno 3 punti per settore, applicata al fatturato dei settori NIS. | AF11: the average ICT security spending of the total turnover per sector in 2020 is estimated to approx. 0.52%. | AG11: B | AH11: Pubblico | AI11: Sì | AJ11: Letto da estratto indicizzato della pagina. Prodotto di 9,14% di spesa ICT e 5,69% di spesa ICT sul fatturato. Rapporto direttamente confrontabile con modelli basati sul fatturato SBS. Verifica finale 08/10/2026, valore confermato sulla fonte. Valore e anno coincidono nella valutazione d'impatto NIS2. | AK11: 08/10/2026
A12: 11 | B12: EC-IANIS2-2020 | C12: EU27 | D12: Unione europea (UE27) | E12: UE | F12: Commissione europea | G12: Istituzione UE | H12: SWD(2020) 345 final, Impact assessment report revisione direttiva NIS (allegati) | I12: 16/12/2020 | J12: https://www.eerstekamer.nl/bijlage/20210114/swd_2020_345_impact_assessment_7/document3/f=/vlfghch5jfhz.pdf | K12: Gartner, previsioni 2012-2020 sulla quota di spesa di sicurezza ICT e dati settoriali, citate dalla Commissione | L12: Average ICT security spending per sector, % of ICT spending | M12: Ipotesi della Commissione sulla spesa media di sicurezza ICT dei settori NIS nel 2020 in rapporto alla spesa ICT. | N12: Rapporto di spesa | O12: Quota percentuale | P12: Nessuna | Q12: Totale | R12: 9.14 | S12: % | U12: 2020 | V12: Stima dell'anno in corso | X12: =IF(OR($S12="%",$R12=""),"",$R12*INDEX(Cambi!$J$2:$J$5,MATCH($S12,Cambi!$I$2:$I$5,0))/IF($T12="EUR",1,INDEX(Cambi!$D:$D,MATCH($T12&"|"&$U12,Cambi!$C:$C,0)))) | Y12: Imprese e PA | Z12: Non specificato | AA12: Spesa di sicurezza ICT (perimetro Gartner) | AB12: Non determinabile | AC12: Dedotta. Ipotesi della Commissione costruita su rapporti Gartner globali, non su dati di acquirenti o fornitori UE. | AD12: Modello previsionale o econometrico | AE12: Ipotesi di lavoro della valutazione d'impatto basata su previsioni Gartner 2012-2020 della spesa di sicurezza ICT in rapporto alla spesa ICT e al fatturato, aggiustabile di più o meno 3 punti per settore, applicata al fatturato dei settori NIS. | AF12: the average ICT security spending per sector in 2020 is of approx. 9.14% of the ICT spending. | AG12: B | AH12: Pubblico | AI12: Sì | AJ12: Letto da estratto indicizzato della pagina. Ipotesi derivata da dati Gartner globali, non da misura UE. Documento ufficiale ospitato dal Senato dei Paesi Bassi. | AK12: 08/10/2026
A13: 12 | B13: EC-IANIS2-2020 | C13: EU27 | D13: Unione europea (UE27) | E13: UE | F13: Commissione europea | G13: Istituzione UE | H13: SWD(2020) 345 final, Impact assessment report revisione direttiva NIS (allegati) | I13: 16/12/2020 | J13: https://www.eerstekamer.nl/bijlage/20210114/swd_2020_345_impact_assessment_5/document3/f=/vlfghbk7smnk.pdf | K13: Gartner, previsioni 2012-2020 sulla quota di spesa di sicurezza ICT e dati settoriali, citate dalla Commissione | L13: Average increase in ICT security spending for sectors currently under NIS scope | M13: Aumento medio previsto della spesa di sicurezza ICT per i settori già coperti dalla direttiva NIS nei tre o quattro anni successivi. | N13: Spesa o budget delle organizzazioni | O13: Variazione percentuale | P13: Settore | Q13: Settori già NIS | R13: 12 | S13: % | U13: 2025 | V13: Previsione | X13: =IF(OR($S13="%",$R13=""),"",$R13*INDEX(Cambi!$J$2:$J$5,MATCH($S13,Cambi!$I$2:$I$5,0))/IF($T13="EUR",1,INDEX(Cambi!$D:$D,MATCH($T13&"|"&$U13,Cambi!$C:$C,0)))) | Y13: Imprese e PA | Z13: Non specificato | AA13: Spesa di sicurezza ICT (perimetro Gartner) | AB13: Non determinabile | AC13: Dedotta. Ipotesi della Commissione costruita su rapporti Gartner globali, non su dati di acquirenti o fornitori UE. | AD13: Modello previsionale o econometrico | AE13: Ipotesi di lavoro della valutazione d'impatto basata su previsioni Gartner 2012-2020 della spesa di sicurezza ICT in rapporto alla spesa ICT e al fatturato, aggiustabile di più o meno 3 punti per settore, applicata al fatturato dei settori NIS. | AF13: average 12% increase in ICT security spending is estimated for the sectors/services currently under the scope of the NIS Directive | AG13: B | AH13: Pubblico | AI13: Sì | AJ13: Letto da estratto indicizzato della pagina. Variazione cumulata sull'orizzonte, non annua. | AK13: 08/10/2026
A14: 13 | B14: EC-IANIS2-2020 | C14: EU27 | D14: Unione europea (UE27) | E14: UE | F14: Commissione europea | G14: Istituzione UE | H14: SWD(2020) 345 final, Impact assessment report revisione direttiva NIS (allegati) | I14: 16/12/2020 | J14: https://www.eerstekamer.nl/bijlage/20210114/swd_2020_345_impact_assessment_5/document3/f=/vlfghbk7smnk.pdf | K14: Gartner, previsioni 2012-2020 sulla quota di spesa di sicurezza ICT e dati settoriali, citate dalla Commissione | L14: Average increase in ICT security spending for the new sectors/services added to the NIS scope | M14: Aumento medio previsto della spesa di sicurezza ICT per i nuovi settori NIS2 nei tre o quattro anni successivi. | N14: Spesa o budget delle organizzazioni | O14: Variazione percentuale | P14: Settore | Q14: Nuovi settori NIS2 | R14: 22 | S14: % | U14: 2025 | V14: Previsione | X14: =IF(OR($S14="%",$R14=""),"",$R14*INDEX(Cambi!$J$2:$J$5,MATCH($S14,Cambi!$I$2:$I$5,0))/IF($T14="EUR",1,INDEX(Cambi!$D:$D,MATCH($T14&"|"&$U14,Cambi!$C:$C,0)))) | Y14: Imprese e PA | Z14: Non specificato | AA14: Spesa di sicurezza ICT (perimetro Gartner) | AB14: Non determinabile | AC14: Dedotta. Ipotesi della Commissione costruita su rapporti Gartner globali, non su dati di acquirenti o fornitori UE. | AD14: Modello previsionale o econometrico | AE14: Ipotesi di lavoro della valutazione d'impatto basata su previsioni Gartner 2012-2020 della spesa di sicurezza ICT in rapporto alla spesa ICT e al fatturato, aggiustabile di più o meno 3 punti per settore, applicata al fatturato dei settori NIS. | AF14: Average 22% increase in ICT security spending for the new sectors/services added to the NIS scope in the next 3-4 years. | AG14: B | AH14: Pubblico | AI14: Sì | AJ14: Letto da estratto indicizzato della pagina. Variazione cumulata sull'orizzonte, non annua. | AK14: 08/10/2026
A15: 14 | B15: EC-IANIS2-2020 | C15: EU27 | D15: Unione europea (UE27) | E15: UE | F15: Commissione europea | G15: Istituzione UE | H15: SWD(2020) 345 final, Impact assessment report revisione direttiva NIS (allegati) | I15: 16/12/2020 | J15: https://www.eerstekamer.nl/bijlage/20210114/swd_2020_345_impact_assessment_7/document3/f=/vlfghch5jfhz.pdf | K15: Gartner, previsioni 2012-2020 sulla quota di spesa di sicurezza ICT e dati settoriali, citate dalla Commissione | L15: ICT security spending in average per sector, % of ICT spending, after revised NIS Directive (current sectors) | M15: Quota prevista della spesa di sicurezza ICT sulla spesa ICT per i settori già NIS, tre o quattro anni dopo l'entrata in vigore della NIS2. | N15: Rapporto di spesa | O15: Quota percentuale | P15: Nessuna | Q15: Totale | R15: 11 | S15: % | U15: 2025 | V15: Previsione | X15: =IF(OR($S15="%",$R15=""),"",$R15*INDEX(Cambi!$J$2:$J$5,MATCH($S15,Cambi!$I$2:$I$5,0))/IF($T15="EUR",1,INDEX(Cambi!$D:$D,MATCH($T15&"|"&$U15,Cambi!$C:$C,0)))) | Y15: Imprese e PA | Z15: Non specificato | AA15: Spesa di sicurezza ICT (perimetro Gartner) | AB15: Non determinabile | AC15: Dedotta. Ipotesi della Commissione costruita su rapporti Gartner globali, non su dati di acquirenti o fornitori UE. | AD15: Modello previsionale o econometrico | AE15: Ipotesi di lavoro della valutazione d'impatto basata su previsioni Gartner 2012-2020 della spesa di sicurezza ICT in rapporto alla spesa ICT e al fatturato, aggiustabile di più o meno 3 punti per settore, applicata al fatturato dei settori NIS. | AF15: ICT security spending in average per sector reaching about 11% of the ICT spending and 0.63% of the total turnover in three to four years | AG15: B | AH15: Pubblico | AI15: Sì | AJ15: Letto da estratto indicizzato della pagina. Orizzonte dichiarato tre o quattro anni dall'entrata in vigore, anno 2025 dedotto e approssimativo. | AK15: 08/10/2026
A16: 15 | B16: EC-IANIS2-2020 | C16: EU27 | D16: Unione europea (UE27) | E16: UE | F16: Commissione europea | G16: Istituzione UE | H16: SWD(2020) 345 final, Impact assessment report revisione direttiva NIS (allegati) | I16: 16/12/2020 | J16: https://www.eerstekamer.nl/bijlage/20210114/swd_2020_345_impact_assessment_7/document3/f=/vlfghch5jfhz.pdf | K16: Gartner, previsioni 2012-2020 sulla quota di spesa di sicurezza ICT e dati settoriali, citate dalla Commissione | L16: ICT security spending in average per sector, % of total turnover, after revised NIS Directive (current sectors) | M16: Quota prevista della spesa di sicurezza ICT sul fatturato per i settori già NIS, tre o quattro anni dopo l'entrata in vigore della NIS2. | N16: Rapporto di spesa | O16: Quota percentuale | P16: Nessuna | Q16: Totale | R16: 0.63 | S16: % | U16: 2025 | V16: Previsione | X16: =IF(OR($S16="%",$R16=""),"",$R16*INDEX(Cambi!$J$2:$J$5,MATCH($S16,Cambi!$I$2:$I$5,0))/IF($T16="EUR",1,INDEX(Cambi!$D:$D,MATCH($T16&"|"&$U16,Cambi!$C:$C,0)))) | Y16: Imprese e PA | Z16: Non specificato | AA16: Spesa di sicurezza ICT (perimetro Gartner) | AB16: Non determinabile | AC16: Dedotta. Ipotesi della Commissione costruita su rapporti Gartner globali, non su dati di acquirenti o fornitori UE. | AD16: Modello previsionale o econometrico | AE16: Ipotesi di lavoro della valutazione d'impatto basata su previsioni Gartner 2012-2020 della spesa di sicurezza ICT in rapporto alla spesa ICT e al fatturato, aggiustabile di più o meno 3 punti per settore, applicata al fatturato dei settori NIS. | AF16: ICT security spending in average per sector reaching about 11% of the ICT spending and 0.63% of the total turnover in three to four years | AG16: B | AH16: Pubblico | AI16: Sì | AJ16: Letto da estratto indicizzato della pagina. Anno 2025 dedotto e approssimativo. | AK16: 08/10/2026
A17: 16 | B17: EC-IANIS2-2020 | C17: EU27 | D17: Unione europea (UE27) | E17: UE | F17: Commissione europea | G17: Istituzione UE | H17: SWD(2020) 345 final, Impact assessment report revisione direttiva NIS (allegati) | I17: 16/12/2020 | J17: https://www.eerstekamer.nl/bijlage/20210114/swd_2020_345_impact_assessment_7/document3/f=/vlfghch5jfhz.pdf | K17: Gartner, previsioni 2012-2020 sulla quota di spesa di sicurezza ICT e dati settoriali, citate dalla Commissione | L17: ICT security spending in average per sector, new sectors, % of ICT spending | M17: Quota prevista della spesa di sicurezza ICT sulla spesa ICT per i nuovi settori NIS2, tre o quattro anni dopo l'entrata in vigore. | N17: Rapporto di spesa | O17: Quota percentuale | P17: Settore | Q17: Nuovi settori NIS2 | R17: 11.4 | S17: % | U17: 2025 | V17: Previsione | X17: =IF(OR($S17="%",$R17=""),"",$R17*INDEX(Cambi!$J$2:$J$5,MATCH($S17,Cambi!$I$2:$I$5,0))/IF($T17="EUR",1,INDEX(Cambi!$D:$D,MATCH($T17&"|"&$U17,Cambi!$C:$C,0)))) | Y17: Imprese e PA | Z17: Non specificato | AA17: Spesa di sicurezza ICT (perimetro Gartner) | AB17: Non determinabile | AC17: Dedotta. Ipotesi della Commissione costruita su rapporti Gartner globali, non su dati di acquirenti o fornitori UE. | AD17: Modello previsionale o econometrico | AE17: Ipotesi di lavoro della valutazione d'impatto basata su previsioni Gartner 2012-2020 della spesa di sicurezza ICT in rapporto alla spesa ICT e al fatturato, aggiustabile di più o meno 3 punti per settore, applicata al fatturato dei settori NIS. | AF17: For the new sectors, this would translate into ICT security spending in average per sector reaching about 11.4% of the ICT spending and 0.65% | AG17: B | AH17: Pubblico | AI17: Sì | AJ17: Letto da estratto indicizzato della pagina. Anno 2025 dedotto e approssimativo. Verifica finale 08/10/2026, valore confermato sulla fonte. Quota prevista a tre o quattro anni dalla direttiva rivista, coerente con la riga. | AK17: 08/10/2026
A18: 17 | B18: EC-IANIS2-2020 | C18: EU27 | D18: Unione europea (UE27) | E18: UE | F18: Commissione europea | G18: Istituzione UE | H18: SWD(2020) 345 final, Impact assessment report revisione direttiva NIS (allegati) | I18: 16/12/2020 | J18: https://www.eerstekamer.nl/bijlage/20210114/swd_2020_345_impact_assessment_7/document3/f=/vlfghch5jfhz.pdf | K18: Gartner, previsioni 2012-2020 sulla quota di spesa di sicurezza ICT e dati settoriali, citate dalla Commissione | L18: ICT security spending in average per sector, new sectors, % of total turnover | M18: Quota prevista della spesa di sicurezza ICT sul fatturato per i nuovi settori NIS2, tre o quattro anni dopo l'entrata in vigore. | N18: Rapporto di spesa | O18: Quota percentuale | P18: Settore | Q18: Nuovi settori NIS2 | R18: 0.65 | S18: % | U18: 2025 | V18: Previsione | X18: =IF(OR($S18="%",$R18=""),"",$R18*INDEX(Cambi!$J$2:$J$5,MATCH($S18,Cambi!$I$2:$I$5,0))/IF($T18="EUR",1,INDEX(Cambi!$D:$D,MATCH($T18&"|"&$U18,Cambi!$C:$C,0)))) | Y18: Imprese e PA | Z18: Non specificato | AA18: Spesa di sicurezza ICT (perimetro Gartner) | AB18: Non determinabile | AC18: Dedotta. Ipotesi della Commissione costruita su rapporti Gartner globali, non su dati di acquirenti o fornitori UE. | AD18: Modello previsionale o econometrico | AE18: Ipotesi di lavoro della valutazione d'impatto basata su previsioni Gartner 2012-2020 della spesa di sicurezza ICT in rapporto alla spesa ICT e al fatturato, aggiustabile di più o meno 3 punti per settore, applicata al fatturato dei settori NIS. | AF18: reaching about 11.4% of the ICT spending and 0.65% of the total turnover in three to four years | AG18: B | AH18: Pubblico | AI18: Sì | AJ18: Letto da estratto indicizzato della pagina. Anno 2025 dedotto e approssimativo. | AK18: 08/10/2026
A19: 18 | B19: EC-IANIS2-2020 | C19: EU27 | D19: Unione europea (UE27) | E19: UE | F19: Commissione europea | G19: Istituzione UE | H19: SWD(2020) 345 final, Impact assessment report revisione direttiva NIS (allegati) | I19: 16/12/2020 | J19: https://www.eerstekamer.nl/bijlage/20210114/swd_2020_345_impact_assessment_7/document3/f=/vlfghch5jfhz.pdf | K19: Gartner, previsioni 2012-2020 sulla quota di spesa di sicurezza ICT e dati settoriali, citate dalla Commissione | L19: Increase of ICT security spending per sector, Air transport | M19: Aumento complessivo previsto della spesa di sicurezza ICT nel trasporto aereo UE per effetto della NIS2. | N19: Spesa o budget delle organizzazioni | O19: Totale aggregato | P19: Settore | Q19: Trasporto aereo | R19: 0.27 | S19: miliardi | T19: EUR | U19: 2025 | V19: Previsione | X19: =IF(OR($S19="%",$R19=""),"",$R19*INDEX(Cambi!$J$2:$J$5,MATCH($S19,Cambi!$I$2:$I$5,0))/IF($T19="EUR",1,INDEX(Cambi!$D:$D,MATCH($T19&"|"&$U19,Cambi!$C:$C,0)))) -> 270 | Y19: Imprese | Z19: Non specificato | AA19: Spesa di sicurezza ICT (perimetro Gartner) | AB19: Non determinabile | AC19: Dedotta. Ipotesi della Commissione costruita su rapporti Gartner globali, non su dati di acquirenti o fornitori UE. | AD19: Modello previsionale o econometrico | AE19: Ipotesi di lavoro della valutazione d'impatto basata su previsioni Gartner 2012-2020 della spesa di sicurezza ICT in rapporto alla spesa ICT e al fatturato, aggiustabile di più o meno 3 punti per settore, applicata al fatturato dei settori NIS. | AF19: Air transport: an increase of EUR 0.27 billion per sector and EUR 1.18 million | AG19: B | AH19: Pubblico | AI19: Sì | AJ19: Letto da estratto indicizzato della pagina. Incremento di spesa, non livello. Verifica finale 08/10/2026, valore confermato sulla fonte. Incremento stimato per il trasporto aereo confermato. | AK19: 08/10/2026
A20: 19 | B20: EC-IANIS2-2020 | C20: EU27 | D20: Unione europea (UE27) | E20: UE | F20: Commissione europea | G20: Istituzione UE | H20: SWD(2020) 345 final, Impact assessment report revisione direttiva NIS (allegati) | I20: 16/12/2020 | J20: https://www.eerstekamer.nl/bijlage/20210114/swd_2020_345_impact_assessment_7/document3/f=/vlfghch5jfhz.pdf | K20: Gartner, previsioni 2012-2020 sulla quota di spesa di sicurezza ICT e dati settoriali, citate dalla Commissione | L20: Total increase of ICT security spending per company, Electricity and gas | M20: Aumento previsto della spesa di sicurezza ICT per impresa del settore elettricità e gas per effetto della NIS2. | N20: Spesa o budget delle organizzazioni | O20: Media per organizzazione | P20: Settore | Q20: Elettricità e gas | R20: 1.94 | S20: milioni | T20: EUR | U20: 2025 | V20: Previsione | X20: =IF(OR($S20="%",$R20=""),"",$R20*INDEX(Cambi!$J$2:$J$5,MATCH($S20,Cambi!$I$2:$I$5,0))/IF($T20="EUR",1,INDEX(Cambi!$D:$D,MATCH($T20&"|"&$U20,Cambi!$C:$C,0)))) -> 1.94 | Y20: Imprese | Z20: Non specificato | AA20: Spesa di sicurezza ICT (perimetro Gartner) | AB20: Non determinabile | AC20: Dedotta. Ipotesi della Commissione costruita su rapporti Gartner globali, non su dati di acquirenti o fornitori UE. | AD20: Modello previsionale o econometrico | AE20: Ipotesi di lavoro della valutazione d'impatto basata su previsioni Gartner 2012-2020 della spesa di sicurezza ICT in rapporto alla spesa ICT e al fatturato, aggiustabile di più o meno 3 punti per settore, applicata al fatturato dei settori NIS. | AF20: Electricity and gas: a total increase of EUR 6 billion per sector and EUR 1.94 million per company. | AG20: B | AH20: Pubblico | AI20: Sì | AJ20: Letto da estratto indicizzato della pagina. Incremento medio per impresa, non livello. | AK20: 08/10/2026
A21: 20 | B21: EC-IANIS2-2020 | C21: EU27 | D21: Unione europea (UE27) | E21: UE | F21: Commissione europea | G21: Istituzione UE | H21: SWD(2020) 345 final, Impact assessment report revisione direttiva NIS (allegati) | I21: 16/12/2020 | J21: https://www.eerstekamer.nl/bijlage/20210114/swd_2020_345_impact_assessment_7/document3/f=/vlfghch5jfhz.pdf | K21: Gartner, previsioni 2012-2020 sulla quota di spesa di sicurezza ICT e dati settoriali, citate dalla Commissione | L21: Total increase of ICT security spending per sector, Electricity and gas | M21: Aumento complessivo previsto della spesa di sicurezza ICT nel settore elettricità e gas UE per effetto della NIS2 in tre o quattro anni. | N21: Spesa o budget delle organizzazioni | O21: Totale aggregato | P21: Settore | Q21: Elettricità e gas | R21: 6 | S21: miliardi | T21: EUR | U21: 2025 | V21: Previsione | X21: =IF(OR($S21="%",$R21=""),"",$R21*INDEX(Cambi!$J$2:$J$5,MATCH($S21,Cambi!$I$2:$I$5,0))/IF($T21="EUR",1,INDEX(Cambi!$D:$D,MATCH($T21&"|"&$U21,Cambi!$C:$C,0)))) -> 6000 | Y21: Imprese | Z21: Non specificato | AA21: Spesa di sicurezza ICT (perimetro Gartner) | AB21: Non determinabile | AC21: Dedotta. Ipotesi della Commissione costruita su rapporti Gartner globali, non su dati di acquirenti o fornitori UE. | AD21: Modello previsionale o econometrico | AE21: Ipotesi di lavoro della valutazione d'impatto basata su previsioni Gartner 2012-2020 della spesa di sicurezza ICT in rapporto alla spesa ICT e al fatturato, aggiustabile di più o meno 3 punti per settore, applicata al fatturato dei settori NIS. | AF21: Electricity and gas: a total increase of EUR 6 billion per sector and EUR 1.94 million per company. | AG21: B | AH21: Pubblico | AI21: Sì | AJ21: Letto da estratto indicizzato della pagina. Incremento di spesa, non livello. Anno 2025 dedotto dall'orizzonte di tre o quattro anni. | AK21: 08/10/2026
A22: 21 | B22: TECHNOPOLIS-DIGCAP-2026 | C22: EU27 | D22: Unione europea (UE27) | E22: UE | F22: Commissione europea (studio di Technopolis Group) | G22: Istituzione UE | H22: Study on the EU's critical digital capacities deployment beyond 2027, Annex 7 Technology Area Report Cybersecurity and digital identity technologies | I22: 22/06/2026 | J22: https://op.europa.eu/o/opportal-service/download-handler?identifier=fa9b11af-6d4a-11f1-ae88-01aa75ed71a1&format=PDF&language=en&productionSystem=cellar | L22: Contribution of DIGITAL and CEF Digital to Cybersecurity by type of action | M22: Quota del contributo UE 2021-2027 all'area cybersecurity destinata a costruzione dell'ecosistema. | N22: Budget pubblico dedicato | O22: Totale aggregato | P22: Segmento di offerta | Q22: Costruzione dell'ecosistema | R22: 851.7 | S22: milioni | T22: EUR | U22: 2027 | V22: Previsione | X22: =IF(OR($S22="%",$R22=""),"",$R22*INDEX(Cambi!$J$2:$J$5,MATCH($S22,Cambi!$I$2:$I$5,0))/IF($T22="EUR",1,INDEX(Cambi!$D:$D,MATCH($T22&"|"&$U22,Cambi!$C:$C,0)))) -> 851.7 | Y22: Imprese e PA | Z22: Non specificato | AA22: Non specificato | AB22: Non determinabile | AC22: Dedotta. Dotazione di bilancio pubblico, non stima di mercato. | AD22: Non dichiarato | AE22: Elaborazione Technopolis su Digital Europe Dashboard e programmi di lavoro di DIGITAL e CEF Digital. Allocazione finale ancora soggetta a variazioni. | AF22: ecosystem building (€851.7 m), technology deployment (€151.1 m), and digital infrastructure (€65.8 m). | AG22: B | AH22: Pubblico | AI22: Sì | AJ22: Letto da estratto indicizzato della pagina. Verifica finale 08/10/2026, valore confermato sulla fonte. Contributo DIGITAL e CEF Digital nel QFP 2021-2027, anno di chiusura 2027. | AK22: 08/10/2026
A23: 22 | B23: TECHNOPOLIS-DIGCAP-2026 | C23: EU27 | D23: Unione europea (UE27) | E23: UE | F23: Commissione europea (studio di Technopolis Group) | G23: Istituzione UE | H23: Study on the EU's critical digital capacities deployment beyond 2027, Annex 7 Technology Area Report Cybersecurity and digital identity technologies | I23: 22/06/2026 | J23: https://op.europa.eu/o/opportal-service/download-handler?identifier=fa9b11af-6d4a-11f1-ae88-01aa75ed71a1&format=PDF&language=en&productionSystem=cellar | L23: Contribution of DIGITAL and CEF Digital to Cybersecurity by type of action | M23: Quota del contributo UE 2021-2027 all'area cybersecurity destinata a diffusione delle tecnologie. | N23: Budget pubblico dedicato | O23: Totale aggregato | P23: Segmento di offerta | Q23: Diffusione delle tecnologie | R23: 151.1 | S23: milioni | T23: EUR | U23: 2027 | V23: Previsione | X23: =IF(OR($S23="%",$R23=""),"",$R23*INDEX(Cambi!$J$2:$J$5,MATCH($S23,Cambi!$I$2:$I$5,0))/IF($T23="EUR",1,INDEX(Cambi!$D:$D,MATCH($T23&"|"&$U23,Cambi!$C:$C,0)))) -> 151.1 | Y23: Imprese e PA | Z23: Non specificato | AA23: Non specificato | AB23: Non determinabile | AC23: Dedotta. Dotazione di bilancio pubblico, non stima di mercato. | AD23: Non dichiarato | AE23: Elaborazione Technopolis su Digital Europe Dashboard e programmi di lavoro di DIGITAL e CEF Digital. Allocazione finale ancora soggetta a variazioni. | AF23: ecosystem building (€851.7 m), technology deployment (€151.1 m), and digital infrastructure (€65.8 m). | AG23: B | AH23: Pubblico | AI23: Sì | AJ23: Letto da estratto indicizzato della pagina. Verifica finale 08/10/2026, valore confermato sulla fonte. Contributo DIGITAL e CEF Digital nel QFP 2021-2027, anno di chiusura 2027. | AK23: 08/10/2026
A24: 23 | B24: TECHNOPOLIS-DIGCAP-2026 | C24: EU27 | D24: Unione europea (UE27) | E24: UE | F24: Commissione europea (studio di Technopolis Group) | G24: Istituzione UE | H24: Study on the EU's critical digital capacities deployment beyond 2027, Annex 7 Technology Area Report Cybersecurity and digital identity technologies | I24: 22/06/2026 | J24: https://op.europa.eu/o/opportal-service/download-handler?identifier=fa9b11af-6d4a-11f1-ae88-01aa75ed71a1&format=PDF&language=en&productionSystem=cellar | L24: Contribution of DIGITAL and CEF Digital to Cybersecurity by type of action | M24: Quota del contributo UE 2021-2027 all'area cybersecurity destinata a infrastruttura digitale. | N24: Budget pubblico dedicato | O24: Totale aggregato | P24: Segmento di offerta | Q24: Infrastruttura digitale | R24: 65.8 | S24: milioni | T24: EUR | U24: 2027 | V24: Previsione | X24: =IF(OR($S24="%",$R24=""),"",$R24*INDEX(Cambi!$J$2:$J$5,MATCH($S24,Cambi!$I$2:$I$5,0))/IF($T24="EUR",1,INDEX(Cambi!$D:$D,MATCH($T24&"|"&$U24,Cambi!$C:$C,0)))) -> 65.8 | Y24: Imprese e PA | Z24: Non specificato | AA24: Non specificato | AB24: Non determinabile | AC24: Dedotta. Dotazione di bilancio pubblico, non stima di mercato. | AD24: Non dichiarato | AE24: Elaborazione Technopolis su Digital Europe Dashboard e programmi di lavoro di DIGITAL e CEF Digital. Allocazione finale ancora soggetta a variazioni. | AF24: ecosystem building (€851.7 m), technology deployment (€151.1 m), and digital infrastructure (€65.8 m). | AG24: B | AH24: Pubblico | AI24: Sì | AJ24: Letto da estratto indicizzato della pagina. | AK24: 08/10/2026
A25: 24 | B25: TECHNOPOLIS-DIGCAP-2026 | C25: EU27 | D25: Unione europea (UE27) | E25: UE | F25: Commissione europea (studio di Technopolis Group) | G25: Istituzione UE | H25: Study on the EU's critical digital capacities deployment beyond 2027, Annex 7 Technology Area Report Cybersecurity and digital identity technologies | I25: 22/06/2026 | J25: https://op.europa.eu/o/opportal-service/download-handler?identifier=fa9b11af-6d4a-11f1-ae88-01aa75ed71a1&format=PDF&language=en&productionSystem=cellar | L25: Contribution of DIGITAL and CEF Digital to the technology area of Cybersecurity (MFF 2021-2027) | M25: Contributo complessivo dei programmi Europa digitale e CEF Digital all'area cybersecurity nel quadro finanziario 2021-2027. | N25: Budget pubblico dedicato | O25: Totale aggregato | P25: Nessuna | Q25: Totale | R25: 1149 | S25: milioni | T25: EUR | U25: 2027 | V25: Previsione | X25: =IF(OR($S25="%",$R25=""),"",$R25*INDEX(Cambi!$J$2:$J$5,MATCH($S25,Cambi!$I$2:$I$5,0))/IF($T25="EUR",1,INDEX(Cambi!$D:$D,MATCH($T25&"|"&$U25,Cambi!$C:$C,0)))) -> 1149 | Y25: Imprese e PA | Z25: Non specificato | AA25: Non specificato | AB25: Non determinabile | AC25: Dedotta. Dotazione di bilancio pubblico, non stima di mercato. | AD25: Non dichiarato | AE25: Elaborazione Technopolis su Digital Europe Dashboard e programmi di lavoro di DIGITAL e CEF Digital. Allocazione finale ancora soggetta a variazioni. | AF25: the contribution of DIGITAL and CEF Digital to the technology area of Cybersecurity totals €1 149 m | AG25: B | AH25: Pubblico | AI25: Sì | AJ25: Letto da estratto indicizzato della pagina. Dotazione pluriennale 2021-2027 registrata sull'anno di chiusura. | AK25: 08/10/2026
A26: 25 | B26: ECA-COMPENDIUM-2020 | C26: EU27 | D26: Unione europea (UE27) | E26: UE | F26: Corte dei conti europea | G26: Istituzione UE | H26: Audit Compendium Cybersecurity of the EU and its Member States | I26: 12/2020 | J26: https://www.eca.europa.eu/sites/cc/Lists/CCDocuments/Compendium_Cybersecurity/CC_Compendium_Cybersecurity_EN.pdf | K26: Commissione europea (stima citata in nota 65) | L26: EU funding for non-military cybersecurity per year 2014-2020 | M26: Finanziamento UE annuo per la cybersecurity non militare nel periodo 2014-2020 secondo la Commissione, inferiore a 200 milioni. | N26: Budget pubblico dedicato | O26: Totale aggregato | P26: Nessuna | Q26: Totale | R26: 200 | S26: milioni | T26: EUR | U26: 2020 | V26: Consuntivo | X26: =IF(OR($S26="%",$R26=""),"",$R26*INDEX(Cambi!$J$2:$J$5,MATCH($S26,Cambi!$I$2:$I$5,0))/IF($T26="EUR",1,INDEX(Cambi!$D:$D,MATCH($T26&"|"&$U26,Cambi!$C:$C,0)))) -> 200 | Y26: PA | Z26: Non specificato | AA26: Spesa pubblica in cybersecurity | AB26: Non determinabile | AC26: Dedotta. La Corte riprende una stima della Commissione senza descriverne la costruzione. | AD26: Ripreso da altra fonte | AE26: Non dichiarata | AF26: In total, EU funding for non-military cybersecurity has amounted to less than €200 million per year during the 2014-2020 period. | AG26: D | AH26: Pubblico | AI26: No | AJ26: Letto da estratto indicizzato della pagina. Valore soglia (meno di 200 milioni annui), media del periodo 2014-2020. Verifica finale 08/10/2026, valore confermato sulla fonte. Valore annuo massimo confermato nel compendio della Corte dei conti. | AK26: 08/10/2026
A27: 26 | B27: ECA-COMPENDIUM-2020 | C27: EU27 | D27: Unione europea (UE27) | E27: UE | F27: Corte dei conti europea | G27: Istituzione UE | H27: Audit Compendium Cybersecurity of the EU and its Member States | I27: 12/2020 | J27: https://www.eca.europa.eu/sites/cc/Lists/CCDocuments/Compendium_Cybersecurity/CC_Compendium_Cybersecurity_EN.pdf | K27: Commissione europea (stima citata in nota 65) | L27: Horizon 2020 allocation to cybersecurity and cybercrime projects 2014-2020 | M27: Fondi Horizon 2020 assegnati a progetti di cybersecurity e cybercrime nel periodo 2014-2020, inclusi 450 milioni per il partenariato contrattuale. | N27: Budget pubblico dedicato | O27: Totale aggregato | P27: Nessuna | Q27: Totale | R27: 600 | S27: milioni | T27: EUR | U27: 2020 | V27: Consuntivo | X27: =IF(OR($S27="%",$R27=""),"",$R27*INDEX(Cambi!$J$2:$J$5,MATCH($S27,Cambi!$I$2:$I$5,0))/IF($T27="EUR",1,INDEX(Cambi!$D:$D,MATCH($T27&"|"&$U27,Cambi!$C:$C,0)))) -> 600 | Y27: PA | Z27: Non specificato | AA27: Spesa pubblica in cybersecurity | AB27: Non determinabile | AC27: Dedotta. La Corte riprende una stima della Commissione senza descriverne la costruzione. | AD27: Ripreso da altra fonte | AE27: Non dichiarata | AF27: The EU's Horizon 2020 research programmes allocated about €600 million to cybersecurity and cybercrime projects for the period 2014-2020. | AG27: D | AH27: Pubblico | AI27: No | AJ27: Letto da estratto indicizzato della pagina. Cumulato 2014-2020 registrato sull'anno di chiusura. Verifica finale 08/10/2026, valore confermato sulla fonte. Stanziamento Horizon 2020 confermato, riferito al periodo 2014-2020. | AK27: 08/10/2026
A28: 27 | B28: ECCC-DEPWP-2025 | C28: EU27 | D28: Unione europea (UE27) | E28: UE | F28: ECCC, Centro europeo di competenza per la cibersicurezza | G28: Istituzione UE | H28: ECCC Digital Europe Cybersecurity Work Programme 2025-2027 (Decisione GB/2025/4) | I28: 03/2025 | J28: https://cybersecurity-centre.europa.eu/document/download/8af166e1-69c5-4ccd-b38f-5a3ffe43ad73_en?filename=DEP%20WP2025-2027_March2025.pdf | L28: Budget for Cybersecurity actions covered by this Work Programme, by year | M28: Bilancio indicativo annuale delle azioni di cybersecurity del programma Europa digitale gestite dall'ECCC, anno 2025. | N28: Budget pubblico dedicato | O28: Totale aggregato | P28: Nessuna | Q28: Totale | R28: 158 | S28: milioni | T28: EUR | U28: 2025 | V28: Previsione | X28: =IF(OR($S28="%",$R28=""),"",$R28*INDEX(Cambi!$J$2:$J$5,MATCH($S28,Cambi!$I$2:$I$5,0))/IF($T28="EUR",1,INDEX(Cambi!$D:$D,MATCH($T28&"|"&$U28,Cambi!$C:$C,0)))) -> 158 | Y28: Imprese e PA | Z28: Non specificato | AA28: Non specificato | AB28: Non determinabile | AC28: Dedotta. Dotazione di bilancio pubblico, non stima di mercato. | AD28: Non dichiarato | AE28: Dotazione di bilancio programmata, nessuna stima statistica. | AF28: TOTAL (in million EUR) 158 118 114 390 | AG28: B | AH28: Pubblico | AI28: Sì | AJ28: Letto da estratto indicizzato della pagina. Valori indicativi soggetti a decisioni del consiglio di amministrazione, ridotti a circa 355 milioni complessivi dall'emendamento successivo. Verifica finale 08/10/2026, valore confermato sulla fonte. Prima colonna della ripartizione annuale 2025-2027 del programma di lavoro. | AK28: 08/10/2026
A29: 28 | B29: ECCC-DEPWP-2025 | C29: EU27 | D29: Unione europea (UE27) | E29: UE | F29: ECCC, Centro europeo di competenza per la cibersicurezza | G29: Istituzione UE | H29: ECCC Digital Europe Cybersecurity Work Programme 2025-2027 (Decisione GB/2025/4) | I29: 03/2025 | J29: https://cybersecurity-centre.europa.eu/document/download/8af166e1-69c5-4ccd-b38f-5a3ffe43ad73_en?filename=DEP%20WP2025-2027_March2025.pdf | L29: Budget for Cybersecurity actions covered by this Work Programme, by year | M29: Bilancio indicativo annuale delle azioni di cybersecurity del programma Europa digitale gestite dall'ECCC, anno 2026. | N29: Budget pubblico dedicato | O29: Totale aggregato | P29: Nessuna | Q29: Totale | R29: 118 | S29: milioni | T29: EUR | U29: 2026 | V29: Previsione | X29: =IF(OR($S29="%",$R29=""),"",$R29*INDEX(Cambi!$J$2:$J$5,MATCH($S29,Cambi!$I$2:$I$5,0))/IF($T29="EUR",1,INDEX(Cambi!$D:$D,MATCH($T29&"|"&$U29,Cambi!$C:$C,0)))) -> 118 | Y29: Imprese e PA | Z29: Non specificato | AA29: Non specificato | AB29: Non determinabile | AC29: Dedotta. Dotazione di bilancio pubblico, non stima di mercato. | AD29: Non dichiarato | AE29: Dotazione di bilancio programmata, nessuna stima statistica. | AF29: TOTAL (in million EUR) 158 118 114 390 | AG29: B | AH29: Pubblico | AI29: Sì | AJ29: Letto da estratto indicizzato della pagina. Valori indicativi soggetti a decisioni del consiglio di amministrazione, ridotti a circa 355 milioni complessivi dall'emendamento successivo. Verifica finale 08/10/2026, valore confermato sulla fonte. Seconda colonna della ripartizione annuale, corrispondente al 2026. | AK29: 08/10/2026
A30: 29 | B30: ECCC-DEPWP-2025 | C30: EU27 | D30: Unione europea (UE27) | E30: UE | F30: ECCC, Centro europeo di competenza per la cibersicurezza | G30: Istituzione UE | H30: ECCC Digital Europe Cybersecurity Work Programme 2025-2027 (Decisione GB/2025/4) | I30: 03/2025 | J30: https://cybersecurity-centre.europa.eu/document/download/8af166e1-69c5-4ccd-b38f-5a3ffe43ad73_en?filename=DEP%20WP2025-2027_March2025.pdf | L30: Budget for Cybersecurity actions covered by this Work Programme, 2025-2027 | M30: Bilancio complessivo delle azioni di cybersecurity del programma Europa digitale gestite dall'ECCC nel triennio 2025-2027. | N30: Budget pubblico dedicato | O30: Totale aggregato | P30: Nessuna | Q30: Totale | R30: 390 | S30: milioni | T30: EUR | U30: 2027 | V30: Previsione | X30: =IF(OR($S30="%",$R30=""),"",$R30*INDEX(Cambi!$J$2:$J$5,MATCH($S30,Cambi!$I$2:$I$5,0))/IF($T30="EUR",1,INDEX(Cambi!$D:$D,MATCH($T30&"|"&$U30,Cambi!$C:$C,0)))) -> 390 | Y30: Imprese e PA | Z30: Non specificato | AA30: Non specificato | AB30: Non determinabile | AC30: Dedotta. Dotazione di bilancio pubblico, non stima di mercato. | AD30: Non dichiarato | AE30: Dotazione di bilancio programmata, nessuna stima statistica. | AF30: The budget for Cybersecurity actions covered by this Work Programme is of approximatively EUR 390 million30, distributed across 3 years from 2025 to 2027. | AG30: B | AH30: Pubblico | AI30: Sì | AJ30: Letto da estratto indicizzato della pagina. Totale triennale registrato sull'anno di chiusura. Comprende 42 milioni riportati dal 2022. Verifica finale 08/10/2026, valore confermato sulla fonte. Valore cumulato sul triennio 2025-2027 registrato con anno finale 2027. | AK30: 08/10/2026
A31: 30 | B31: ECCC-DEPWP-2025 | C31: EU27 | D31: Unione europea (UE27) | E31: UE | F31: ECCC, Centro europeo di competenza per la cibersicurezza | G31: Istituzione UE | H31: ECCC Digital Europe Cybersecurity Work Programme 2025-2027 (Decisione GB/2025/4) | I31: 03/2025 | J31: https://cybersecurity-centre.europa.eu/document/download/8af166e1-69c5-4ccd-b38f-5a3ffe43ad73_en?filename=DEP%20WP2025-2027_March2025.pdf | L31: Budget for Cybersecurity actions covered by this Work Programme, by year | M31: Bilancio indicativo annuale delle azioni di cybersecurity del programma Europa digitale gestite dall'ECCC, anno 2027. | N31: Budget pubblico dedicato | O31: Totale aggregato | P31: Nessuna | Q31: Totale | R31: 114 | S31: milioni | T31: EUR | U31: 2027 | V31: Previsione | X31: =IF(OR($S31="%",$R31=""),"",$R31*INDEX(Cambi!$J$2:$J$5,MATCH($S31,Cambi!$I$2:$I$5,0))/IF($T31="EUR",1,INDEX(Cambi!$D:$D,MATCH($T31&"|"&$U31,Cambi!$C:$C,0)))) -> 114 | Y31: Imprese e PA | Z31: Non specificato | AA31: Non specificato | AB31: Non determinabile | AC31: Dedotta. Dotazione di bilancio pubblico, non stima di mercato. | AD31: Non dichiarato | AE31: Dotazione di bilancio programmata, nessuna stima statistica. | AF31: TOTAL (in million EUR) 158 118 114 390 | AG31: B | AH31: Pubblico | AI31: Sì | AJ31: Letto da estratto indicizzato della pagina. Valori indicativi soggetti a decisioni del consiglio di amministrazione, ridotti a circa 355 milioni complessivi dall'emendamento successivo. | AK31: 08/10/2026
A32: 31 | B32: ECCC-DEPWPAM2-2025 | C32: EU27 | D32: Unione europea (UE27) | E32: UE | F32: ECCC, Centro europeo di competenza per la cibersicurezza | G32: Istituzione UE | H32: ECCC Digital Europe Cybersecurity Work Programme 2025-2027, emendamento 2 (testo consolidato) | I32: 2025 | J32: https://cybersecurity-centre.europa.eu/document/download/a35f7be2-4464-43d3-a40f-6ec942036f48_en?filename=Amendment2cleanDEPcybersecurityWP2025-2027.pdf | L32: Budget for Cybersecurity actions covered by this Work Programme (amended) | M32: Bilancio rivisto delle azioni di cybersecurity ECCC 2025-2027 dopo la riallocazione di 35 milioni alle AI Gigafactories. | N32: Budget pubblico dedicato | O32: Totale aggregato | P32: Nessuna | Q32: Totale | R32: 355 | S32: milioni | T32: EUR | U32: 2027 | V32: Previsione | X32: =IF(OR($S32="%",$R32=""),"",$R32*INDEX(Cambi!$J$2:$J$5,MATCH($S32,Cambi!$I$2:$I$5,0))/IF($T32="EUR",1,INDEX(Cambi!$D:$D,MATCH($T32&"|"&$U32,Cambi!$C:$C,0)))) -> 355 | Y32: Imprese e PA | Z32: Non specificato | AA32: Non specificato | AB32: Non determinabile | AC32: Dedotta. Dotazione di bilancio pubblico, non stima di mercato. | AD32: Non dichiarato | AE32: Dotazione di bilancio programmata, nessuna stima statistica. | AF32: The budget for Cybersecurity actions covered by this Work Programme is of approximatively EUR 355 million31, distributed across 3 years from 2025 to 2027. | AG32: B | AH32: Pubblico | AI32: Sì | AJ32: Letto da estratto indicizzato della pagina. Totale triennale registrato sull'anno di chiusura. | AK32: 08/10/2026
A33: 32 | B33: ECCC-DEPWPAM2-2025 | C33: EU27 | D33: Unione europea (UE27) | E33: UE | F33: ECCC, Centro europeo di competenza per la cibersicurezza | G33: Istituzione UE | H33: ECCC Digital Europe Cybersecurity Work Programme 2025-2027, emendamento 2 (testo consolidato) | I33: 2025 | J33: https://cybersecurity-centre.europa.eu/document/download/a35f7be2-4464-43d3-a40f-6ec942036f48_en?filename=Amendment2cleanDEPcybersecurityWP2025-2027.pdf | L33: Updated indicative proposal for the distribution of the budget | M33: Ripartizione indicativa del bilancio cyber ECCC 2025-2027 per area, voce attuazione del cyber solidarity act e allerta. | N33: Budget pubblico dedicato | O33: Totale aggregato | P33: Segmento di offerta | Q33: Attuazione del Cyber Solidarity Act e allerta | R33: 97 | S33: milioni | T33: EUR | U33: 2027 | V33: Previsione | X33: =IF(OR($S33="%",$R33=""),"",$R33*INDEX(Cambi!$J$2:$J$5,MATCH($S33,Cambi!$I$2:$I$5,0))/IF($T33="EUR",1,INDEX(Cambi!$D:$D,MATCH($T33&"|"&$U33,Cambi!$C:$C,0)))) -> 97 | Y33: Imprese e PA | Z33: Non specificato | AA33: Non specificato | AB33: Non determinabile | AC33: Dedotta. Dotazione di bilancio pubblico, non stima di mercato. | AD33: Non dichiarato | AE33: Dotazione di bilancio programmata, nessuna stima statistica. | AF33: EUR 97 million for the implementation of Cyber Solidarity Act, consolidation of European Cybersecurity Alert System | AG33: B | AH33: Pubblico | AI33: Sì | AJ33: Letto da estratto indicizzato della pagina. Totale triennale registrato sull'anno di chiusura. | AK33: 08/10/2026
A34: 33 | B34: ECCC-DEPWPAM2-2025 | C34: EU27 | D34: Unione europea (UE27) | E34: UE | F34: ECCC, Centro europeo di competenza per la cibersicurezza | G34: Istituzione UE | H34: ECCC Digital Europe Cybersecurity Work Programme 2025-2027, emendamento 2 (testo consolidato) | I34: 2025 | J34: https://cybersecurity-centre.europa.eu/document/download/a35f7be2-4464-43d3-a40f-6ec942036f48_en?filename=Amendment2cleanDEPcybersecurityWP2025-2027.pdf | L34: Updated indicative proposal for the distribution of the budget | M34: Ripartizione indicativa del bilancio cyber ECCC 2025-2027 per area, voce nuove tecnologie, ia e transizione post-quantistica. | N34: Budget pubblico dedicato | O34: Totale aggregato | P34: Segmento di offerta | Q34: Nuove tecnologie, IA e transizione post-quantistica | R34: 139 | S34: milioni | T34: EUR | U34: 2027 | V34: Previsione | X34: =IF(OR($S34="%",$R34=""),"",$R34*INDEX(Cambi!$J$2:$J$5,MATCH($S34,Cambi!$I$2:$I$5,0))/IF($T34="EUR",1,INDEX(Cambi!$D:$D,MATCH($T34&"|"&$U34,Cambi!$C:$C,0)))) -> 139 | Y34: Imprese e PA | Z34: Non specificato | AA34: Non specificato | AB34: Non determinabile | AC34: Dedotta. Dotazione di bilancio pubblico, non stima di mercato. | AD34: Non dichiarato | AE34: Dotazione di bilancio programmata, nessuna stima statistica. | AF34: EUR 139 million for new technologies and cybersecurity, the deployment of Artificial Intelligence & cybersecurity and the post-quantum transition. | AG34: B | AH34: Pubblico | AI34: Sì | AJ34: Letto da estratto indicizzato della pagina. Totale triennale registrato sull'anno di chiusura. | AK34: 08/10/2026
A35: 34 | B35: ECCC-DEPWPAM2-2025 | C35: EU27 | D35: Unione europea (UE27) | E35: UE | F35: ECCC, Centro europeo di competenza per la cibersicurezza | G35: Istituzione UE | H35: ECCC Digital Europe Cybersecurity Work Programme 2025-2027, emendamento 2 (testo consolidato) | I35: 2025 | J35: https://cybersecurity-centre.europa.eu/document/download/a35f7be2-4464-43d3-a40f-6ec942036f48_en?filename=Amendment2cleanDEPcybersecurityWP2025-2027.pdf | L35: Updated indicative proposal for the distribution of the budget | M35: Ripartizione indicativa del bilancio cyber ECCC 2025-2027 per area, voce supporto al programma. | N35: Budget pubblico dedicato | O35: Totale aggregato | P35: Segmento di offerta | Q35: Supporto al programma | R35: 9 | S35: milioni | T35: EUR | U35: 2027 | V35: Previsione | X35: =IF(OR($S35="%",$R35=""),"",$R35*INDEX(Cambi!$J$2:$J$5,MATCH($S35,Cambi!$I$2:$I$5,0))/IF($T35="EUR",1,INDEX(Cambi!$D:$D,MATCH($T35&"|"&$U35,Cambi!$C:$C,0)))) -> 9 | Y35: Imprese e PA | Z35: Non specificato | AA35: Non specificato | AB35: Non determinabile | AC35: Dedotta. Dotazione di bilancio pubblico, non stima di mercato. | AD35: Non dichiarato | AE35: Dotazione di bilancio programmata, nessuna stima statistica. | AF35: EUR 9 million for programme support actions, including evaluations and reviews. | AG35: B | AH35: Pubblico | AI35: Sì | AJ35: Letto da estratto indicizzato della pagina. Totale triennale registrato sull'anno di chiusura. | AK35: 08/10/2026
A36: 35 | B36: ECCC-DEPWPAM2-2025 | C36: EU27 | D36: Unione europea (UE27) | E36: UE | F36: ECCC, Centro europeo di competenza per la cibersicurezza | G36: Istituzione UE | H36: ECCC Digital Europe Cybersecurity Work Programme 2025-2027, emendamento 2 (testo consolidato) | I36: 2025 | J36: https://cybersecurity-centre.europa.eu/document/download/a35f7be2-4464-43d3-a40f-6ec942036f48_en?filename=Amendment2cleanDEPcybersecurityWP2025-2027.pdf | L36: Updated indicative proposal for the distribution of the budget | M36: Ripartizione indicativa del bilancio cyber ECCC 2025-2027 per area, voce ulteriori azioni di resilienza ue. | N36: Budget pubblico dedicato | O36: Totale aggregato | P36: Segmento di offerta | Q36: Ulteriori azioni di resilienza UE | R36: 110 | S36: milioni | T36: EUR | U36: 2027 | V36: Previsione | X36: =IF(OR($S36="%",$R36=""),"",$R36*INDEX(Cambi!$J$2:$J$5,MATCH($S36,Cambi!$I$2:$I$5,0))/IF($T36="EUR",1,INDEX(Cambi!$D:$D,MATCH($T36&"|"&$U36,Cambi!$C:$C,0)))) -> 110 | Y36: Imprese e PA | Z36: Non specificato | AA36: Non specificato | AB36: Non determinabile | AC36: Dedotta. Dotazione di bilancio pubblico, non stima di mercato. | AD36: Non dichiarato | AE36: Dotazione di bilancio programmata, nessuna stima statistica. | AF36: EUR 110 million for additional actions improving EU resilience. | AG36: B | AH36: Pubblico | AI36: Sì | AJ36: Letto da estratto indicizzato della pagina. Totale triennale registrato sull'anno di chiusura. | AK36: 08/10/2026
A37: 36 | B37: ECCC-SPD-2024 | C37: EU27 | D37: Unione europea (UE27) | E37: UE | F37: ECCC, Centro europeo di competenza per la cibersicurezza | G37: Istituzione UE | H37: ECCC Single Programming Document 2024-2026 (Decisione GB 2023/8) | I37: 01/2024 | J37: https://cybersecurity-centre.europa.eu/system/files/2024-01/ECCC%20GB%20Decision%20No%202023_8%20ECCC%20final%20SPD%202024-2026.pdf | L37: Estimated budget for ECCC in the Cybersecurity part of DEP during 2023-2024 | M37: Bilancio stimato per l'ECCC nella parte cybersecurity del programma Europa digitale nel biennio 2023-2024. | N37: Budget pubblico dedicato | O37: Totale aggregato | P37: Nessuna | Q37: Totale | R37: 375 | S37: milioni | T37: EUR | U37: 2024 | V37: Previsione | X37: =IF(OR($S37="%",$R37=""),"",$R37*INDEX(Cambi!$J$2:$J$5,MATCH($S37,Cambi!$I$2:$I$5,0))/IF($T37="EUR",1,INDEX(Cambi!$D:$D,MATCH($T37&"|"&$U37,Cambi!$C:$C,0)))) -> 375 | Y37: Imprese e PA | Z37: Non specificato | AA37: Non specificato | AB37: Non determinabile | AC37: Dedotta. Dotazione di bilancio pubblico, non stima di mercato. | AD37: Non dichiarato | AE37: Dotazione di bilancio programmata, nessuna stima statistica. | AF37: The estimated budget for ECCC in the Cybersecurity part of DEP during the 2-year period 2023-2024 is approximately EUR 375 million. | AG37: B | AH37: Pubblico | AI37: Sì | AJ37: Letto da estratto indicizzato della pagina. Totale biennale registrato sull'anno di chiusura. | AK37: 08/10/2026
A38: 37 | B38: ECCC-SPD-2024 | C38: EU27 | D38: Unione europea (UE27) | E38: UE | F38: ECCC, Centro europeo di competenza per la cibersicurezza | G38: Istituzione UE | H38: ECCC Single Programming Document 2024-2026 (Decisione GB 2023/8) | I38: 01/2024 | J38: https://cybersecurity-centre.europa.eu/system/files/2024-01/ECCC%20GB%20Decision%20No%202023_8%20ECCC%20final%20SPD%202024-2026.pdf | L38: Total estimated revenue for ECCC (EUR) | M38: Entrate totali stimate dell'ECCC per l'anno 2024 nel documento di programmazione 2024-2026. | N38: Budget pubblico dedicato | O38: Totale aggregato | P38: Nessuna | Q38: Totale | R38: 218.83113 | S38: milioni | T38: EUR | U38: 2024 | V38: Previsione | X38: =IF(OR($S38="%",$R38=""),"",$R38*INDEX(Cambi!$J$2:$J$5,MATCH($S38,Cambi!$I$2:$I$5,0))/IF($T38="EUR",1,INDEX(Cambi!$D:$D,MATCH($T38&"|"&$U38,Cambi!$C:$C,0)))) -> 218.83113 | Y38: Imprese e PA | Z38: Non specificato | AA38: Non specificato | AB38: Non determinabile | AC38: Dedotta. Dotazione di bilancio pubblico, non stima di mercato. | AD38: Non dichiarato | AE38: Dotazione di bilancio programmata, nessuna stima statistica. | AF38: Total estimated revenue for ECCC (EUR) 23 218.831.127,16 125.766.680,63 126.032.746,58 | AG38: B | AH38: Pubblico | AI38: Sì | AJ38: Letto da estratto indicizzato della pagina. Pubblicato in euro, convertito in milioni con arrotondamento a sei decimali. Entrate dell'agenzia, include fondi per bandi. Verifica finale 08/10/2026, valore confermato sulla fonte. Entrate stimate 2024 pari a 218,83 milioni EUR, confermate. | AK38: 08/10/2026
A39: 38 | B39: ECCC-SPD-2024 | C39: EU27 | D39: Unione europea (UE27) | E39: UE | F39: ECCC, Centro europeo di competenza per la cibersicurezza | G39: Istituzione UE | H39: ECCC Single Programming Document 2024-2026 (Decisione GB 2023/8) | I39: 01/2024 | J39: https://cybersecurity-centre.europa.eu/system/files/2024-01/ECCC%20GB%20Decision%20No%202023_8%20ECCC%20final%20SPD%202024-2026.pdf | L39: Total estimated revenue for ECCC (EUR) | M39: Entrate totali stimate dell'ECCC per l'anno 2025 nel documento di programmazione 2024-2026. | N39: Budget pubblico dedicato | O39: Totale aggregato | P39: Nessuna | Q39: Totale | R39: 125.76668 | S39: milioni | T39: EUR | U39: 2025 | V39: Previsione | X39: =IF(OR($S39="%",$R39=""),"",$R39*INDEX(Cambi!$J$2:$J$5,MATCH($S39,Cambi!$I$2:$I$5,0))/IF($T39="EUR",1,INDEX(Cambi!$D:$D,MATCH($T39&"|"&$U39,Cambi!$C:$C,0)))) -> 125.76668 | Y39: Imprese e PA | Z39: Non specificato | AA39: Non specificato | AB39: Non determinabile | AC39: Dedotta. Dotazione di bilancio pubblico, non stima di mercato. | AD39: Non dichiarato | AE39: Dotazione di bilancio programmata, nessuna stima statistica. | AF39: Total estimated revenue for ECCC (EUR) 23 218.831.127,16 125.766.680,63 126.032.746,58 | AG39: B | AH39: Pubblico | AI39: Sì | AJ39: Letto da estratto indicizzato della pagina. Pubblicato in euro, convertito in milioni con arrotondamento a sei decimali. Entrate dell'agenzia, include fondi per bandi. | AK39: 08/10/2026
A40: 39 | B40: ECCC-SPD-2024 | C40: EU27 | D40: Unione europea (UE27) | E40: UE | F40: ECCC, Centro europeo di competenza per la cibersicurezza | G40: Istituzione UE | H40: ECCC Single Programming Document 2024-2026 (Decisione GB 2023/8) | I40: 01/2024 | J40: https://cybersecurity-centre.europa.eu/system/files/2024-01/ECCC%20GB%20Decision%20No%202023_8%20ECCC%20final%20SPD%202024-2026.pdf | L40: Total estimated revenue for ECCC (EUR) | M40: Entrate totali stimate dell'ECCC per l'anno 2026 nel documento di programmazione 2024-2026. | N40: Budget pubblico dedicato | O40: Totale aggregato | P40: Nessuna | Q40: Totale | R40: 126.03275 | S40: milioni | T40: EUR | U40: 2026 | V40: Previsione | X40: =IF(OR($S40="%",$R40=""),"",$R40*INDEX(Cambi!$J$2:$J$5,MATCH($S40,Cambi!$I$2:$I$5,0))/IF($T40="EUR",1,INDEX(Cambi!$D:$D,MATCH($T40&"|"&$U40,Cambi!$C:$C,0)))) -> 126.03275 | Y40: Imprese e PA | Z40: Non specificato | AA40: Non specificato | AB40: Non determinabile | AC40: Dedotta. Dotazione di bilancio pubblico, non stima di mercato. | AD40: Non dichiarato | AE40: Dotazione di bilancio programmata, nessuna stima statistica. | AF40: Total estimated revenue for ECCC (EUR) 23 218.831.127,16 125.766.680,63 126.032.746,58 | AG40: B | AH40: Pubblico | AI40: Sì | AJ40: Letto da estratto indicizzato della pagina. Pubblicato in euro, convertito in milioni con arrotondamento a sei decimali. Entrate dell'agenzia, include fondi per bandi. | AK40: 08/10/2026
A41: 40 | B41: ECSO-MARKET-2024 | C41: EU27 | D41: Unione europea (UE27) | E41: UE | F41: ECSO, European Cyber Security Organisation | G41: Associazione | H41: ECSO Cybersecurity Market Analysis and Recommendations v1.1 | I41: 19/12/2024 | J41: https://ecs-org.eu/ecso-uploads/2024/12/ECSO-Cybersecurity-Market-Analysis-and-Recommendations-v1.1.pdf | K41: Analisi di mercato del progetto ECCO, adattata da ECSO | L41: European Market: EU | M41: Dimensione del mercato UE della cybersecurity secondo ECSO, con crescita media del 10%. | N41: Mercato domestico | O41: Totale aggregato | P41: Nessuna | Q41: Totale | R41: 30 | S41: miliardi | T41: EUR | U41: 2024 | V41: Stima dell'anno in corso | W41: Crescita media 10% | X41: =IF(OR($S41="%",$R41=""),"",$R41*INDEX(Cambi!$J$2:$J$5,MATCH($S41,Cambi!$I$2:$I$5,0))/IF($T41="EUR",1,INDEX(Cambi!$D:$D,MATCH($T41&"|"&$U41,Cambi!$C:$C,0)))) -> 30000 | Y41: Non specificato | Z41: No | AA41: Non specificato | AB41: Non determinabile | AC41: Dedotta. Il documento non descrive come è costruito il valore. | AD41: Ripreso da altra fonte | AE41: Non dichiarata. Valori adattati dall'analisi di mercato del progetto ECCO. | AF41: European Market: EU €30 billion; 10% ave. growth. | AG41: D | AH41: Pubblico | AI41: No | AJ41: Letto da estratto indicizzato della pagina. Anno non dichiarato per il dato UE, dedotto 2024 dal dato globale dello stesso riquadro. Verifica finale 08/10/2026, valore confermato sulla fonte. Valore confermato. L'estratto non indica l'anno, coerente con la pubblicazione di dicembre 2024. | AK41: 08/10/2026
A42: 41 | B42: ECSO-MARKET-2024 | C42: EU27 | D42: Unione europea (UE27) | E42: UE | F42: ECSO, European Cyber Security Organisation | G42: Associazione | H42: ECSO Cybersecurity Market Analysis and Recommendations v1.1 | I42: 19/12/2024 | J42: https://ecs-org.eu/ecso-uploads/2024/12/ECSO-Cybersecurity-Market-Analysis-and-Recommendations-v1.1.pdf | K42: Analisi di mercato del progetto ECCO, adattata da ECSO | L42: Market share | M42: Quota di mercato della voce finanza nel riquadro ECSO sul mercato della cybersecurity. | N42: Mercato domestico | O42: Quota percentuale | P42: Settore | Q42: Finanza | R42: 30 | S42: % | U42: 2024 | V42: Stima dell'anno in corso | X42: =IF(OR($S42="%",$R42=""),"",$R42*INDEX(Cambi!$J$2:$J$5,MATCH($S42,Cambi!$I$2:$I$5,0))/IF($T42="EUR",1,INDEX(Cambi!$D:$D,MATCH($T42&"|"&$U42,Cambi!$C:$C,0)))) | Y42: Non specificato | Z42: No | AA42: Non specificato | AB42: Non determinabile | AC42: Dedotta. Il documento non descrive come è costruito il valore. | AD42: Ripreso da altra fonte | AE42: Non dichiarata. Valori adattati dall'analisi di mercato del progetto ECCO. | AF42: MARKET SHARE Finance (30%) Government (18%) Majority of others (about 10%) Security Services (>40%) Infrastructure protection (15%) Network Security (11%) | AG42: D | AH42: Pubblico | AI42: No | AJ42: Letto da estratto indicizzato della pagina. Non è chiaro se le quote si riferiscano al mercato UE o globale. | AK42: 08/10/2026
A43: 42 | B43: ECSO-MARKET-2024 | C43: EU27 | D43: Unione europea (UE27) | E43: UE | F43: ECSO, European Cyber Security Organisation | G43: Associazione | H43: ECSO Cybersecurity Market Analysis and Recommendations v1.1 | I43: 19/12/2024 | J43: https://ecs-org.eu/ecso-uploads/2024/12/ECSO-Cybersecurity-Market-Analysis-and-Recommendations-v1.1.pdf | K43: Analisi di mercato del progetto ECCO, adattata da ECSO | L43: Market share | M43: Quota di mercato della voce protezione delle infrastrutture nel riquadro ECSO sul mercato della cybersecurity. | N43: Mercato domestico | O43: Quota percentuale | P43: Segmento di offerta | Q43: Protezione delle infrastrutture | R43: 15 | S43: % | U43: 2024 | V43: Stima dell'anno in corso | X43: =IF(OR($S43="%",$R43=""),"",$R43*INDEX(Cambi!$J$2:$J$5,MATCH($S43,Cambi!$I$2:$I$5,0))/IF($T43="EUR",1,INDEX(Cambi!$D:$D,MATCH($T43&"|"&$U43,Cambi!$C:$C,0)))) | Y43: Non specificato | Z43: No | AA43: Non specificato | AB43: Non determinabile | AC43: Dedotta. Il documento non descrive come è costruito il valore. | AD43: Ripreso da altra fonte | AE43: Non dichiarata. Valori adattati dall'analisi di mercato del progetto ECCO. | AF43: MARKET SHARE Finance (30%) Government (18%) Majority of others (about 10%) Security Services (>40%) Infrastructure protection (15%) Network Security (11%) | AG43: D | AH43: Pubblico | AI43: No | AJ43: Letto da estratto indicizzato della pagina. Non è chiaro se le quote si riferiscano al mercato UE o globale. | AK43: 08/10/2026
A44: 43 | B44: ECSO-MARKET-2024 | C44: EU27 | D44: Unione europea (UE27) | E44: UE | F44: ECSO, European Cyber Security Organisation | G44: Associazione | H44: ECSO Cybersecurity Market Analysis and Recommendations v1.1 | I44: 19/12/2024 | J44: https://ecs-org.eu/ecso-uploads/2024/12/ECSO-Cybersecurity-Market-Analysis-and-Recommendations-v1.1.pdf | K44: Analisi di mercato del progetto ECCO, adattata da ECSO | L44: Market share | M44: Quota di mercato della voce pubblica amministrazione nel riquadro ECSO sul mercato della cybersecurity. | N44: Mercato domestico | O44: Quota percentuale | P44: Tipo di cliente | Q44: Pubblica amministrazione | R44: 18 | S44: % | U44: 2024 | V44: Stima dell'anno in corso | X44: =IF(OR($S44="%",$R44=""),"",$R44*INDEX(Cambi!$J$2:$J$5,MATCH($S44,Cambi!$I$2:$I$5,0))/IF($T44="EUR",1,INDEX(Cambi!$D:$D,MATCH($T44&"|"&$U44,Cambi!$C:$C,0)))) | Y44: Non specificato | Z44: No | AA44: Non specificato | AB44: Non determinabile | AC44: Dedotta. Il documento non descrive come è costruito il valore. | AD44: Ripreso da altra fonte | AE44: Non dichiarata. Valori adattati dall'analisi di mercato del progetto ECCO. | AF44: MARKET SHARE Finance (30%) Government (18%) Majority of others (about 10%) Security Services (>40%) Infrastructure protection (15%) Network Security (11%) | AG44: D | AH44: Pubblico | AI44: No | AJ44: Letto da estratto indicizzato della pagina. Non è chiaro se le quote si riferiscano al mercato UE o globale. | AK44: 08/10/2026
A45: 44 | B45: ECSO-MARKET-2024 | C45: EU27 | D45: Unione europea (UE27) | E45: UE | F45: ECSO, European Cyber Security Organisation | G45: Associazione | H45: ECSO Cybersecurity Market Analysis and Recommendations v1.1 | I45: 19/12/2024 | J45: https://ecs-org.eu/ecso-uploads/2024/12/ECSO-Cybersecurity-Market-Analysis-and-Recommendations-v1.1.pdf | K45: Analisi di mercato del progetto ECCO, adattata da ECSO | L45: Market share | M45: Quota di mercato della voce servizi di sicurezza nel riquadro ECSO sul mercato della cybersecurity. | N45: Mercato domestico | O45: Quota percentuale | P45: Segmento di offerta | Q45: Servizi di sicurezza | R45: 40 | S45: % | U45: 2024 | V45: Stima dell'anno in corso | X45: =IF(OR($S45="%",$R45=""),"",$R45*INDEX(Cambi!$J$2:$J$5,MATCH($S45,Cambi!$I$2:$I$5,0))/IF($T45="EUR",1,INDEX(Cambi!$D:$D,MATCH($T45&"|"&$U45,Cambi!$C:$C,0)))) | Y45: Non specificato | Z45: No | AA45: Non specificato | AB45: Non determinabile | AC45: Dedotta. Il documento non descrive come è costruito il valore. | AD45: Ripreso da altra fonte | AE45: Non dichiarata. Valori adattati dall'analisi di mercato del progetto ECCO. | AF45: MARKET SHARE Finance (30%) Government (18%) Majority of others (about 10%) Security Services (>40%) Infrastructure protection (15%) Network Security (11%) | AG45: D | AH45: Pubblico | AI45: No | AJ45: Letto da estratto indicizzato della pagina. Non è chiaro se le quote si riferiscano al mercato UE o globale. Pubblicato come oltre 40%. Verifica finale 08/10/2026, valore confermato sulla fonte. Quota confermata, nella fonte è un limite inferiore oltre il 40 per cento. | AK45: 08/10/2026
A46: 45 | B46: ECSO-MARKET-2024 | C46: EU27 | D46: Unione europea (UE27) | E46: UE | F46: ECSO, European Cyber Security Organisation | G46: Associazione | H46: ECSO Cybersecurity Market Analysis and Recommendations v1.1 | I46: 19/12/2024 | J46: https://ecs-org.eu/ecso-uploads/2024/12/ECSO-Cybersecurity-Market-Analysis-and-Recommendations-v1.1.pdf | K46: Analisi di mercato del progetto ECCO, adattata da ECSO | L46: Market share | M46: Quota di mercato della voce sicurezza di rete nel riquadro ECSO sul mercato della cybersecurity. | N46: Mercato domestico | O46: Quota percentuale | P46: Segmento di offerta | Q46: Sicurezza di rete | R46: 11 | S46: % | U46: 2024 | V46: Stima dell'anno in corso | X46: =IF(OR($S46="%",$R46=""),"",$R46*INDEX(Cambi!$J$2:$J$5,MATCH($S46,Cambi!$I$2:$I$5,0))/IF($T46="EUR",1,INDEX(Cambi!$D:$D,MATCH($T46&"|"&$U46,Cambi!$C:$C,0)))) | Y46: Non specificato | Z46: No | AA46: Non specificato | AB46: Non determinabile | AC46: Dedotta. Il documento non descrive come è costruito il valore. | AD46: Ripreso da altra fonte | AE46: Non dichiarata. Valori adattati dall'analisi di mercato del progetto ECCO. | AF46: MARKET SHARE Finance (30%) Government (18%) Majority of others (about 10%) Security Services (>40%) Infrastructure protection (15%) Network Security (11%) | AG46: D | AH46: Pubblico | AI46: No | AJ46: Letto da estratto indicizzato della pagina. Non è chiaro se le quote si riferiscano al mercato UE o globale. | AK46: 08/10/2026
A47: 46 | B47: ENISA-CAAR-2025 | C47: EU27 | D47: Unione europea (UE27) | E47: UE | F47: ENISA | G47: Istituzione UE | H47: 2024 Consolidated Annual Activity Report | I47: 06/2025 | J47: https://www.enisa.europa.eu/sites/default/files/2025-06/Consolidated%20Annual%20Activity%20Report%202024.pdf | L47: ENISA operating budget | M47: Bilancio di funzionamento di ENISA, agenzia UE per la cibersicurezza, nell'anno 2023. | N47: Budget pubblico dedicato | O47: Totale aggregato | P47: Nessuna | Q47: Totale | R47: 25.2 | S47: milioni | T47: EUR | U47: 2023 | V47: Consuntivo | X47: =IF(OR($S47="%",$R47=""),"",$R47*INDEX(Cambi!$J$2:$J$5,MATCH($S47,Cambi!$I$2:$I$5,0))/IF($T47="EUR",1,INDEX(Cambi!$D:$D,MATCH($T47&"|"&$U47,Cambi!$C:$C,0)))) -> 25.2 | Y47: PA | Z47: Non specificato | AA47: Non specificato | AB47: Non determinabile | AC47: Dedotta. Dotazione di bilancio pubblico, non stima di mercato. | AD47: Non dichiarato | AE47: Rendiconto di bilancio dell'agenzia. | AF47: During 2024, ENISA operated with a budget of EUR 26.2 million compared with the 2023 budget of EUR 25.2 million. | AG47: B | AH47: Pubblico | AI47: Sì | AJ47: Letto da estratto indicizzato della pagina. | AK47: 08/10/2026
A48: 47 | B48: ENISA-CAAR-2025 | C48: EU27 | D48: Unione europea (UE27) | E48: UE | F48: ENISA | G48: Istituzione UE | H48: 2024 Consolidated Annual Activity Report | I48: 06/2025 | J48: https://www.enisa.europa.eu/sites/default/files/2025-06/Consolidated%20Annual%20Activity%20Report%202024.pdf | L48: ENISA operating budget | M48: Bilancio di funzionamento di ENISA, agenzia UE per la cibersicurezza, nell'anno 2024. | N48: Budget pubblico dedicato | O48: Totale aggregato | P48: Nessuna | Q48: Totale | R48: 26.2 | S48: milioni | T48: EUR | U48: 2024 | V48: Consuntivo | X48: =IF(OR($S48="%",$R48=""),"",$R48*INDEX(Cambi!$J$2:$J$5,MATCH($S48,Cambi!$I$2:$I$5,0))/IF($T48="EUR",1,INDEX(Cambi!$D:$D,MATCH($T48&"|"&$U48,Cambi!$C:$C,0)))) -> 26.2 | Y48: PA | Z48: Non specificato | AA48: Non specificato | AB48: Non determinabile | AC48: Dedotta. Dotazione di bilancio pubblico, non stima di mercato. | AD48: Non dichiarato | AE48: Rendiconto di bilancio dell'agenzia. | AF48: During 2024, ENISA operated with a budget of EUR 26.2 million compared with the 2023 budget of EUR 25.2 million. | AG48: B | AH48: Pubblico | AI48: Sì | AJ48: Letto da estratto indicizzato della pagina. Verifica finale 08/10/2026, valore confermato sulla fonte. Bilancio 2024 dell'agenzia confermato. | AK48: 08/10/2026
A49: 48 | B49: ENISA-NISINV-2020 | C49: EU27 | D49: Unione europea (UE27) | E49: UE | F49: ENISA, Agenzia dell'Unione europea per la cibersicurezza | G49: Istituzione UE | H49: NIS Investments Report 2020 (prima edizione) | I49: 11/12/2020 | J49: https://www.enisa.europa.eu/sites/default/files/publications/ENISA%20-%20NIS%20Investments%20Report.pdf | L49: Average budget for NIS Directive implementation projects | M49: Budget medio per organizzazione dedicato ai progetti di attuazione della direttiva NIS, campione di operatori di cinque Stati membri. | N49: Spesa o budget delle organizzazioni | O49: Media per organizzazione | P49: Segmento di offerta | Q49: Attuazione della direttiva NIS | R49: 175 | S49: migliaia | T49: EUR | U49: 2020 | V49: Consuntivo | X49: =IF(OR($S49="%",$R49=""),"",$R49*INDEX(Cambi!$J$2:$J$5,MATCH($S49,Cambi!$I$2:$I$5,0))/IF($T49="EUR",1,INDEX(Cambi!$D:$D,MATCH($T49&"|"&$U49,Cambi!$C:$C,0)))) -> 0.175 | Y49: Imprese e PA | Z49: Non specificato | AA49: hardware, software, personale interno, collaboratori, outsourcing (CAPEX e OPEX) | AB49: Domanda (end user) | AC49: Dichiarata | AD49: Non dichiarato | AE49: Survey a 251 operatori OES e DSP di Francia, Germania, Italia, Spagna e Polonia, correlata con dati Gartner globali ed europei non legati alla survey. | AF49: The average budget for NIS Directive implementation projects is approximately 175 K€, with 42.7% of affected organisations allocating between 100 and 250 K€. | AG49: B | AH49: Pubblico | AI49: Sì | AJ49: Letto da estratto indicizzato della pagina. Campione limitato a FR, DE, IT, ES e PL, registrato come EU27 in assenza di un codice dedicato. Anno di riferimento non esplicitato, dedotto dall'anno dell'indagine. Valore per singola organizzazione del campione NIS, non moltiplicabile per il numero di imprese. | AK49: 08/10/2026
A50: 49 | B50: ENISA-NISINV-2021 | C50: EU27 | D50: Unione europea (UE27) | E50: UE | F50: ENISA, Agenzia dell'Unione europea per la cibersicurezza | G50: Istituzione UE | H50: NIS Investments 2021 (seconda edizione) | I50: 17/11/2021 | J50: https://www.enisa.europa.eu/sites/default/files/publications/ENISA%20Report%20-%20NIS%20Investments%202021.pdf | L50: Average spending for information security of a typical OES/DSP | M50: Spesa media in sicurezza informatica per operatore OES o DSP nel 2020. | N50: Spesa o budget delle organizzazioni | O50: Media per organizzazione | P50: Nessuna | Q50: Totale | R50: 10.4 | S50: milioni | T50: EUR | U50: 2020 | V50: Consuntivo | X50: =IF(OR($S50="%",$R50=""),"",$R50*INDEX(Cambi!$J$2:$J$5,MATCH($S50,Cambi!$I$2:$I$5,0))/IF($T50="EUR",1,INDEX(Cambi!$D:$D,MATCH($T50&"|"&$U50,Cambi!$C:$C,0)))) -> 10.4 | Y50: Imprese e PA | Z50: Sì | AA50: hardware, software, personale interno, collaboratori, outsourcing (CAPEX e OPEX) | AB50: Domanda (end user) | AC50: Dichiarata | AD50: Non dichiarato | AE50: Survey di mercato dedicata a 947 organizzazioni identificate come OES o DSP, almeno 35 per Stato membro. Spesa 2020 autodichiarata comprensiva di CAPEX e OPEX per hardware, software, personale interno, collaboratori e outsourcing. Mediane e medie del campione. | AF50: median spending for information security of a typical OES/DSP was EUR 2 million in 2020, while the average spending was EUR 10.4 million | AG50: A | AH50: Pubblico | AI50: Sì | AJ50: Letto da estratto indicizzato della pagina. Valore per singola organizzazione del campione NIS, non moltiplicabile per il numero di imprese. | AK50: 08/10/2026
A51: 50 | B51: ENISA-NISINV-2021 | C51: EU27 | D51: Unione europea (UE27) | E51: UE | F51: ENISA, Agenzia dell'Unione europea per la cibersicurezza | G51: Istituzione UE | H51: NIS Investments 2021 (seconda edizione) | I51: 17/11/2021 | J51: https://www.enisa.europa.eu/sites/default/files/publications/ENISA%20Report%20-%20NIS%20Investments%202021.pdf | L51: Information security spending as a share of IT spending (average) | M51: Quota media della spesa di sicurezza sul budget IT degli operatori OES e DSP nel 2020. | N51: Rapporto di spesa | O51: Quota percentuale | P51: Nessuna | Q51: Totale | R51: 8.8 | S51: % | U51: 2020 | V51: Consuntivo | X51: =IF(OR($S51="%",$R51=""),"",$R51*INDEX(Cambi!$J$2:$J$5,MATCH($S51,Cambi!$I$2:$I$5,0))/IF($T51="EUR",1,INDEX(Cambi!$D:$D,MATCH($T51&"|"&$U51,Cambi!$C:$C,0)))) | Y51: Imprese e PA | Z51: Sì | AA51: hardware, software, personale interno, collaboratori, outsourcing (CAPEX e OPEX) | AB51: Domanda (end user) | AC51: Dichiarata | AD51: Non dichiarato | AE51: Survey di mercato dedicata a 947 organizzazioni identificate come OES o DSP, almeno 35 per Stato membro. Spesa 2020 autodichiarata comprensiva di CAPEX e OPEX per hardware, software, personale interno, collaboratori e outsourcing. Mediane e medie del campione. | AF51: a typical OES/DSP in the EU earmarks 7.7 % of its IT investments for information security, while the average value is 8.8 % | AG51: A | AH51: Pubblico | AI51: Sì | AJ51: Letto da estratto indicizzato della pagina. | AK51: 08/10/2026
A52: 51 | B52: ENISA-NISINV-2021 | C52: EU27 | D52: Unione europea (UE27) | E52: UE | F52: ENISA, Agenzia dell'Unione europea per la cibersicurezza | G52: Istituzione UE | H52: NIS Investments 2021 (seconda edizione) | I52: 17/11/2021 | J52: https://www.enisa.europa.eu/sites/default/files/publications/ENISA%20Report%20-%20NIS%20Investments%202021.pdf | L52: Information security spending as a share of IT spending (median) | M52: Quota mediana della spesa di sicurezza sul budget IT degli operatori OES e DSP nel 2020. | N52: Rapporto di spesa | O52: Quota percentuale | P52: Nessuna | Q52: Totale | R52: 7.7 | S52: % | U52: 2020 | V52: Consuntivo | X52: =IF(OR($S52="%",$R52=""),"",$R52*INDEX(Cambi!$J$2:$J$5,MATCH($S52,Cambi!$I$2:$I$5,0))/IF($T52="EUR",1,INDEX(Cambi!$D:$D,MATCH($T52&"|"&$U52,Cambi!$C:$C,0)))) | Y52: Imprese e PA | Z52: Sì | AA52: hardware, software, personale interno, collaboratori, outsourcing (CAPEX e OPEX) | AB52: Domanda (end user) | AC52: Dichiarata | AD52: Non dichiarato | AE52: Survey di mercato dedicata a 947 organizzazioni identificate come OES o DSP, almeno 35 per Stato membro. Spesa 2020 autodichiarata comprensiva di CAPEX e OPEX per hardware, software, personale interno, collaboratori e outsourcing. Mediane e medie del campione. | AF52: a typical OES/DSP in the EU earmarks 7.7 % of its IT investments for information security, while the average value is 8.8 % | AG52: A | AH52: Pubblico | AI52: Sì | AJ52: Letto da estratto indicizzato della pagina. Verifica finale 08/10/2026, valore confermato sulla fonte. Mediana per organizzazione su dati 2020. | AK52: 08/10/2026
A53: 52 | B53: ENISA-NISINV-2021 | C53: EU27 | D53: Unione europea (UE27) | E53: UE | F53: ENISA, Agenzia dell'Unione europea per la cibersicurezza | G53: Istituzione UE | H53: NIS Investments 2021 (seconda edizione) | I53: 17/11/2021 | J53: https://www.enisa.europa.eu/sites/default/files/publications/ENISA%20Report%20-%20NIS%20Investments%202021.pdf | L53: Information security spending per sector (median) | M53: Spesa mediana in sicurezza informatica per operatore del settore banche nel 2020. | N53: Spesa o budget delle organizzazioni | O53: Mediana per organizzazione | P53: Settore | Q53: Banche | R53: 4 | S53: milioni | T53: EUR | U53: 2020 | V53: Consuntivo | X53: =IF(OR($S53="%",$R53=""),"",$R53*INDEX(Cambi!$J$2:$J$5,MATCH($S53,Cambi!$I$2:$I$5,0))/IF($T53="EUR",1,INDEX(Cambi!$D:$D,MATCH($T53&"|"&$U53,Cambi!$C:$C,0)))) -> 4 | Y53: Imprese e PA | Z53: Sì | AA53: hardware, software, personale interno, collaboratori, outsourcing (CAPEX e OPEX) | AB53: Domanda (end user) | AC53: Dichiarata | AD53: Non dichiarato | AE53: Survey di mercato dedicata a 947 organizzazioni identificate come OES o DSP, almeno 35 per Stato membro. Spesa 2020 autodichiarata comprensiva di CAPEX e OPEX per hardware, software, personale interno, collaboratori e outsourcing. Mediane e medie del campione. | AF53: the banking sector (EUR 4 million) and the energy sector (EUR 3 million) account for the highest median spending per sector. | AG53: A | AH53: Pubblico | AI53: Sì | AJ53: Letto da estratto indicizzato della pagina. Valore per singola organizzazione del campione NIS, non moltiplicabile per il numero di imprese. | AK53: 08/10/2026
A54: 53 | B54: ENISA-NISINV-2021 | C54: EU27 | D54: Unione europea (UE27) | E54: UE | F54: ENISA, Agenzia dell'Unione europea per la cibersicurezza | G54: Istituzione UE | H54: NIS Investments 2021 (seconda edizione) | I54: 17/11/2021 | J54: https://www.enisa.europa.eu/sites/default/files/publications/ENISA%20Report%20-%20NIS%20Investments%202021.pdf | L54: Information security spending per sector (median) | M54: Spesa mediana in sicurezza informatica per operatore del settore energia nel 2020. | N54: Spesa o budget delle organizzazioni | O54: Mediana per organizzazione | P54: Settore | Q54: Energia | R54: 3 | S54: milioni | T54: EUR | U54: 2020 | V54: Consuntivo | X54: =IF(OR($S54="%",$R54=""),"",$R54*INDEX(Cambi!$J$2:$J$5,MATCH($S54,Cambi!$I$2:$I$5,0))/IF($T54="EUR",1,INDEX(Cambi!$D:$D,MATCH($T54&"|"&$U54,Cambi!$C:$C,0)))) -> 3 | Y54: Imprese e PA | Z54: Sì | AA54: hardware, software, personale interno, collaboratori, outsourcing (CAPEX e OPEX) | AB54: Domanda (end user) | AC54: Dichiarata | AD54: Non dichiarato | AE54: Survey di mercato dedicata a 947 organizzazioni identificate come OES o DSP, almeno 35 per Stato membro. Spesa 2020 autodichiarata comprensiva di CAPEX e OPEX per hardware, software, personale interno, collaboratori e outsourcing. Mediane e medie del campione. | AF54: the banking sector (EUR 4 million) and the energy sector (EUR 3 million) account for the highest median spending per sector. | AG54: A | AH54: Pubblico | AI54: Sì | AJ54: Letto da estratto indicizzato della pagina. Valore per singola organizzazione del campione NIS, non moltiplicabile per il numero di imprese. Verifica finale 08/10/2026, valore confermato sulla fonte. Mediana per organizzazione del settore energia. | AK54: 08/10/2026
A55: 54 | B55: ENISA-NISINV-2021 | C55: EU27 | D55: Unione europea (UE27) | E55: UE | F55: ENISA, Agenzia dell'Unione europea per la cibersicurezza | G55: Istituzione UE | H55: NIS Investments 2021 (seconda edizione) | I55: 17/11/2021 | J55: https://www.enisa.europa.eu/sites/default/files/publications/ENISA%20Report%20-%20NIS%20Investments%202021.pdf | L55: Median spending for information security of a typical OES/DSP | M55: Spesa mediana in sicurezza informatica per operatore OES o DSP nel 2020. | N55: Spesa o budget delle organizzazioni | O55: Mediana per organizzazione | P55: Nessuna | Q55: Totale | R55: 2 | S55: milioni | T55: EUR | U55: 2020 | V55: Consuntivo | X55: =IF(OR($S55="%",$R55=""),"",$R55*INDEX(Cambi!$J$2:$J$5,MATCH($S55,Cambi!$I$2:$I$5,0))/IF($T55="EUR",1,INDEX(Cambi!$D:$D,MATCH($T55&"|"&$U55,Cambi!$C:$C,0)))) -> 2 | Y55: Imprese e PA | Z55: Sì | AA55: hardware, software, personale interno, collaboratori, outsourcing (CAPEX e OPEX) | AB55: Domanda (end user) | AC55: Dichiarata | AD55: Non dichiarato | AE55: Survey di mercato dedicata a 947 organizzazioni identificate come OES o DSP, almeno 35 per Stato membro. Spesa 2020 autodichiarata comprensiva di CAPEX e OPEX per hardware, software, personale interno, collaboratori e outsourcing. Mediane e medie del campione. | AF55: median spending for information security of a typical OES/DSP was EUR 2 million in 2020, while the average spending was EUR 10.4 million | AG55: A | AH55: Pubblico | AI55: Sì | AJ55: Letto da estratto indicizzato della pagina. Valore per singola organizzazione del campione NIS, non moltiplicabile per il numero di imprese. Valori 2020 molto superiori a quelli 2021 dell'edizione successiva, segno di forte variabilità campionaria. | AK55: 08/10/2026
A56: 55 | B56: ENISA-NISINV-2021 | C56: EU27 | D56: Unione europea (UE27) | E56: UE | F56: ENISA, Agenzia dell'Unione europea per la cibersicurezza | G56: Istituzione UE | H56: NIS Investments 2021 (seconda edizione) | I56: 17/11/2021 | J56: https://www.enisa.europa.eu/sites/default/files/publications/ENISA%20Report%20-%20NIS%20Investments%202021.pdf | L56: NIS Directive implementation spending as share of information security spending (median) | M56: Quota mediana della spesa per l'attuazione della direttiva NIS sulla spesa complessiva di sicurezza nel 2020. | N56: Rapporto di spesa | O56: Quota percentuale | P56: Segmento di offerta | Q56: Attuazione della direttiva NIS | R56: 5.1 | S56: % | U56: 2020 | V56: Consuntivo | X56: =IF(OR($S56="%",$R56=""),"",$R56*INDEX(Cambi!$J$2:$J$5,MATCH($S56,Cambi!$I$2:$I$5,0))/IF($T56="EUR",1,INDEX(Cambi!$D:$D,MATCH($T56&"|"&$U56,Cambi!$C:$C,0)))) | Y56: Imprese e PA | Z56: Sì | AA56: hardware, software, personale interno, collaboratori, outsourcing (CAPEX e OPEX) | AB56: Domanda (end user) | AC56: Dichiarata | AD56: Non dichiarato | AE56: Survey di mercato dedicata a 947 organizzazioni identificate come OES o DSP, almeno 35 per Stato membro. Spesa 2020 autodichiarata comprensiva di CAPEX e OPEX per hardware, software, personale interno, collaboratori e outsourcing. Mediane e medie del campione. | AF56: spending on implementing the NIS directive within an OES/DSP amounts to 5.1 % of their overall information security spending | AG56: A | AH56: Pubblico | AI56: Sì | AJ56: Letto da estratto indicizzato della pagina. Verifica finale 08/10/2026, valore confermato sulla fonte. Mediana, la media è 10,5 per cento. | AK56: 08/10/2026
A57: 56 | B57: ENISA-NISINV-2021 | C57: EU27 | D57: Unione europea (UE27) | E57: UE | F57: ENISA, Agenzia dell'Unione europea per la cibersicurezza | G57: Istituzione UE | H57: NIS Investments 2021 (seconda edizione) | I57: 17/11/2021 | J57: https://www.enisa.europa.eu/sites/default/files/publications/ENISA%20Report%20-%20NIS%20Investments%202021.pdf | L57: Spending on implementing the NIS Directive (average) | M57: Spesa media per operatore dedicata all'attuazione dei requisiti della direttiva NIS nel 2020. | N57: Spesa o budget delle organizzazioni | O57: Media per organizzazione | P57: Segmento di offerta | Q57: Attuazione della direttiva NIS | R57: 98000 | S57: unità | T57: EUR | U57: 2020 | V57: Consuntivo | X57: =IF(OR($S57="%",$R57=""),"",$R57*INDEX(Cambi!$J$2:$J$5,MATCH($S57,Cambi!$I$2:$I$5,0))/IF($T57="EUR",1,INDEX(Cambi!$D:$D,MATCH($T57&"|"&$U57,Cambi!$C:$C,0)))) -> 0.098 | Y57: Imprese e PA | Z57: Sì | AA57: hardware, software, personale interno, collaboratori, outsourcing (CAPEX e OPEX) | AB57: Domanda (end user) | AC57: Dichiarata | AD57: Non dichiarato | AE57: Survey di mercato dedicata a 947 organizzazioni identificate come OES o DSP, almeno 35 per Stato membro. Spesa 2020 autodichiarata comprensiva di CAPEX e OPEX per hardware, software, personale interno, collaboratori e outsourcing. Mediane e medie del campione. | AF57: a typical OES/DSP in the EU spends EUR 40 000 on implementing the NIS Directive, while on average the spending amounts to EUR 98 000 | AG57: A | AH57: Pubblico | AI57: Sì | AJ57: Letto da estratto indicizzato della pagina. Valore per singola organizzazione del campione NIS, non moltiplicabile per il numero di imprese. | AK57: 08/10/2026
A58: 57 | B58: ENISA-NISINV-2021 | C58: EU27 | D58: Unione europea (UE27) | E58: UE | F58: ENISA, Agenzia dell'Unione europea per la cibersicurezza | G58: Istituzione UE | H58: NIS Investments 2021 (seconda edizione) | I58: 17/11/2021 | J58: https://www.enisa.europa.eu/sites/default/files/publications/ENISA%20Report%20-%20NIS%20Investments%202021.pdf | L58: Spending on implementing the NIS Directive (median) | M58: Spesa mediana per operatore dedicata all'attuazione dei requisiti della direttiva NIS nel 2020, quota della spesa di sicurezza. | N58: Spesa o budget delle organizzazioni | O58: Mediana per organizzazione | P58: Segmento di offerta | Q58: Attuazione della direttiva NIS | R58: 40000 | S58: unità | T58: EUR | U58: 2020 | V58: Consuntivo | X58: =IF(OR($S58="%",$R58=""),"",$R58*INDEX(Cambi!$J$2:$J$5,MATCH($S58,Cambi!$I$2:$I$5,0))/IF($T58="EUR",1,INDEX(Cambi!$D:$D,MATCH($T58&"|"&$U58,Cambi!$C:$C,0)))) -> 0.04 | Y58: Imprese e PA | Z58: Sì | AA58: hardware, software, personale interno, collaboratori, outsourcing (CAPEX e OPEX) | AB58: Domanda (end user) | AC58: Dichiarata | AD58: Non dichiarato | AE58: Survey di mercato dedicata a 947 organizzazioni identificate come OES o DSP, almeno 35 per Stato membro. Spesa 2020 autodichiarata comprensiva di CAPEX e OPEX per hardware, software, personale interno, collaboratori e outsourcing. Mediane e medie del campione. | AF58: a typical OES/DSP in the EU spends EUR 40 000 on implementing the NIS Directive, while on average the spending amounts to EUR 98 000 | AG58: A | AH58: Pubblico | AI58: Sì | AJ58: Letto da estratto indicizzato della pagina. Sottoinsieme della spesa di sicurezza. Valore per singola organizzazione del campione NIS, non moltiplicabile per il numero di imprese. | AK58: 08/10/2026
A59: 58 | B59: ENISA-NISINV-2022 | C59: EU27 | D59: Unione europea (UE27) | E59: UE | F59: ENISA, Agenzia dell'Unione europea per la cibersicurezza | G59: Istituzione UE | H59: NIS Investments 2022 (terza edizione) | I59: 23/11/2022 | J59: https://www.enisa.europa.eu/sites/default/files/publications/NIS%20Investments%202022.pdf | L59: Average percentage of IT budgets spent on IS | M59: Quota media della spesa di sicurezza sul budget IT degli operatori OES e DSP nel 2021. | N59: Rapporto di spesa | O59: Quota percentuale | P59: Nessuna | Q59: Totale | R59: 7.2 | S59: % | U59: 2021 | V59: Consuntivo | X59: =IF(OR($S59="%",$R59=""),"",$R59*INDEX(Cambi!$J$2:$J$5,MATCH($S59,Cambi!$I$2:$I$5,0))/IF($T59="EUR",1,INDEX(Cambi!$D:$D,MATCH($T59&"|"&$U59,Cambi!$C:$C,0)))) | Y59: Imprese e PA | Z59: Sì | AA59: hardware, software, personale interno, collaboratori, outsourcing (CAPEX e OPEX) | AB59: Domanda (end user) | AC59: Dichiarata | AD59: Non dichiarato | AE59: Survey dedicata a 1080 operatori OES e DSP dei 27 Stati membri. Spesa 2021 autodichiarata. Mediane e medie del campione, senza riporto all'universo. Gartner partner dello studio. | AF59: an OES or DSP in the EU earmarks 6.7% of its IT investments for information security, while the average value is 7.2% | AG59: B | AH59: Pubblico | AI59: Sì | AJ59: Letto da estratto indicizzato della pagina. Verifica finale 08/10/2026, valore confermato sulla fonte. Valore medio 7,2 per cento riferito al 2021, survey presso operatori OES e DSP. | AK59: 08/10/2026
A60: 59 | B60: ENISA-NISINV-2022 | C60: EU27 | D60: Unione europea (UE27) | E60: UE | F60: ENISA, Agenzia dell'Unione europea per la cibersicurezza | G60: Istituzione UE | H60: NIS Investments 2022 (terza edizione) | I60: 23/11/2022 | J60: https://www.enisa.europa.eu/sites/default/files/publications/NIS%20Investments%202022.pdf | L60: Average spending for information security (IS) of an OES or DSP | M60: Spesa media in sicurezza informatica per operatore OES o DSP nel 2021. | N60: Spesa o budget delle organizzazioni | O60: Media per organizzazione | P60: Nessuna | Q60: Totale | R60: 4 | S60: milioni | T60: EUR | U60: 2021 | V60: Consuntivo | X60: =IF(OR($S60="%",$R60=""),"",$R60*INDEX(Cambi!$J$2:$J$5,MATCH($S60,Cambi!$I$2:$I$5,0))/IF($T60="EUR",1,INDEX(Cambi!$D:$D,MATCH($T60&"|"&$U60,Cambi!$C:$C,0)))) -> 4 | Y60: Imprese e PA | Z60: Sì | AA60: hardware, software, personale interno, collaboratori, outsourcing (CAPEX e OPEX) | AB60: Domanda (end user) | AC60: Dichiarata | AD60: Non dichiarato | AE60: Survey dedicata a 1080 operatori OES e DSP dei 27 Stati membri. Spesa 2021 autodichiarata. Mediane e medie del campione, senza riporto all'universo. Gartner partner dello studio. | AF60: median spending for information security (IS) of an OES or DSP was EUR 600 000 in 2021, while the average spending was EUR 4 million | AG60: B | AH60: Pubblico | AI60: Sì | AJ60: Letto da estratto indicizzato della pagina. Valore per singola organizzazione del campione NIS, non moltiplicabile per il numero di imprese. Inclusione del personale interno dedotta per continuità con il questionario delle edizioni 2021 e 2023, che la dichiarano. | AK60: 08/10/2026
A61: 60 | B61: ENISA-NISINV-2022 | C61: EU27 | D61: Unione europea (UE27) | E61: UE | F61: ENISA, Agenzia dell'Unione europea per la cibersicurezza | G61: Istituzione UE | H61: NIS Investments 2022 (terza edizione) | I61: 23/11/2022 | J61: https://www.enisa.europa.eu/sites/default/files/publications/NIS%20Investments%202022.pdf | L61: CTI spending of an OES or DSP (average) | M61: Spesa media in cyber threat intelligence per operatore OES o DSP nel 2021. | N61: Spesa o budget delle organizzazioni | O61: Media per organizzazione | P61: Segmento di offerta | Q61: Cyber threat intelligence | R61: 399000 | S61: unità | T61: EUR | U61: 2021 | V61: Consuntivo | X61: =IF(OR($S61="%",$R61=""),"",$R61*INDEX(Cambi!$J$2:$J$5,MATCH($S61,Cambi!$I$2:$I$5,0))/IF($T61="EUR",1,INDEX(Cambi!$D:$D,MATCH($T61&"|"&$U61,Cambi!$C:$C,0)))) -> 0.399 | Y61: Imprese e PA | Z61: Sì | AA61: Cyber threat intelligence | AB61: Domanda (end user) | AC61: Dichiarata | AD61: Non dichiarato | AE61: Survey dedicata a 1080 operatori OES e DSP dei 27 Stati membri. Spesa 2021 autodichiarata. Mediane e medie del campione, senza riporto all'universo. Gartner partner dello studio. | AF61: On median, an OES or DSP in the EU spends EUR 50 000 on CTI, while the average spending amounts to EUR 399 000. | AG61: B | AH61: Pubblico | AI61: Sì | AJ61: Letto da estratto indicizzato della pagina. Valore per singola organizzazione del campione NIS, non moltiplicabile per il numero di imprese. | AK61: 08/10/2026
A62: 61 | B62: ENISA-NISINV-2022 | C62: EU27 | D62: Unione europea (UE27) | E62: UE | F62: ENISA, Agenzia dell'Unione europea per la cibersicurezza | G62: Istituzione UE | H62: NIS Investments 2022 (terza edizione) | I62: 23/11/2022 | J62: https://www.enisa.europa.eu/sites/default/files/publications/NIS%20Investments%202022.pdf | L62: CTI spending of an OES or DSP (median) | M62: Spesa mediana in cyber threat intelligence per operatore OES o DSP nel 2021, componente della spesa di sicurezza. | N62: Spesa o budget delle organizzazioni | O62: Mediana per organizzazione | P62: Segmento di offerta | Q62: Cyber threat intelligence | R62: 50000 | S62: unità | T62: EUR | U62: 2021 | V62: Consuntivo | X62: =IF(OR($S62="%",$R62=""),"",$R62*INDEX(Cambi!$J$2:$J$5,MATCH($S62,Cambi!$I$2:$I$5,0))/IF($T62="EUR",1,INDEX(Cambi!$D:$D,MATCH($T62&"|"&$U62,Cambi!$C:$C,0)))) -> 0.05 | Y62: Imprese e PA | Z62: Sì | AA62: Cyber threat intelligence | AB62: Domanda (end user) | AC62: Dichiarata | AD62: Non dichiarato | AE62: Survey dedicata a 1080 operatori OES e DSP dei 27 Stati membri. Spesa 2021 autodichiarata. Mediane e medie del campione, senza riporto all'universo. Gartner partner dello studio. | AF62: On median, an OES or DSP in the EU spends EUR 50 000 on CTI, while the average spending amounts to EUR 399 000. | AG62: B | AH62: Pubblico | AI62: Sì | AJ62: Letto da estratto indicizzato della pagina. Valore per singola organizzazione del campione NIS, non moltiplicabile per il numero di imprese. Verifica finale 08/10/2026, valore confermato sulla fonte. Mediana della spesa in threat intelligence riferita al 2021. | AK62: 08/10/2026
A63: 62 | B63: ENISA-NISINV-2022 | C63: EU27 | D63: Unione europea (UE27) | E63: UE | F63: ENISA, Agenzia dell'Unione europea per la cibersicurezza | G63: Istituzione UE | H63: NIS Investments 2022 (terza edizione) | I63: 23/11/2022 | J63: https://www.enisa.europa.eu/sites/default/files/publications/NIS%20Investments%202022.pdf | L63: IS spending per sector (median) | M63: Spesa mediana in sicurezza informatica per operatore del settore banche nel 2021. | N63: Spesa o budget delle organizzazioni | O63: Mediana per organizzazione | P63: Settore | Q63: Banche | R63: 2.5 | S63: milioni | T63: EUR | U63: 2021 | V63: Consuntivo | X63: =IF(OR($S63="%",$R63=""),"",$R63*INDEX(Cambi!$J$2:$J$5,MATCH($S63,Cambi!$I$2:$I$5,0))/IF($T63="EUR",1,INDEX(Cambi!$D:$D,MATCH($T63&"|"&$U63,Cambi!$C:$C,0)))) -> 2.5 | Y63: Imprese e PA | Z63: Sì | AA63: hardware, software, personale interno, collaboratori, outsourcing (CAPEX e OPEX) | AB63: Domanda (end user) | AC63: Dichiarata | AD63: Non dichiarato | AE63: Survey dedicata a 1080 operatori OES e DSP dei 27 Stati membri. Spesa 2021 autodichiarata. Mediane e medie del campione, senza riporto all'universo. Gartner partner dello studio. | AF63: the Banking sector (EUR 2.5 million) has the highest IS spending, followed by the Healthcare (EUR 1.2 million) and Energy sectors (EUR 1.0 million). | AG63: B | AH63: Pubblico | AI63: Sì | AJ63: Letto da estratto indicizzato della pagina. Valore per singola organizzazione del campione NIS, non moltiplicabile per il numero di imprese. | AK63: 08/10/2026
A64: 63 | B64: ENISA-NISINV-2022 | C64: EU27 | D64: Unione europea (UE27) | E64: UE | F64: ENISA, Agenzia dell'Unione europea per la cibersicurezza | G64: Istituzione UE | H64: NIS Investments 2022 (terza edizione) | I64: 23/11/2022 | J64: https://www.enisa.europa.eu/sites/default/files/publications/NIS%20Investments%202022.pdf | L64: IS spending per sector (median) | M64: Spesa mediana in sicurezza informatica per operatore del settore energia nel 2021. | N64: Spesa o budget delle organizzazioni | O64: Mediana per organizzazione | P64: Settore | Q64: Energia | R64: 1 | S64: milioni | T64: EUR | U64: 2021 | V64: Consuntivo | X64: =IF(OR($S64="%",$R64=""),"",$R64*INDEX(Cambi!$J$2:$J$5,MATCH($S64,Cambi!$I$2:$I$5,0))/IF($T64="EUR",1,INDEX(Cambi!$D:$D,MATCH($T64&"|"&$U64,Cambi!$C:$C,0)))) -> 1 | Y64: Imprese e PA | Z64: Sì | AA64: hardware, software, personale interno, collaboratori, outsourcing (CAPEX e OPEX) | AB64: Domanda (end user) | AC64: Dichiarata | AD64: Non dichiarato | AE64: Survey dedicata a 1080 operatori OES e DSP dei 27 Stati membri. Spesa 2021 autodichiarata. Mediane e medie del campione, senza riporto all'universo. Gartner partner dello studio. | AF64: the Banking sector (EUR 2.5 million) has the highest IS spending, followed by the Healthcare (EUR 1.2 million) and Energy sectors (EUR 1.0 million). | AG64: B | AH64: Pubblico | AI64: Sì | AJ64: Letto da estratto indicizzato della pagina. Valore per singola organizzazione del campione NIS, non moltiplicabile per il numero di imprese. | AK64: 08/10/2026
A65: 64 | B65: ENISA-NISINV-2022 | C65: EU27 | D65: Unione europea (UE27) | E65: UE | F65: ENISA, Agenzia dell'Unione europea per la cibersicurezza | G65: Istituzione UE | H65: NIS Investments 2022 (terza edizione) | I65: 23/11/2022 | J65: https://www.enisa.europa.eu/sites/default/files/publications/NIS%20Investments%202022.pdf | L65: IS spending per sector (median) | M65: Spesa mediana in sicurezza informatica per operatore del settore sanità nel 2021. | N65: Spesa o budget delle organizzazioni | O65: Mediana per organizzazione | P65: Settore | Q65: Sanità | R65: 1.2 | S65: milioni | T65: EUR | U65: 2021 | V65: Consuntivo | X65: =IF(OR($S65="%",$R65=""),"",$R65*INDEX(Cambi!$J$2:$J$5,MATCH($S65,Cambi!$I$2:$I$5,0))/IF($T65="EUR",1,INDEX(Cambi!$D:$D,MATCH($T65&"|"&$U65,Cambi!$C:$C,0)))) -> 1.2 | Y65: Imprese e PA | Z65: Sì | AA65: hardware, software, personale interno, collaboratori, outsourcing (CAPEX e OPEX) | AB65: Domanda (end user) | AC65: Dichiarata | AD65: Non dichiarato | AE65: Survey dedicata a 1080 operatori OES e DSP dei 27 Stati membri. Spesa 2021 autodichiarata. Mediane e medie del campione, senza riporto all'universo. Gartner partner dello studio. | AF65: the Banking sector (EUR 2.5 million) has the highest IS spending, followed by the Healthcare (EUR 1.2 million) and Energy sectors (EUR 1.0 million). | AG65: B | AH65: Pubblico | AI65: Sì | AJ65: Letto da estratto indicizzato della pagina. Valore per singola organizzazione del campione NIS, non moltiplicabile per il numero di imprese. Verifica finale 08/10/2026, valore confermato sulla fonte. Mediana settoriale sanità 1,2 milioni EUR, dati 2021 da survey presso gli operatori. | AK65: 08/10/2026
A66: 65 | B66: ENISA-NISINV-2022 | C66: EU27 | D66: Unione europea (UE27) | E66: UE | F66: ENISA, Agenzia dell'Unione europea per la cibersicurezza | G66: Istituzione UE | H66: NIS Investments 2022 (terza edizione) | I66: 23/11/2022 | J66: https://www.enisa.europa.eu/sites/default/files/publications/NIS%20Investments%202022.pdf | L66: IS spending per sector (median), Digital Infrastructure and Online Search Engines | M66: Spesa mediana in sicurezza informatica degli operatori di infrastrutture digitali e motori di ricerca nel 2021. | N66: Spesa o budget delle organizzazioni | O66: Mediana per organizzazione | P66: Settore | Q66: Infrastrutture digitali e motori di ricerca online | R66: 100000 | S66: unità | T66: EUR | U66: 2021 | V66: Consuntivo | X66: =IF(OR($S66="%",$R66=""),"",$R66*INDEX(Cambi!$J$2:$J$5,MATCH($S66,Cambi!$I$2:$I$5,0))/IF($T66="EUR",1,INDEX(Cambi!$D:$D,MATCH($T66&"|"&$U66,Cambi!$C:$C,0)))) -> 0.1 | Y66: Imprese e PA | Z66: Sì | AA66: hardware, software, personale interno, collaboratori, outsourcing (CAPEX e OPEX) | AB66: Domanda (end user) | AC66: Dichiarata | AD66: Non dichiarato | AE66: Survey dedicata a 1080 operatori OES e DSP dei 27 Stati membri. Spesa 2021 autodichiarata. Mediane e medie del campione, senza riporto all'universo. Gartner partner dello studio. | AF66: the information security spend of Digital Infrastructure and Online Search Engine companies is the lowest, amounting to a median spending of EUR 100 000. | AG66: B | AH66: Pubblico | AI66: Sì | AJ66: Letto da estratto indicizzato della pagina. Valore per singola organizzazione del campione NIS, non moltiplicabile per il numero di imprese. Verifica finale 08/10/2026, valore confermato sulla fonte. Mediana 100 000 EUR riferita al 2021. | AK66: 08/10/2026
A67: 66 | B67: ENISA-NISINV-2022 | C67: EU27 | D67: Unione europea (UE27) | E67: UE | F67: ENISA, Agenzia dell'Unione europea per la cibersicurezza | G67: Istituzione UE | H67: NIS Investments 2022 (terza edizione) | I67: 23/11/2022 | J67: https://www.enisa.europa.eu/sites/default/files/publications/NIS%20Investments%202022.pdf | L67: IS vs IT spending per sector (median) | M67: Quota della spesa di sicurezza sul budget IT nel settore cloud computing nel 2021. | N67: Rapporto di spesa | O67: Quota percentuale | P67: Settore | Q67: Cloud computing | R67: 8.5 | S67: % | U67: 2021 | V67: Consuntivo | X67: =IF(OR($S67="%",$R67=""),"",$R67*INDEX(Cambi!$J$2:$J$5,MATCH($S67,Cambi!$I$2:$I$5,0))/IF($T67="EUR",1,INDEX(Cambi!$D:$D,MATCH($T67&"|"&$U67,Cambi!$C:$C,0)))) | Y67: Imprese e PA | Z67: Sì | AA67: hardware, software, personale interno, collaboratori, outsourcing (CAPEX e OPEX) | AB67: Domanda (end user) | AC67: Dichiarata | AD67: Non dichiarato | AE67: Survey dedicata a 1080 operatori OES e DSP dei 27 Stati membri. Spesa 2021 autodichiarata. Mediane e medie del campione, senza riporto all'universo. Gartner partner dello studio. | AF67: Digital Infrastructures maintain the highest IS vs IT spending (10%) in 2021, followed closely by Online Marketplaces (8.8%) and Cloud Computing (8.5%). | AG67: B | AH67: Pubblico | AI67: Sì | AJ67: Letto da estratto indicizzato della pagina. Non è esplicitato se si tratti di mediana o media, il capitolo usa di norma la mediana. Verifica finale 08/10/2026, valore confermato sulla fonte. Quota della spesa IS sulla spesa IT nel cloud computing, anno 2021. | AK67: 08/10/2026
A68: 67 | B68: ENISA-NISINV-2022 | C68: EU27 | D68: Unione europea (UE27) | E68: UE | F68: ENISA, Agenzia dell'Unione europea per la cibersicurezza | G68: Istituzione UE | H68: NIS Investments 2022 (terza edizione) | I68: 23/11/2022 | J68: https://www.enisa.europa.eu/sites/default/files/publications/NIS%20Investments%202022.pdf | L68: IS vs IT spending per sector (median) | M68: Quota della spesa di sicurezza sul budget IT nel settore infrastrutture digitali nel 2021. | N68: Rapporto di spesa | O68: Quota percentuale | P68: Settore | Q68: Infrastrutture digitali | R68: 10 | S68: % | U68: 2021 | V68: Consuntivo | X68: =IF(OR($S68="%",$R68=""),"",$R68*INDEX(Cambi!$J$2:$J$5,MATCH($S68,Cambi!$I$2:$I$5,0))/IF($T68="EUR",1,INDEX(Cambi!$D:$D,MATCH($T68&"|"&$U68,Cambi!$C:$C,0)))) | Y68: Imprese e PA | Z68: Sì | AA68: hardware, software, personale interno, collaboratori, outsourcing (CAPEX e OPEX) | AB68: Domanda (end user) | AC68: Dichiarata | AD68: Non dichiarato | AE68: Survey dedicata a 1080 operatori OES e DSP dei 27 Stati membri. Spesa 2021 autodichiarata. Mediane e medie del campione, senza riporto all'universo. Gartner partner dello studio. | AF68: Digital Infrastructures maintain the highest IS vs IT spending (10%) in 2021, followed closely by Online Marketplaces (8.8%) and Cloud Computing (8.5%). | AG68: B | AH68: Pubblico | AI68: Sì | AJ68: Letto da estratto indicizzato della pagina. Non è esplicitato se si tratti di mediana o media, il capitolo usa di norma la mediana. | AK68: 08/10/2026
A69: 68 | B69: ENISA-NISINV-2022 | C69: EU27 | D69: Unione europea (UE27) | E69: UE | F69: ENISA, Agenzia dell'Unione europea per la cibersicurezza | G69: Istituzione UE | H69: NIS Investments 2022 (terza edizione) | I69: 23/11/2022 | J69: https://www.enisa.europa.eu/sites/default/files/publications/NIS%20Investments%202022.pdf | L69: IS vs IT spending per sector (median) | M69: Quota della spesa di sicurezza sul budget IT nel settore mercati online nel 2021. | N69: Rapporto di spesa | O69: Quota percentuale | P69: Settore | Q69: Mercati online | R69: 8.8 | S69: % | U69: 2021 | V69: Consuntivo | X69: =IF(OR($S69="%",$R69=""),"",$R69*INDEX(Cambi!$J$2:$J$5,MATCH($S69,Cambi!$I$2:$I$5,0))/IF($T69="EUR",1,INDEX(Cambi!$D:$D,MATCH($T69&"|"&$U69,Cambi!$C:$C,0)))) | Y69: Imprese e PA | Z69: Sì | AA69: hardware, software, personale interno, collaboratori, outsourcing (CAPEX e OPEX) | AB69: Domanda (end user) | AC69: Dichiarata | AD69: Non dichiarato | AE69: Survey dedicata a 1080 operatori OES e DSP dei 27 Stati membri. Spesa 2021 autodichiarata. Mediane e medie del campione, senza riporto all'universo. Gartner partner dello studio. | AF69: Digital Infrastructures maintain the highest IS vs IT spending (10%) in 2021, followed closely by Online Marketplaces (8.8%) and Cloud Computing (8.5%). | AG69: B | AH69: Pubblico | AI69: Sì | AJ69: Letto da estratto indicizzato della pagina. Non è esplicitato se si tratti di mediana o media, il capitolo usa di norma la mediana. | AK69: 08/10/2026
A70: 69 | B70: ENISA-NISINV-2022 | C70: EU27 | D70: Unione europea (UE27) | E70: UE | F70: ENISA, Agenzia dell'Unione europea per la cibersicurezza | G70: Istituzione UE | H70: NIS Investments 2022 (terza edizione) | I70: 23/11/2022 | J70: https://www.enisa.europa.eu/sites/default/files/publications/NIS%20Investments%202022.pdf | L70: Median percentage of IT budgets spent on IS | M70: Quota mediana della spesa di sicurezza sul budget IT degli operatori OES e DSP nel 2021, in calo di un punto. | N70: Rapporto di spesa | O70: Quota percentuale | P70: Nessuna | Q70: Totale | R70: 6.7 | S70: % | U70: 2021 | V70: Consuntivo | X70: =IF(OR($S70="%",$R70=""),"",$R70*INDEX(Cambi!$J$2:$J$5,MATCH($S70,Cambi!$I$2:$I$5,0))/IF($T70="EUR",1,INDEX(Cambi!$D:$D,MATCH($T70&"|"&$U70,Cambi!$C:$C,0)))) | Y70: Imprese e PA | Z70: Sì | AA70: hardware, software, personale interno, collaboratori, outsourcing (CAPEX e OPEX) | AB70: Domanda (end user) | AC70: Dichiarata | AD70: Non dichiarato | AE70: Survey dedicata a 1080 operatori OES e DSP dei 27 Stati membri. Spesa 2021 autodichiarata. Mediane e medie del campione, senza riporto all'universo. Gartner partner dello studio. | AF70: an OES or DSP in the EU earmarks 6.7% of its IT investments for information security, while the average value is 7.2% | AG70: B | AH70: Pubblico | AI70: Sì | AJ70: Letto da estratto indicizzato della pagina. Inclusione del personale interno dedotta per continuità con il questionario delle edizioni 2021 e 2023, che la dichiarano. | AK70: 08/10/2026
A71: 70 | B71: ENISA-NISINV-2022 | C71: EU27 | D71: Unione europea (UE27) | E71: UE | F71: ENISA, Agenzia dell'Unione europea per la cibersicurezza | G71: Istituzione UE | H71: NIS Investments 2022 (terza edizione) | I71: 23/11/2022 | J71: https://www.enisa.europa.eu/sites/default/files/publications/NIS%20Investments%202022.pdf | L71: Median spending for information security (IS) of an OES or DSP | M71: Spesa mediana in sicurezza informatica per operatore OES o DSP nel 2021. | N71: Spesa o budget delle organizzazioni | O71: Mediana per organizzazione | P71: Nessuna | Q71: Totale | R71: 600000 | S71: unità | T71: EUR | U71: 2021 | V71: Consuntivo | X71: =IF(OR($S71="%",$R71=""),"",$R71*INDEX(Cambi!$J$2:$J$5,MATCH($S71,Cambi!$I$2:$I$5,0))/IF($T71="EUR",1,INDEX(Cambi!$D:$D,MATCH($T71&"|"&$U71,Cambi!$C:$C,0)))) -> 0.6 | Y71: Imprese e PA | Z71: Sì | AA71: hardware, software, personale interno, collaboratori, outsourcing (CAPEX e OPEX) | AB71: Domanda (end user) | AC71: Dichiarata | AD71: Non dichiarato | AE71: Survey dedicata a 1080 operatori OES e DSP dei 27 Stati membri. Spesa 2021 autodichiarata. Mediane e medie del campione, senza riporto all'universo. Gartner partner dello studio. | AF71: median spending for information security (IS) of an OES or DSP was EUR 600 000 in 2021, while the average spending was EUR 4 million | AG71: B | AH71: Pubblico | AI71: Sì | AJ71: Letto da estratto indicizzato della pagina. Valore per singola organizzazione del campione NIS, non moltiplicabile per il numero di imprese. Inclusione del personale interno dedotta per continuità con il questionario delle edizioni 2021 e 2023, che la dichiarano. | AK71: 08/10/2026
A72: 71 | B72: ENISA-NISINV-2023 | C72: EU27 | D72: Unione europea (UE27) | E72: UE | F72: ENISA, Agenzia dell'Unione europea per la cibersicurezza | G72: Istituzione UE | H72: NIS Investments 2023 (quarta edizione) | I72: 16/11/2023 | J72: https://www.enisa.europa.eu/sites/default/files/publications/CSPA%20-%20NIS%20Investments%20-%202023.pdf | L72: Average spending for information security (IS) of an OES and DSP | M72: Spesa media in sicurezza informatica per operatore OES o DSP nel 2022. | N72: Spesa o budget delle organizzazioni | O72: Media per organizzazione | P72: Nessuna | Q72: Totale | R72: 5.1 | S72: milioni | T72: EUR | U72: 2022 | V72: Consuntivo | X72: =IF(OR($S72="%",$R72=""),"",$R72*INDEX(Cambi!$J$2:$J$5,MATCH($S72,Cambi!$I$2:$I$5,0))/IF($T72="EUR",1,INDEX(Cambi!$D:$D,MATCH($T72&"|"&$U72,Cambi!$C:$C,0)))) -> 5.1 | Y72: Imprese e PA | Z72: Sì | AA72: hardware, software, personale interno, collaboratori, outsourcing (CAPEX e OPEX) | AB72: Domanda (end user) | AC72: Dichiarata | AD72: Non dichiarato | AE72: Survey dedicata a 1080 operatori di servizi essenziali e fornitori di servizi digitali, 40 per Stato membro. Spesa 2022 autodichiarata comprensiva di CAPEX e OPEX per hardware, software, personale interno, collaboratori e outsourcing. Mediane e medie del campione, senza riporto all'universo. | AF72: in the EU was 700 k€ in 2022, while the average expenditure was 5,1 M€ | AG72: A | AH72: Pubblico | AI72: Sì | AJ72: Letto da estratto indicizzato della pagina. Valore per singola organizzazione del campione NIS, non moltiplicabile per il numero di imprese. | AK72: 08/10/2026
A73: 72 | B73: ENISA-NISINV-2023 | C73: EU27 | D73: Unione europea (UE27) | E73: UE | F73: ENISA, Agenzia dell'Unione europea per la cibersicurezza | G73: Istituzione UE | H73: NIS Investments 2023 (quarta edizione) | I73: 16/11/2023 | J73: https://www.enisa.europa.eu/sites/default/files/publications/CSPA%20-%20NIS%20Investments%20-%202023.pdf | K73: Gartner, IT Key Metrics Data 2023 e Security Spend Analytics Workbench, citati da ENISA | L73: IS Spending as % of 2021 Revenues, European Union | M73: Spesa in sicurezza informatica in percentuale del fatturato 2021 delle organizzazioni UE nel benchmark Gartner citato da ENISA. | N73: Rapporto di spesa | O73: Quota percentuale | P73: Nessuna | Q73: Totale | R73: 2.1 | S73: % | U73: 2022 | V73: Consuntivo | X73: =IF(OR($S73="%",$R73=""),"",$R73*INDEX(Cambi!$J$2:$J$5,MATCH($S73,Cambi!$I$2:$I$5,0))/IF($T73="EUR",1,INDEX(Cambi!$D:$D,MATCH($T73&"|"&$U73,Cambi!$C:$C,0)))) | Y73: Non specificato | Z73: Non specificato | AA73: Non specificato | AB73: Domanda (end user) | AC73: Dedotta. ENISA presenta il dato come metrica di un peer group di organizzazioni UE (IT Key Metrics Data), cioè misurata presso gli utenti, non da ricavi dei vendor. | AD73: Ripreso da altra fonte | AE73: Ripreso da Gartner IT Key Metrics Data. Peer group di organizzazioni UE escluso Cipro, valori medi. Campione e passaggi non dichiarati nel rapporto ENISA. | AF73: Table 1: Information security spending metrics by region, 2022 ... IS Spending as % of 2021 Revenues ... European Union* 5,1% 4,5% 673€ 2,1% | AG73: C | AH73: Solo citato da terzi | AI73: No | AJ73: Letto da estratto indicizzato della pagina. Valore pubblicato sotto l'intestazione IS spending in percentuale dei ricavi 2021. Ordine di grandezza poco plausibile per la sola sicurezza (la valutazione d'impatto NIS2 ipotizza 0,52%), possibile errore di intestazione per la spesa IT. Da verificare sulla fonte Gartner. | AK73: 08/10/2026
A74: 73 | B74: ENISA-NISINV-2023 | C74: EU27 | D74: Unione europea (UE27) | E74: UE | F74: ENISA, Agenzia dell'Unione europea per la cibersicurezza | G74: Istituzione UE | H74: NIS Investments 2023 (quarta edizione) | I74: 16/11/2023 | J74: https://www.enisa.europa.eu/sites/default/files/publications/CSPA%20-%20NIS%20Investments%20-%202023.pdf | L74: IS spending as a share of IT spending (average) | M74: Quota media della spesa di sicurezza sul budget IT degli operatori OES e DSP nel 2022. | N74: Rapporto di spesa | O74: Quota percentuale | P74: Nessuna | Q74: Totale | R74: 7.6 | S74: % | U74: 2022 | V74: Consuntivo | X74: =IF(OR($S74="%",$R74=""),"",$R74*INDEX(Cambi!$J$2:$J$5,MATCH($S74,Cambi!$I$2:$I$5,0))/IF($T74="EUR",1,INDEX(Cambi!$D:$D,MATCH($T74&"|"&$U74,Cambi!$C:$C,0)))) | Y74: Imprese e PA | Z74: Sì | AA74: hardware, software, personale interno, collaboratori, outsourcing (CAPEX e OPEX) | AB74: Domanda (end user) | AC74: Dichiarata | AD74: Non dichiarato | AE74: Survey dedicata a 1080 operatori di servizi essenziali e fornitori di servizi digitali, 40 per Stato membro. Spesa 2022 autodichiarata comprensiva di CAPEX e OPEX per hardware, software, personale interno, collaboratori e outsourcing. Mediane e medie del campione, senza riporto all'universo. | AF74: earmarks 7,1% of its IT investments for information security, while the average value is 7,6% | AG74: A | AH74: Pubblico | AI74: Sì | AJ74: Letto da estratto indicizzato della pagina. | AK74: 08/10/2026
A75: 74 | B75: ENISA-NISINV-2023 | C75: EU27 | D75: Unione europea (UE27) | E75: UE | F75: ENISA, Agenzia dell'Unione europea per la cibersicurezza | G75: Istituzione UE | H75: NIS Investments 2023 (quarta edizione) | I75: 16/11/2023 | J75: https://www.enisa.europa.eu/sites/default/files/publications/CSPA%20-%20NIS%20Investments%20-%202023.pdf | L75: IS spending as a share of IT spending (median) | M75: Quota mediana della spesa di sicurezza sul budget IT degli operatori OES e DSP nel 2022. | N75: Rapporto di spesa | O75: Quota percentuale | P75: Nessuna | Q75: Totale | R75: 7.1 | S75: % | U75: 2022 | V75: Consuntivo | X75: =IF(OR($S75="%",$R75=""),"",$R75*INDEX(Cambi!$J$2:$J$5,MATCH($S75,Cambi!$I$2:$I$5,0))/IF($T75="EUR",1,INDEX(Cambi!$D:$D,MATCH($T75&"|"&$U75,Cambi!$C:$C,0)))) | Y75: Imprese e PA | Z75: Sì | AA75: hardware, software, personale interno, collaboratori, outsourcing (CAPEX e OPEX) | AB75: Domanda (end user) | AC75: Dichiarata | AD75: Non dichiarato | AE75: Survey dedicata a 1080 operatori di servizi essenziali e fornitori di servizi digitali, 40 per Stato membro. Spesa 2022 autodichiarata comprensiva di CAPEX e OPEX per hardware, software, personale interno, collaboratori e outsourcing. Mediane e medie del campione, senza riporto all'universo. | AF75: earmarks 7,1% of its IT investments for information security, while the average value is 7,6% | AG75: A | AH75: Pubblico | AI75: Sì | AJ75: Letto da estratto indicizzato della pagina. | AK75: 08/10/2026
A76: 75 | B76: ENISA-NISINV-2023 | C76: EU27 | D76: Unione europea (UE27) | E76: UE | F76: ENISA, Agenzia dell'Unione europea per la cibersicurezza | G76: Istituzione UE | H76: NIS Investments 2023 (quarta edizione) | I76: 16/11/2023 | J76: https://www.enisa.europa.eu/sites/default/files/publications/CSPA%20-%20NIS%20Investments%20-%202023.pdf | K76: Gartner, IT Key Metrics Data 2023 e Security Spend Analytics Workbench, citati da ENISA | L76: IS spending per employee, European Union | M76: Spesa in sicurezza informatica per dipendente delle organizzazioni UE nel benchmark Gartner, la più bassa rispetto a Nord America e Asia Pacifico. | N76: Rapporto di spesa | O76: Media per organizzazione | P76: Nessuna | Q76: Totale | R76: 673 | S76: unità | T76: EUR | U76: 2022 | V76: Consuntivo | X76: =IF(OR($S76="%",$R76=""),"",$R76*INDEX(Cambi!$J$2:$J$5,MATCH($S76,Cambi!$I$2:$I$5,0))/IF($T76="EUR",1,INDEX(Cambi!$D:$D,MATCH($T76&"|"&$U76,Cambi!$C:$C,0)))) -> 0.000673 | Y76: Non specificato | Z76: Non specificato | AA76: Non specificato | AB76: Domanda (end user) | AC76: Dedotta. ENISA presenta il dato come metrica di un peer group di organizzazioni UE (IT Key Metrics Data), cioè misurata presso gli utenti, non da ricavi dei vendor. | AD76: Ripreso da altra fonte | AE76: Ripreso da Gartner IT Key Metrics Data. Peer group di organizzazioni UE escluso Cipro, valori medi. Campione e passaggi non dichiarati nel rapporto ENISA. | AF76: IS spending per employee is also the lowest in the EU, at 673 €, while it is much higher in APAC (1050 € | AG76: C | AH76: Solo citato da terzi | AI76: No | AJ76: Letto da estratto indicizzato della pagina. Anno 2022 dal titolo della Tabella 1 (Information security spending metrics by region, 2022). Rapporto di spesa per addetto. Peer group UE senza Cipro. | AK76: 08/10/2026
A77: 76 | B77: ENISA-NISINV-2023 | C77: EU27 | D77: Unione europea (UE27) | E77: UE | F77: ENISA, Agenzia dell'Unione europea per la cibersicurezza | G77: Istituzione UE | H77: NIS Investments 2023 (quarta edizione) | I77: 16/11/2023 | J77: https://www.enisa.europa.eu/sites/default/files/publications/CSPA%20-%20NIS%20Investments%20-%202023.pdf | L77: IS spending per sector (median) | M77: Spesa mediana in sicurezza informatica per operatore del settore banche nel 2022. | N77: Spesa o budget delle organizzazioni | O77: Mediana per organizzazione | P77: Settore | Q77: Banche | R77: 2 | S77: milioni | T77: EUR | U77: 2022 | V77: Consuntivo | X77: =IF(OR($S77="%",$R77=""),"",$R77*INDEX(Cambi!$J$2:$J$5,MATCH($S77,Cambi!$I$2:$I$5,0))/IF($T77="EUR",1,INDEX(Cambi!$D:$D,MATCH($T77&"|"&$U77,Cambi!$C:$C,0)))) -> 2 | Y77: Imprese e PA | Z77: Sì | AA77: hardware, software, personale interno, collaboratori, outsourcing (CAPEX e OPEX) | AB77: Domanda (end user) | AC77: Dichiarata | AD77: Non dichiarato | AE77: Survey dedicata a 1080 operatori di servizi essenziali e fornitori di servizi digitali, 40 per Stato membro. Spesa 2022 autodichiarata comprensiva di CAPEX e OPEX per hardware, software, personale interno, collaboratori e outsourcing. Mediane e medie del campione, senza riporto all'universo. | AF77: The Banking sector has the highest IS spending (2,0 M€), followed by the Energy (1,9 M€) and Healthcare sectors (1,3 M€). | AG77: A | AH77: Pubblico | AI77: Sì | AJ77: Letto da estratto indicizzato della pagina. Valore per singola organizzazione del campione NIS, non moltiplicabile per il numero di imprese. | AK77: 08/10/2026
A78: 77 | B78: ENISA-NISINV-2023 | C78: EU27 | D78: Unione europea (UE27) | E78: UE | F78: ENISA, Agenzia dell'Unione europea per la cibersicurezza | G78: Istituzione UE | H78: NIS Investments 2023 (quarta edizione) | I78: 16/11/2023 | J78: https://www.enisa.europa.eu/sites/default/files/publications/CSPA%20-%20NIS%20Investments%20-%202023.pdf | L78: IS spending per sector (median) | M78: Spesa mediana in sicurezza informatica per operatore del settore energia nel 2022. | N78: Spesa o budget delle organizzazioni | O78: Mediana per organizzazione | P78: Settore | Q78: Energia | R78: 1.9 | S78: milioni | T78: EUR | U78: 2022 | V78: Consuntivo | X78: =IF(OR($S78="%",$R78=""),"",$R78*INDEX(Cambi!$J$2:$J$5,MATCH($S78,Cambi!$I$2:$I$5,0))/IF($T78="EUR",1,INDEX(Cambi!$D:$D,MATCH($T78&"|"&$U78,Cambi!$C:$C,0)))) -> 1.9 | Y78: Imprese e PA | Z78: Sì | AA78: hardware, software, personale interno, collaboratori, outsourcing (CAPEX e OPEX) | AB78: Domanda (end user) | AC78: Dichiarata | AD78: Non dichiarato | AE78: Survey dedicata a 1080 operatori di servizi essenziali e fornitori di servizi digitali, 40 per Stato membro. Spesa 2022 autodichiarata comprensiva di CAPEX e OPEX per hardware, software, personale interno, collaboratori e outsourcing. Mediane e medie del campione, senza riporto all'universo. | AF78: The Banking sector has the highest IS spending (2,0 M€), followed by the Energy (1,9 M€) and Healthcare sectors (1,3 M€). | AG78: A | AH78: Pubblico | AI78: Sì | AJ78: Letto da estratto indicizzato della pagina. Valore per singola organizzazione del campione NIS, non moltiplicabile per il numero di imprese. Verifica finale 08/10/2026, valore confermato sulla fonte. Valore del settore energia presente nel PDF ENISA NIS Investments 2023. | AK78: 08/10/2026
A79: 78 | B79: ENISA-NISINV-2023 | C79: EU27 | D79: Unione europea (UE27) | E79: UE | F79: ENISA, Agenzia dell'Unione europea per la cibersicurezza | G79: Istituzione UE | H79: NIS Investments 2023 (quarta edizione) | I79: 16/11/2023 | J79: https://www.enisa.europa.eu/sites/default/files/publications/CSPA%20-%20NIS%20Investments%20-%202023.pdf | L79: IS spending per sector (median) | M79: Spesa mediana in sicurezza informatica per operatore del settore infrastrutture digitali nel 2022. | N79: Spesa o budget delle organizzazioni | O79: Mediana per organizzazione | P79: Settore | Q79: Infrastrutture digitali | R79: 0.1 | S79: milioni | T79: EUR | U79: 2022 | V79: Consuntivo | X79: =IF(OR($S79="%",$R79=""),"",$R79*INDEX(Cambi!$J$2:$J$5,MATCH($S79,Cambi!$I$2:$I$5,0))/IF($T79="EUR",1,INDEX(Cambi!$D:$D,MATCH($T79&"|"&$U79,Cambi!$C:$C,0)))) -> 0.1 | Y79: Imprese e PA | Z79: Sì | AA79: hardware, software, personale interno, collaboratori, outsourcing (CAPEX e OPEX) | AB79: Domanda (end user) | AC79: Dichiarata | AD79: Non dichiarato | AE79: Survey dedicata a 1080 operatori di servizi essenziali e fornitori di servizi digitali, 40 per Stato membro. Spesa 2022 autodichiarata comprensiva di CAPEX e OPEX per hardware, software, personale interno, collaboratori e outsourcing. Mediane e medie del campione, senza riporto all'universo. | AF79: the information security spending of Digital Infrastructure organisations is the lowest, amounting to a median spending of 100 000 €. | AG79: A | AH79: Pubblico | AI79: Sì | AJ79: Letto da estratto indicizzato della pagina. Valore per singola organizzazione del campione NIS, non moltiplicabile per il numero di imprese. Pubblicato come 100 000 euro, qui espresso in milioni. | AK79: 08/10/2026
A80: 79 | B80: ENISA-NISINV-2023 | C80: EU27 | D80: Unione europea (UE27) | E80: UE | F80: ENISA, Agenzia dell'Unione europea per la cibersicurezza | G80: Istituzione UE | H80: NIS Investments 2023 (quarta edizione) | I80: 16/11/2023 | J80: https://www.enisa.europa.eu/sites/default/files/publications/CSPA%20-%20NIS%20Investments%20-%202023.pdf | L80: IS spending per sector (median) | M80: Spesa mediana in sicurezza informatica per operatore del settore sanità nel 2022. | N80: Spesa o budget delle organizzazioni | O80: Mediana per organizzazione | P80: Settore | Q80: Sanità | R80: 1.3 | S80: milioni | T80: EUR | U80: 2022 | V80: Consuntivo | X80: =IF(OR($S80="%",$R80=""),"",$R80*INDEX(Cambi!$J$2:$J$5,MATCH($S80,Cambi!$I$2:$I$5,0))/IF($T80="EUR",1,INDEX(Cambi!$D:$D,MATCH($T80&"|"&$U80,Cambi!$C:$C,0)))) -> 1.3 | Y80: Imprese e PA | Z80: Sì | AA80: hardware, software, personale interno, collaboratori, outsourcing (CAPEX e OPEX) | AB80: Domanda (end user) | AC80: Dichiarata | AD80: Non dichiarato | AE80: Survey dedicata a 1080 operatori di servizi essenziali e fornitori di servizi digitali, 40 per Stato membro. Spesa 2022 autodichiarata comprensiva di CAPEX e OPEX per hardware, software, personale interno, collaboratori e outsourcing. Mediane e medie del campione, senza riporto all'universo. | AF80: The Banking sector has the highest IS spending (2,0 M€), followed by the Energy (1,9 M€) and Healthcare sectors (1,3 M€). | AG80: A | AH80: Pubblico | AI80: Sì | AJ80: Letto da estratto indicizzato della pagina. Valore per singola organizzazione del campione NIS, non moltiplicabile per il numero di imprese. Verifica finale 08/10/2026, valore confermato sulla fonte. Valore del settore sanitario presente nel PDF ENISA NIS Investments 2023. | AK80: 08/10/2026
A81: 80 | B81: ENISA-NISINV-2023 | C81: EU27 | D81: Unione europea (UE27) | E81: UE | F81: ENISA, Agenzia dell'Unione europea per la cibersicurezza | G81: Istituzione UE | H81: NIS Investments 2023 (quarta edizione) | I81: 16/11/2023 | J81: https://www.enisa.europa.eu/sites/default/files/publications/CSPA%20-%20NIS%20Investments%20-%202023.pdf | L81: Median spending for information security (IS) of an OES and DSP | M81: Spesa mediana in sicurezza informatica per operatore OES o DSP nel 2022. | N81: Spesa o budget delle organizzazioni | O81: Mediana per organizzazione | P81: Nessuna | Q81: Totale | R81: 700 | S81: migliaia | T81: EUR | U81: 2022 | V81: Consuntivo | X81: =IF(OR($S81="%",$R81=""),"",$R81*INDEX(Cambi!$J$2:$J$5,MATCH($S81,Cambi!$I$2:$I$5,0))/IF($T81="EUR",1,INDEX(Cambi!$D:$D,MATCH($T81&"|"&$U81,Cambi!$C:$C,0)))) -> 0.7 | Y81: Imprese e PA | Z81: Sì | AA81: hardware, software, personale interno, collaboratori, outsourcing (CAPEX e OPEX) | AB81: Domanda (end user) | AC81: Dichiarata | AD81: Non dichiarato | AE81: Survey dedicata a 1080 operatori di servizi essenziali e fornitori di servizi digitali, 40 per Stato membro. Spesa 2022 autodichiarata comprensiva di CAPEX e OPEX per hardware, software, personale interno, collaboratori e outsourcing. Mediane e medie del campione, senza riporto all'universo. | AF81: median spending for information security (IS) of an OES and DSP in the EU was 700 k€ 2022 | AG81: A | AH81: Pubblico | AI81: Sì | AJ81: Letto da estratto indicizzato della pagina. Valore per singola organizzazione del campione NIS, non moltiplicabile per il numero di imprese. | AK81: 08/10/2026
A82: 81 | B82: ENISA-NISINV-2024 | C82: EU27 | D82: Unione europea (UE27) | E82: UE | F82: ENISA, Agenzia dell'Unione europea per la cibersicurezza | G82: Istituzione UE | H82: NIS Investments 2024 (quinta edizione) | I82: 22/11/2024 | J82: https://www.enisa.europa.eu/sites/default/files/2024-11/CSPA%20-%20NIS%20Investments%20-%202024_0.pdf | K82: Gartner, IT Key Metrics Data (peer group UE senza Cipro), citato da ENISA | L82: IS spending as % of IT spending 2022 (average), European Union | M82: Quota media della spesa di sicurezza sulla spesa IT delle organizzazioni UE nel benchmark Gartner, anno 2022, non limitata ai soggetti NIS. | N82: Rapporto di spesa | O82: Quota percentuale | P82: Nessuna | Q82: Totale | R82: 5.1 | S82: % | U82: 2022 | V82: Consuntivo | X82: =IF(OR($S82="%",$R82=""),"",$R82*INDEX(Cambi!$J$2:$J$5,MATCH($S82,Cambi!$I$2:$I$5,0))/IF($T82="EUR",1,INDEX(Cambi!$D:$D,MATCH($T82&"|"&$U82,Cambi!$C:$C,0)))) | Y82: Non specificato | Z82: Non specificato | AA82: Non specificato | AB82: Domanda (end user) | AC82: Dedotta. ENISA presenta il dato come metrica di un peer group di organizzazioni UE (IT Key Metrics Data), cioè misurata presso gli utenti, non da ricavi dei vendor. | AD82: Ripreso da altra fonte | AE82: Ripreso da Gartner IT Key Metrics Data. Peer group di organizzazioni UE escluso Cipro, valori medi. Campione e passaggi non dichiarati nel rapporto ENISA. | AF82: IS spending as % of IT spending 2022 (average) IS spending as % of IT spending 2023 (average) ... European Union* 5.1% 5.6% | AG82: C | AH82: Solo citato da terzi | AI82: No | AJ82: Letto da estratto indicizzato della pagina. Fonte primaria Gartner non consultabile. Perimetro organizzazioni UE in generale, diverso dal campione NIS. | AK82: 08/10/2026
A83: 82 | B83: ENISA-NISINV-2024 | C83: EU27 | D83: Unione europea (UE27) | E83: UE | F83: ENISA, Agenzia dell'Unione europea per la cibersicurezza | G83: Istituzione UE | H83: NIS Investments 2024 (quinta edizione) | I83: 22/11/2024 | J83: https://www.enisa.europa.eu/sites/default/files/2024-11/CSPA%20-%20NIS%20Investments%20-%202024_0.pdf | L83: Average spending for information security (M€) | M83: Spesa media in sicurezza informatica per organizzazione in perimetro NIS2 nel 2023. | N83: Spesa o budget delle organizzazioni | O83: Media per organizzazione | P83: Nessuna | Q83: Totale | R83: 6.7 | S83: milioni | T83: EUR | U83: 2023 | V83: Consuntivo | X83: =IF(OR($S83="%",$R83=""),"",$R83*INDEX(Cambi!$J$2:$J$5,MATCH($S83,Cambi!$I$2:$I$5,0))/IF($T83="EUR",1,INDEX(Cambi!$D:$D,MATCH($T83&"|"&$U83,Cambi!$C:$C,0)))) -> 6.7 | Y83: Imprese e PA | Z83: Sì | AA83: hardware, software, personale interno, collaboratori, outsourcing (CAPEX e OPEX) | AB83: Domanda (end user) | AC83: Dichiarata | AD83: Non dichiarato | AE83: Survey dedicata a 1350 organizzazioni, 50 per Stato membro, dei settori NIS2 ad alta criticità e del manifatturiero. Spesa 2023 autodichiarata comprensiva di CAPEX e OPEX per hardware, software, personale interno, collaboratori e outsourcing. Mediane e medie del campione, senza riporto all'universo. | AF83: The median spending for information security of organisations in the EU was 1,4 M€ 2023, while the average expenditure was 6,7 M€ | AG83: A | AH83: Pubblico | AI83: Sì | AJ83: Letto da estratto indicizzato della pagina. Media influenzata dalle grandi organizzazioni. Valore per singola organizzazione del campione NIS, non moltiplicabile per il numero di imprese. | AK83: 08/10/2026
A84: 83 | B84: ENISA-NISINV-2024 | C84: EU27 | D84: Unione europea (UE27) | E84: UE | F84: ENISA, Agenzia dell'Unione europea per la cibersicurezza | G84: Istituzione UE | H84: NIS Investments 2024 (quinta edizione) | I84: 22/11/2024 | J84: https://www.enisa.europa.eu/sites/default/files/2024-11/CSPA%20-%20NIS%20Investments%20-%202024_0.pdf | L84: Information security spending per sector (average) | M84: Spesa media in sicurezza informatica per organizzazione del settore banche nel 2023. | N84: Spesa o budget delle organizzazioni | O84: Media per organizzazione | P84: Settore | Q84: Banche | R84: 13.9 | S84: milioni | T84: EUR | U84: 2023 | V84: Consuntivo | X84: =IF(OR($S84="%",$R84=""),"",$R84*INDEX(Cambi!$J$2:$J$5,MATCH($S84,Cambi!$I$2:$I$5,0))/IF($T84="EUR",1,INDEX(Cambi!$D:$D,MATCH($T84&"|"&$U84,Cambi!$C:$C,0)))) -> 13.9 | Y84: Imprese | Z84: Sì | AA84: hardware, software, personale interno, collaboratori, outsourcing (CAPEX e OPEX) | AB84: Domanda (end user) | AC84: Dichiarata | AD84: Non dichiarato | AE84: Survey dedicata a 1350 organizzazioni, 50 per Stato membro, dei settori NIS2 ad alta criticità e del manifatturiero. Spesa 2023 autodichiarata comprensiva di CAPEX e OPEX per hardware, software, personale interno, collaboratori e outsourcing. Mediane e medie del campione, senza riporto all'universo. | AF84: the Banking sector leads in information security investment with an average spending of € 13.9 million and a median of € 4.0 million | AG84: A | AH84: Pubblico | AI84: Sì | AJ84: Letto da estratto indicizzato della pagina. Valore per singola organizzazione del campione NIS, non moltiplicabile per il numero di imprese. | AK84: 08/10/2026
A85: 84 | B85: ENISA-NISINV-2024 | C85: EU27 | D85: Unione europea (UE27) | E85: UE | F85: ENISA, Agenzia dell'Unione europea per la cibersicurezza | G85: Istituzione UE | H85: NIS Investments 2024 (quinta edizione) | I85: 22/11/2024 | J85: https://www.enisa.europa.eu/sites/default/files/2024-11/CSPA%20-%20NIS%20Investments%20-%202024_0.pdf | L85: Information security spending per sector (average) | M85: Spesa media in sicurezza informatica per organizzazione del settore energia nel 2023. | N85: Spesa o budget delle organizzazioni | O85: Media per organizzazione | P85: Settore | Q85: Energia | R85: 8.8 | S85: milioni | T85: EUR | U85: 2023 | V85: Consuntivo | X85: =IF(OR($S85="%",$R85=""),"",$R85*INDEX(Cambi!$J$2:$J$5,MATCH($S85,Cambi!$I$2:$I$5,0))/IF($T85="EUR",1,INDEX(Cambi!$D:$D,MATCH($T85&"|"&$U85,Cambi!$C:$C,0)))) -> 8.8 | Y85: Imprese | Z85: Sì | AA85: hardware, software, personale interno, collaboratori, outsourcing (CAPEX e OPEX) | AB85: Domanda (end user) | AC85: Dichiarata | AD85: Non dichiarato | AE85: Survey dedicata a 1350 organizzazioni, 50 per Stato membro, dei settori NIS2 ad alta criticità e del manifatturiero. Spesa 2023 autodichiarata comprensiva di CAPEX e OPEX per hardware, software, personale interno, collaboratori e outsourcing. Mediane e medie del campione, senza riporto all'universo. | AF85: the Energy sector allocates an average of € 8.8 million and a median of € 2.5 million | AG85: A | AH85: Pubblico | AI85: Sì | AJ85: Letto da estratto indicizzato della pagina. Valore per singola organizzazione del campione NIS, non moltiplicabile per il numero di imprese. | AK85: 08/10/2026
A86: 85 | B86: ENISA-NISINV-2024 | C86: EU27 | D86: Unione europea (UE27) | E86: UE | F86: ENISA, Agenzia dell'Unione europea per la cibersicurezza | G86: Istituzione UE | H86: NIS Investments 2024 (quinta edizione) | I86: 22/11/2024 | J86: https://www.enisa.europa.eu/sites/default/files/2024-11/CSPA%20-%20NIS%20Investments%20-%202024_0.pdf | L86: Information security spending per sector (average) | M86: Spesa media in sicurezza informatica per organizzazione del settore pubblica amministrazione nel 2023. | N86: Spesa o budget delle organizzazioni | O86: Media per organizzazione | P86: Settore | Q86: Pubblica amministrazione | R86: 7.6 | S86: milioni | T86: EUR | U86: 2023 | V86: Consuntivo | X86: =IF(OR($S86="%",$R86=""),"",$R86*INDEX(Cambi!$J$2:$J$5,MATCH($S86,Cambi!$I$2:$I$5,0))/IF($T86="EUR",1,INDEX(Cambi!$D:$D,MATCH($T86&"|"&$U86,Cambi!$C:$C,0)))) -> 7.6 | Y86: PA | Z86: Sì | AA86: hardware, software, personale interno, collaboratori, outsourcing (CAPEX e OPEX) | AB86: Domanda (end user) | AC86: Dichiarata | AD86: Non dichiarato | AE86: Survey dedicata a 1350 organizzazioni, 50 per Stato membro, dei settori NIS2 ad alta criticità e del manifatturiero. Spesa 2023 autodichiarata comprensiva di CAPEX e OPEX per hardware, software, personale interno, collaboratori e outsourcing. Mediane e medie del campione, senza riporto all'universo. | AF86: Public administration ranks third, with an average spending of € 7.6 million and a median of € 2.0 million | AG86: A | AH86: Pubblico | AI86: Sì | AJ86: Letto da estratto indicizzato della pagina. Valore per singola organizzazione del campione NIS, non moltiplicabile per il numero di imprese. Verifica finale 08/10/2026, valore confermato sulla fonte. Media della pubblica amministrazione 7,6 milioni EUR nel 2023. | AK86: 08/10/2026
A87: 86 | B87: ENISA-NISINV-2024 | C87: EU27 | D87: Unione europea (UE27) | E87: UE | F87: ENISA, Agenzia dell'Unione europea per la cibersicurezza | G87: Istituzione UE | H87: NIS Investments 2024 (quinta edizione) | I87: 22/11/2024 | J87: https://www.enisa.europa.eu/sites/default/files/2024-11/CSPA%20-%20NIS%20Investments%20-%202024_0.pdf | L87: Information security spending per sector (median) | M87: Spesa mediana in sicurezza informatica per organizzazione del settore banche nel 2023. | N87: Spesa o budget delle organizzazioni | O87: Mediana per organizzazione | P87: Settore | Q87: Banche | R87: 4 | S87: milioni | T87: EUR | U87: 2023 | V87: Consuntivo | X87: =IF(OR($S87="%",$R87=""),"",$R87*INDEX(Cambi!$J$2:$J$5,MATCH($S87,Cambi!$I$2:$I$5,0))/IF($T87="EUR",1,INDEX(Cambi!$D:$D,MATCH($T87&"|"&$U87,Cambi!$C:$C,0)))) -> 4 | Y87: Imprese | Z87: Sì | AA87: hardware, software, personale interno, collaboratori, outsourcing (CAPEX e OPEX) | AB87: Domanda (end user) | AC87: Dichiarata | AD87: Non dichiarato | AE87: Survey dedicata a 1350 organizzazioni, 50 per Stato membro, dei settori NIS2 ad alta criticità e del manifatturiero. Spesa 2023 autodichiarata comprensiva di CAPEX e OPEX per hardware, software, personale interno, collaboratori e outsourcing. Mediane e medie del campione, senza riporto all'universo. | AF87: the Banking sector leads in information security investment with an average spending of € 13.9 million and a median of € 4.0 million | AG87: A | AH87: Pubblico | AI87: Sì | AJ87: Letto da estratto indicizzato della pagina. Valore per singola organizzazione del campione NIS, non moltiplicabile per il numero di imprese. Verifica finale 08/10/2026, valore confermato sulla fonte. Mediana bancaria 4,0 milioni EUR riferita al 2023. | AK87: 08/10/2026
A88: 87 | B88: ENISA-NISINV-2024 | C88: EU27 | D88: Unione europea (UE27) | E88: UE | F88: ENISA, Agenzia dell'Unione europea per la cibersicurezza | G88: Istituzione UE | H88: NIS Investments 2024 (quinta edizione) | I88: 22/11/2024 | J88: https://www.enisa.europa.eu/sites/default/files/2024-11/CSPA%20-%20NIS%20Investments%20-%202024_0.pdf | L88: Information security spending per sector (median) | M88: Spesa mediana in sicurezza informatica per organizzazione del settore energia nel 2023. | N88: Spesa o budget delle organizzazioni | O88: Mediana per organizzazione | P88: Settore | Q88: Energia | R88: 2.5 | S88: milioni | T88: EUR | U88: 2023 | V88: Consuntivo | X88: =IF(OR($S88="%",$R88=""),"",$R88*INDEX(Cambi!$J$2:$J$5,MATCH($S88,Cambi!$I$2:$I$5,0))/IF($T88="EUR",1,INDEX(Cambi!$D:$D,MATCH($T88&"|"&$U88,Cambi!$C:$C,0)))) -> 2.5 | Y88: Imprese | Z88: Sì | AA88: hardware, software, personale interno, collaboratori, outsourcing (CAPEX e OPEX) | AB88: Domanda (end user) | AC88: Dichiarata | AD88: Non dichiarato | AE88: Survey dedicata a 1350 organizzazioni, 50 per Stato membro, dei settori NIS2 ad alta criticità e del manifatturiero. Spesa 2023 autodichiarata comprensiva di CAPEX e OPEX per hardware, software, personale interno, collaboratori e outsourcing. Mediane e medie del campione, senza riporto all'universo. | AF88: the Energy sector allocates an average of € 8.8 million and a median of € 2.5 million | AG88: A | AH88: Pubblico | AI88: Sì | AJ88: Letto da estratto indicizzato della pagina. Valore per singola organizzazione del campione NIS, non moltiplicabile per il numero di imprese. | AK88: 08/10/2026
A89: 88 | B89: ENISA-NISINV-2024 | C89: EU27 | D89: Unione europea (UE27) | E89: UE | F89: ENISA, Agenzia dell'Unione europea per la cibersicurezza | G89: Istituzione UE | H89: NIS Investments 2024 (quinta edizione) | I89: 22/11/2024 | J89: https://www.enisa.europa.eu/sites/default/files/2024-11/CSPA%20-%20NIS%20Investments%20-%202024_0.pdf | L89: Information security spending per sector (median) | M89: Spesa mediana in sicurezza informatica per organizzazione del settore pubblica amministrazione nel 2023. | N89: Spesa o budget delle organizzazioni | O89: Mediana per organizzazione | P89: Settore | Q89: Pubblica amministrazione | R89: 2 | S89: milioni | T89: EUR | U89: 2023 | V89: Consuntivo | X89: =IF(OR($S89="%",$R89=""),"",$R89*INDEX(Cambi!$J$2:$J$5,MATCH($S89,Cambi!$I$2:$I$5,0))/IF($T89="EUR",1,INDEX(Cambi!$D:$D,MATCH($T89&"|"&$U89,Cambi!$C:$C,0)))) -> 2 | Y89: PA | Z89: Sì | AA89: hardware, software, personale interno, collaboratori, outsourcing (CAPEX e OPEX) | AB89: Domanda (end user) | AC89: Dichiarata | AD89: Non dichiarato | AE89: Survey dedicata a 1350 organizzazioni, 50 per Stato membro, dei settori NIS2 ad alta criticità e del manifatturiero. Spesa 2023 autodichiarata comprensiva di CAPEX e OPEX per hardware, software, personale interno, collaboratori e outsourcing. Mediane e medie del campione, senza riporto all'universo. | AF89: Public administration ranks third, with an average spending of € 7.6 million and a median of € 2.0 million | AG89: A | AH89: Pubblico | AI89: Sì | AJ89: Letto da estratto indicizzato della pagina. Valore per singola organizzazione del campione NIS, non moltiplicabile per il numero di imprese. Verifica finale 08/10/2026, valore confermato sulla fonte. Mediana della pubblica amministrazione 2,0 milioni EUR nel 2023. | AK89: 08/10/2026
A90: 89 | B90: ENISA-NISINV-2024 | C90: EU27 | D90: Unione europea (UE27) | E90: UE | F90: ENISA, Agenzia dell'Unione europea per la cibersicurezza | G90: Istituzione UE | H90: NIS Investments 2024 (quinta edizione) | I90: 22/11/2024 | J90: https://www.enisa.europa.eu/sites/default/files/2024-11/CSPA%20-%20NIS%20Investments%20-%202024_0.pdf | K90: Gartner, IT Key Metrics Data (peer group UE senza Cipro), citato da ENISA | L90: IS spending as % of IT spending 2023 (average), European Union | M90: Quota media della spesa di sicurezza sulla spesa IT delle organizzazioni UE nel benchmark Gartner, anno 2023, non limitata ai soggetti NIS. | N90: Rapporto di spesa | O90: Quota percentuale | P90: Nessuna | Q90: Totale | R90: 5.6 | S90: % | U90: 2023 | V90: Consuntivo | X90: =IF(OR($S90="%",$R90=""),"",$R90*INDEX(Cambi!$J$2:$J$5,MATCH($S90,Cambi!$I$2:$I$5,0))/IF($T90="EUR",1,INDEX(Cambi!$D:$D,MATCH($T90&"|"&$U90,Cambi!$C:$C,0)))) | Y90: Non specificato | Z90: Non specificato | AA90: Non specificato | AB90: Domanda (end user) | AC90: Dedotta. ENISA presenta il dato come metrica di un peer group di organizzazioni UE (IT Key Metrics Data), cioè misurata presso gli utenti, non da ricavi dei vendor. | AD90: Ripreso da altra fonte | AE90: Ripreso da Gartner IT Key Metrics Data. Peer group di organizzazioni UE escluso Cipro, valori medi. Campione e passaggi non dichiarati nel rapporto ENISA. | AF90: IS spending as % of IT spending 2022 (average) IS spending as % of IT spending 2023 (average) ... European Union* 5.1% 5.6% | AG90: C | AH90: Solo citato da terzi | AI90: No | AJ90: Letto da estratto indicizzato della pagina. Fonte primaria Gartner non consultabile. Perimetro organizzazioni UE in generale, diverso dal campione NIS. | AK90: 08/10/2026
A91: 90 | B91: ENISA-NISINV-2024 | C91: EU27 | D91: Unione europea (UE27) | E91: UE | F91: ENISA, Agenzia dell'Unione europea per la cibersicurezza | G91: Istituzione UE | H91: NIS Investments 2024 (quinta edizione) | I91: 22/11/2024 | J91: https://www.enisa.europa.eu/sites/default/files/2024-11/CSPA%20-%20NIS%20Investments%20-%202024_0.pdf | L91: IS spending as a share of IT spending (average) | M91: Quota media della spesa di sicurezza sul budget IT nel 2023. | N91: Rapporto di spesa | O91: Quota percentuale | P91: Nessuna | Q91: Totale | R91: 9.6 | S91: % | U91: 2023 | V91: Consuntivo | X91: =IF(OR($S91="%",$R91=""),"",$R91*INDEX(Cambi!$J$2:$J$5,MATCH($S91,Cambi!$I$2:$I$5,0))/IF($T91="EUR",1,INDEX(Cambi!$D:$D,MATCH($T91&"|"&$U91,Cambi!$C:$C,0)))) | Y91: Imprese e PA | Z91: Sì | AA91: hardware, software, personale interno, collaboratori, outsourcing (CAPEX e OPEX) | AB91: Domanda (end user) | AC91: Dichiarata | AD91: Non dichiarato | AE91: Survey dedicata a 1350 organizzazioni, 50 per Stato membro, dei settori NIS2 ad alta criticità e del manifatturiero. Spesa 2023 autodichiarata comprensiva di CAPEX e OPEX per hardware, software, personale interno, collaboratori e outsourcing. Mediane e medie del campione, senza riporto all'universo. | AF91: earmark 9,0% of their IT investments for information security, while the average value is 9,6% | AG91: A | AH91: Pubblico | AI91: Sì | AJ91: Letto da estratto indicizzato della pagina. | AK91: 08/10/2026
A92: 91 | B92: ENISA-NISINV-2024 | C92: EU27 | D92: Unione europea (UE27) | E92: UE | F92: ENISA, Agenzia dell'Unione europea per la cibersicurezza | G92: Istituzione UE | H92: NIS Investments 2024 (quinta edizione) | I92: 22/11/2024 | J92: https://www.enisa.europa.eu/sites/default/files/2024-11/CSPA%20-%20NIS%20Investments%20-%202024_0.pdf | L92: IS spending as a share of IT spending (median) | M92: Quota mediana della spesa di sicurezza sul budget IT nel 2023, in aumento di 1,9 punti sul 2022. | N92: Rapporto di spesa | O92: Quota percentuale | P92: Nessuna | Q92: Totale | R92: 9 | S92: % | U92: 2023 | V92: Consuntivo | X92: =IF(OR($S92="%",$R92=""),"",$R92*INDEX(Cambi!$J$2:$J$5,MATCH($S92,Cambi!$I$2:$I$5,0))/IF($T92="EUR",1,INDEX(Cambi!$D:$D,MATCH($T92&"|"&$U92,Cambi!$C:$C,0)))) | Y92: Imprese e PA | Z92: Sì | AA92: hardware, software, personale interno, collaboratori, outsourcing (CAPEX e OPEX) | AB92: Domanda (end user) | AC92: Dichiarata | AD92: Non dichiarato | AE92: Survey dedicata a 1350 organizzazioni, 50 per Stato membro, dei settori NIS2 ad alta criticità e del manifatturiero. Spesa 2023 autodichiarata comprensiva di CAPEX e OPEX per hardware, software, personale interno, collaboratori e outsourcing. Mediane e medie del campione, senza riporto all'universo. | AF92: earmark 9,0% of their IT investments for information security, while the average value is 9,6% | AG92: A | AH92: Pubblico | AI92: Sì | AJ92: Letto da estratto indicizzato della pagina. Quota autodichiarata con personale interno. | AK92: 08/10/2026
A93: 92 | B93: ENISA-NISINV-2024 | C93: EU27 | D93: Unione europea (UE27) | E93: UE | F93: ENISA, Agenzia dell'Unione europea per la cibersicurezza | G93: Istituzione UE | H93: NIS Investments 2024 (quinta edizione) | I93: 22/11/2024 | J93: https://www.enisa.europa.eu/sites/default/files/2024-11/CSPA%20-%20NIS%20Investments%20-%202024_0.pdf | L93: Median spending for information security (M€) | M93: Spesa mediana in sicurezza informatica per organizzazione in perimetro NIS2 nel 2023, raddoppiata rispetto a 0,7 milioni del 2022. | N93: Spesa o budget delle organizzazioni | O93: Mediana per organizzazione | P93: Nessuna | Q93: Totale | R93: 1.4 | S93: milioni | T93: EUR | U93: 2023 | V93: Consuntivo | X93: =IF(OR($S93="%",$R93=""),"",$R93*INDEX(Cambi!$J$2:$J$5,MATCH($S93,Cambi!$I$2:$I$5,0))/IF($T93="EUR",1,INDEX(Cambi!$D:$D,MATCH($T93&"|"&$U93,Cambi!$C:$C,0)))) -> 1.4 | Y93: Imprese e PA | Z93: Sì | AA93: hardware, software, personale interno, collaboratori, outsourcing (CAPEX e OPEX) | AB93: Domanda (end user) | AC93: Dichiarata | AD93: Non dichiarato | AE93: Survey dedicata a 1350 organizzazioni, 50 per Stato membro, dei settori NIS2 ad alta criticità e del manifatturiero. Spesa 2023 autodichiarata comprensiva di CAPEX e OPEX per hardware, software, personale interno, collaboratori e outsourcing. Mediane e medie del campione, senza riporto all'universo. | AF93: The median spending for information security of organisations in the EU was 1,4 M€ 2023, while the average expenditure was 6,7 M€ | AG93: A | AH93: Pubblico | AI93: Sì | AJ93: Letto da estratto indicizzato della pagina. Valore per singola organizzazione del campione NIS, non moltiplicabile per il numero di imprese. | AK93: 08/10/2026
A94: 93 | B94: ENISA-NISINV-2025 | C94: EU27 | D94: Unione europea (UE27) | E94: UE | F94: ENISA, Agenzia dell'Unione europea per la cibersicurezza | G94: Istituzione UE | H94: NIS Investments 2025, Main report (sesta edizione) | I94: 08/12/2025 | J94: https://www.enisa.europa.eu/sites/default/files/2026-02/NIS%20Investments%202025%20-%20Main%20report.pdf | L94: Cybersecurity as a share of IT budget, average | M94: Quota media della spesa in cybersecurity sul budget IT nel 2024, in lieve calo per la riduzione presso i grandi spenditori. | N94: Rapporto di spesa | O94: Quota percentuale | P94: Nessuna | Q94: Totale | R94: 9.3 | S94: % | U94: 2024 | V94: Consuntivo | X94: =IF(OR($S94="%",$R94=""),"",$R94*INDEX(Cambi!$J$2:$J$5,MATCH($S94,Cambi!$I$2:$I$5,0))/IF($T94="EUR",1,INDEX(Cambi!$D:$D,MATCH($T94&"|"&$U94,Cambi!$C:$C,0)))) | Y94: Imprese e PA | Z94: Sì | AA94: hardware, software, personale interno, collaboratori, outsourcing (CAPEX e OPEX) | AB94: Domanda (end user) | AC94: Dichiarata | AD94: Non dichiarato | AE94: Survey con interviste telefoniche strutturate a 1080 professionisti di organizzazioni dei settori NIS2 ad alta criticità nei 27 Stati membri, 83% grandi imprese e 17% PMI. Spesa 2024 autodichiarata, CAPEX e OPEX per hardware, software, personale, collaboratori e outsourcing. Mediane e medie del campione, senza riporto all'universo. | AF94: FIG. 3 - CYBERSECURITY AS A SHARE OF IT BUDGET ... Average Median ... 8,8% 17% 9,6% 12,8% 9,3% 11,7% | AG94: A | AH94: Pubblico | AI94: Sì | AJ94: Letto da estratto indicizzato della pagina. Valore letto da grafico (Fig. 3), serie medie 8,8% 7,2% 7,6% 9,6% 9,3%. Abbinamento all'anno dedotto dall'ordine della serie. Valore leggibile nell'estratto della versione del PDF ripubblicata a febbraio 2026. Verifica finale 08/10/2026, valore confermato sulla fonte. Valore letto dal grafico, coerente con il calo della media indicato nel testo. | AK94: 08/10/2026
A95: 94 | B95: ENISA-NISINV-2025 | C95: EU27 | D95: Unione europea (UE27) | E95: UE | F95: ENISA, Agenzia dell'Unione europea per la cibersicurezza | G95: Istituzione UE | H95: NIS Investments 2025, Main report (sesta edizione) | I95: 08/12/2025 | J95: https://www.enisa.europa.eu/sites/default/files/2025-12/NIS%20Investments%202025%20-%20Main%20report.pdf | L95: Cybersecurity as a share of IT budget, median | M95: Quota mediana della spesa in cybersecurity sul budget IT delle organizzazioni del campione NIS2 nel 2024. | N95: Rapporto di spesa | O95: Quota percentuale | P95: Nessuna | Q95: Totale | R95: 9 | S95: % | U95: 2024 | V95: Consuntivo | X95: =IF(OR($S95="%",$R95=""),"",$R95*INDEX(Cambi!$J$2:$J$5,MATCH($S95,Cambi!$I$2:$I$5,0))/IF($T95="EUR",1,INDEX(Cambi!$D:$D,MATCH($T95&"|"&$U95,Cambi!$C:$C,0)))) | Y95: Imprese e PA | Z95: Sì | AA95: hardware, software, personale interno, collaboratori, outsourcing (CAPEX e OPEX) | AB95: Domanda (end user) | AC95: Dichiarata | AD95: Non dichiarato | AE95: Survey con interviste telefoniche strutturate a 1080 professionisti di organizzazioni dei settori NIS2 ad alta criticità nei 27 Stati membri, 83% grandi imprese e 17% PMI. Spesa 2024 autodichiarata, CAPEX e OPEX per hardware, software, personale, collaboratori e outsourcing. Mediane e medie del campione, senza riporto all'universo. | AF95: Overall, cybersecurity budgets accounted for 9% of total IT budgets | AG95: A | AH95: Pubblico | AI95: Sì | AJ95: Letto da estratto indicizzato della pagina. Quota autodichiarata che include il personale interno, non confrontabile con rapporti di mercato. | AK95: 08/10/2026
A96: 95 | B96: ENISA-NISINV-2025 | C96: EU27 | D96: Unione europea (UE27) | E96: UE | F96: ENISA, Agenzia dell'Unione europea per la cibersicurezza | G96: Istituzione UE | H96: NIS Investments 2025, Main report (sesta edizione) | I96: 08/12/2025 | J96: https://www.enisa.europa.eu/sites/default/files/2025-12/NIS%20Investments%202025%20-%20Main%20report.pdf | L96: Cybersecurity spending, average (million €) | M96: Spesa media in cybersecurity per organizzazione del campione NIS2 nel 2024. | N96: Spesa o budget delle organizzazioni | O96: Media per organizzazione | P96: Nessuna | Q96: Totale | R96: 6.9 | S96: milioni | T96: EUR | U96: 2024 | V96: Consuntivo | X96: =IF(OR($S96="%",$R96=""),"",$R96*INDEX(Cambi!$J$2:$J$5,MATCH($S96,Cambi!$I$2:$I$5,0))/IF($T96="EUR",1,INDEX(Cambi!$D:$D,MATCH($T96&"|"&$U96,Cambi!$C:$C,0)))) -> 6.9 | Y96: Imprese e PA | Z96: Sì | AA96: hardware, software, personale interno, collaboratori, outsourcing (CAPEX e OPEX) | AB96: Domanda (end user) | AC96: Dichiarata | AD96: Non dichiarato | AE96: Survey con interviste telefoniche strutturate a 1080 professionisti di organizzazioni dei settori NIS2 ad alta criticità nei 27 Stati membri, 83% grandi imprese e 17% PMI. Spesa 2024 autodichiarata, CAPEX e OPEX per hardware, software, personale, collaboratori e outsourcing. Mediane e medie del campione, senza riporto all'universo. | AF96: FIG. 1 - IT & CYBERSECURITY SPENDING (ABSOLUTE VALUES) ... CYBERSECURITY SPENDING (MILLION €) ... 10,4 5,1 6,7 6,9 | AG96: A | AH96: Pubblico | AI96: Sì | AJ96: Letto da estratto indicizzato della pagina. Valore letto da grafico (Fig. 1). Abbinamento all'anno 2024 dedotto dall'ordine della serie 2020-2024 e dal testo che indica un aumento modesto della media. Valore per singola organizzazione del campione NIS, non moltiplicabile per il numero di imprese. | AK96: 08/10/2026
A97: 96 | B97: ENISA-NISINV-2025 | C97: EU27 | D97: Unione europea (UE27) | E97: UE | F97: ENISA, Agenzia dell'Unione europea per la cibersicurezza | G97: Istituzione UE | H97: NIS Investments 2025, Main report (sesta edizione) | I97: 08/12/2025 | J97: https://www.enisa.europa.eu/sites/default/files/2025-12/NIS%20Investments%202025%20-%20Main%20report.pdf | L97: Cybersecurity spending, median (million €) | M97: Spesa mediana in cybersecurity per organizzazione del campione NIS2 nel 2024, comprensiva di personale interno e outsourcing. | N97: Spesa o budget delle organizzazioni | O97: Mediana per organizzazione | P97: Nessuna | Q97: Totale | R97: 1.5 | S97: milioni | T97: EUR | U97: 2024 | V97: Consuntivo | X97: =IF(OR($S97="%",$R97=""),"",$R97*INDEX(Cambi!$J$2:$J$5,MATCH($S97,Cambi!$I$2:$I$5,0))/IF($T97="EUR",1,INDEX(Cambi!$D:$D,MATCH($T97&"|"&$U97,Cambi!$C:$C,0)))) -> 1.5 | Y97: Imprese e PA | Z97: Sì | AA97: hardware, software, personale interno, collaboratori, outsourcing (CAPEX e OPEX) | AB97: Domanda (end user) | AC97: Dichiarata | AD97: Non dichiarato | AE97: Survey con interviste telefoniche strutturate a 1080 professionisti di organizzazioni dei settori NIS2 ad alta criticità nei 27 Stati membri, 83% grandi imprese e 17% PMI. Spesa 2024 autodichiarata, CAPEX e OPEX per hardware, software, personale, collaboratori e outsourcing. Mediane e medie del campione, senza riporto all'universo. | AF97: Cybersecurity investment remains broadly in line with the levels reported in last year's study (9% of IT budgets; median 1.5 million euros) | AG97: A | AH97: Pubblico | AI97: Sì | AJ97: Letto da estratto indicizzato della pagina. Valore per singola organizzazione del campione NIS, non moltiplicabile per il numero di imprese. Il valore 1,5 compare anche nella serie della Fig. 1 accanto a 0,6, 0,7 e 1,4 degli anni precedenti. | AK97: 08/10/2026
A98: 97 | B98: FRONTIER-NIS2COST-2023 | C98: EU27 | D98: Unione europea (UE27) | E98: UE | F98: Frontier Economics (studio commissionato da Huawei) | G98: Società di consulenza | H98: Assessing the economic impact of EU initiatives on cybersecurity | I98: 2023 | J98: https://www.frontier-economics.com/media/izyk5rgz/assessing-the-economic-cost-of-eu-initiatives-on-cybersecurity.pdf | L98: Additional costs for businesses to implement NIS2 (per year) | M98: Costo annuo aggiuntivo per le imprese UE per attuare la NIS2, voce nuovi settori nis2, secondo Frontier Economics. | N98: Spesa o budget delle organizzazioni | O98: Totale aggregato | P98: Settore | Q98: Nuovi settori NIS2 | R98: 29.9 | S98: miliardi | T98: EUR | U98: 2025 | V98: Previsione | X98: =IF(OR($S98="%",$R98=""),"",$R98*INDEX(Cambi!$J$2:$J$5,MATCH($S98,Cambi!$I$2:$I$5,0))/IF($T98="EUR",1,INDEX(Cambi!$D:$D,MATCH($T98&"|"&$U98,Cambi!$C:$C,0)))) -> 29900 | Y98: Imprese | Z98: Sì | AA98: personale specializzato, software, hardware, servizi di consulenza e outsourcing | AB98: Domanda (end user) | AC98: Dedotta. Il valore è costruito come costo di conformità per impresa applicato alle imprese dei settori NIS2. | AD98: Bottom-up | AE98: Studio commissionato da Huawei. Stima bottom-up dei costi aggiuntivi delle imprese per attuare la NIS2 (assunzione di specialisti e personale di supporto, software, hardware, servizi esterni), differenziati per dimensione e rischio settoriale, rapportati al fatturato dei settori interessati. | AF98: the increase for the sectors within scope of NIS2 is €29.9 billion per year (0.32% of total revenue). | AG98: B | AH98: Pubblico | AI98: Sì | AJ98: Letto da estratto indicizzato della pagina. Spesa incrementale annua a regime, non livello totale della spesa cyber. Anno non dichiarato, registrato 2025 dopo il recepimento della NIS2. Include personale interno. | AK98: 08/10/2026
A99: 98 | B99: FRONTIER-NIS2COST-2023 | C99: EU27 | D99: Unione europea (UE27) | E99: UE | F99: Frontier Economics (studio commissionato da Huawei) | G99: Società di consulenza | H99: Assessing the economic impact of EU initiatives on cybersecurity | I99: 2023 | J99: https://www.frontier-economics.com/media/izyk5rgz/assessing-the-economic-cost-of-eu-initiatives-on-cybersecurity.pdf | L99: Additional costs for businesses to implement NIS2 (per year) | M99: Costo annuo aggiuntivo per le imprese UE per attuare la NIS2, voce settori già regolati nis, secondo Frontier Economics. | N99: Spesa o budget delle organizzazioni | O99: Totale aggregato | P99: Settore | Q99: Settori già regolati NIS | R99: 1.3 | S99: miliardi | T99: EUR | U99: 2025 | V99: Previsione | X99: =IF(OR($S99="%",$R99=""),"",$R99*INDEX(Cambi!$J$2:$J$5,MATCH($S99,Cambi!$I$2:$I$5,0))/IF($T99="EUR",1,INDEX(Cambi!$D:$D,MATCH($T99&"|"&$U99,Cambi!$C:$C,0)))) -> 1300 | Y99: Imprese | Z99: Sì | AA99: personale specializzato, software, hardware, servizi di consulenza e outsourcing | AB99: Domanda (end user) | AC99: Dedotta. Il valore è costruito come costo di conformità per impresa applicato alle imprese dei settori NIS2. | AD99: Bottom-up | AE99: Studio commissionato da Huawei. Stima bottom-up dei costi aggiuntivi delle imprese per attuare la NIS2 (assunzione di specialisti e personale di supporto, software, hardware, servizi esterni), differenziati per dimensione e rischio settoriale, rapportati al fatturato dei settori interessati. | AF99: The impact of those sectors already regulated under NIS is €1.3 billion per year (0.20% of total sector turnover) | AG99: B | AH99: Pubblico | AI99: Sì | AJ99: Letto da estratto indicizzato della pagina. Spesa incrementale annua a regime, non livello totale della spesa cyber. Anno non dichiarato, registrato 2025 dopo il recepimento della NIS2. Include personale interno. Verifica finale 08/10/2026, valore confermato sulla fonte. Costo annuo di conformità NIS2 confermato, comprende personale, software e hardware di sicurezza. | AK99: 08/10/2026
A100: 99 | B100: FRONTIER-NIS2COST-2023 | C100: EU27 | D100: Unione europea (UE27) | E100: UE | F100: Frontier Economics (studio commissionato da Huawei) | G100: Società di consulenza | H100: Assessing the economic impact of EU initiatives on cybersecurity | I100: 2023 | J100: https://www.frontier-economics.com/media/izyk5rgz/assessing-the-economic-cost-of-eu-initiatives-on-cybersecurity.pdf | L100: Additional costs for businesses to implement NIS2 (per year) | M100: Costo annuo aggiuntivo per le imprese UE per attuare la NIS2, voce totale settori nis2, secondo Frontier Economics. | N100: Spesa o budget delle organizzazioni | O100: Totale aggregato | P100: Nessuna | Q100: Totale | R100: 31.2 | S100: miliardi | T100: EUR | U100: 2025 | V100: Previsione | X100: =IF(OR($S100="%",$R100=""),"",$R100*INDEX(Cambi!$J$2:$J$5,MATCH($S100,Cambi!$I$2:$I$5,0))/IF($T100="EUR",1,INDEX(Cambi!$D:$D,MATCH($T100&"|"&$U100,Cambi!$C:$C,0)))) -> 31200 | Y100: Imprese | Z100: Sì | AA100: personale specializzato, software, hardware, servizi di consulenza e outsourcing | AB100: Domanda (end user) | AC100: Dedotta. Il valore è costruito come costo di conformità per impresa applicato alle imprese dei settori NIS2. | AD100: Bottom-up | AE100: Studio commissionato da Huawei. Stima bottom-up dei costi aggiuntivi delle imprese per attuare la NIS2 (assunzione di specialisti e personale di supporto, software, hardware, servizi esterni), differenziati per dimensione e rischio settoriale, rapportati al fatturato dei settori interessati. | AF100: The direct costs of implementing the regulation on firms across the EU is €31.2 billion per year representing 0.31% of total turnover | AG100: B | AH100: Pubblico | AI100: Sì | AJ100: Letto da estratto indicizzato della pagina. Spesa incrementale annua a regime, non livello totale della spesa cyber. Anno non dichiarato, registrato 2025 dopo il recepimento della NIS2. Include personale interno. | AK100: 08/10/2026
...

Sheet Fonti_Metodologie
A1: ID_Fonte | B1: Ente | C1: Titolo | D1: Edizione | E1: Data di pubblicazione | F1: URL documento | G1: URL nota metodologica | H1: Paesi coperti | I1: Lato della stima | J1: Approccio di calcolo | K1: Metodologia estesa | L1: Campione | M1: Universo | N1: Definizione di cybersecurity adottata | O1: Base prezzi | P1: Trasparenza | Q1: Accesso | R1: N. righe in Dati
A2: 6WRESEARCH-CYBERCZ-2026 | B2: 6Wresearch | C2: Pagine paese sui segmenti della cybersecurity nella Repubblica Ceca | D2: 2026 | E2: 2026 | F2: https://www.6wresearch.com/industry-report/czech-republic-cybersecurity-market | H2: CZ | I2: Non determinabile | J2: Non dichiarato | K2: Pagine prodotto per segmento con valore 2025, previsione 2032 e CAGR. La pagina del mercato totale non mostra valori nell'estratto. Nessuna metodologia. | L2: Non dichiarato | M2: Non dichiarato | N2: Non dichiarata | O2: Non dichiarata | P2: D | Q2: Estratto gratuito di report a pagamento | R2: =COUNTIF(Dati!$B$2:$B$1216,A2) -> 3
A3: 6WRESEARCH-CYBERDE-2026 | B3: 6Wresearch | C3: Germany Cyber Security Market (2020-2026) | D3: aggiornamento giugno 2026 | E3: 2026 | F3: https://www.6wresearch.com/industry-report/germany-cyber-security-market-2020-2026 | H3: DE | I3: Non determinabile | J3: Non dichiarato | K3: Pagina gratuita; dichiara stime basate su un approccio previsionale proprio validato con dataset di settore a giugno 2026. | L3: Non dichiarato | M3: Non dichiarato | N3: Non dichiarata | O3: Non dichiarata | P3: D | Q3: Estratto gratuito di report a pagamento | R3: =COUNTIF(Dati!$B$2:$B$1216,A3) -> 2
A4: 6WRESEARCH-CYBEREUR-2026 | B4: 6Wresearch | C4: Europe Cyber Security Market (2026-2032) | D4: 2026 | E4: 2026 | F4: https://www.6wresearch.com/industry-report/europe-cyber-security-market | G4: https://www.6wresearch.com/faqs | H4: Europa (per paese) | I4: Non determinabile | J4: Modello previsionale o econometrico | K4: Metodologia generica 6Wresearch. Base dati interna e intelligence commerciale (dati di trade e manifest), ricerca primaria con interviste a esperti, panel e sondaggi, banche dati di bilanci; modelli previsionali proprietari (regressione, ARIMA, curve di adozione, dinamica dei sistemi), dimensionamento bottom-up e top-down, triangolazione delle fonti. | L4: Non applicabile | M4: Non dichiarata | N4: Non dichiarata | O4: Dollari USA correnti | P4: C | Q4: Estratto gratuito di report a pagamento | R4: =COUNTIF(Dati!$B$2:$B$1216,A4) -> 2
A5: 6WRESEARCH-CYBERHU-2026 | B5: 6Wresearch | C5: Hungary Cyber Security Market e pagine di segmento | D5: 2026 | E5: 2026 | F5: https://www.6wresearch.com/industry-report/hungary-cyber-security-market | H5: HU | I5: Non determinabile | J5: Non dichiarato | K5: Pagina prodotto con valore di base, previsione e CAGR. Nessuna metodologia nell'estratto. | L5: Non dichiarato | M5: Non dichiarato | N5: Non dichiarata | O5: Non dichiarata | P5: D | Q5: Estratto gratuito di report a pagamento | R5: =COUNTIF(Dati!$B$2:$B$1216,A5) -> 3
A6: 6WRESEARCH-CYBERPL-2026 | B6: 6Wresearch | C6: Poland Cyber Security Market (2025-2031) | D6: 2026 | E6: 2026 | F6: https://www.6wresearch.com/industry-report/poland-cyber-security-market | H6: PL | I6: Non determinabile | J6: Non dichiarato | K6: Pagina prodotto con valore 2025, previsione 2032 e CAGR. Nessuna metodologia nell'estratto. | L6: Non dichiarato | M6: Non dichiarato | N6: Non dichiarata | O6: Non dichiarata | P6: D | Q6: Estratto gratuito di report a pagamento | R6: =COUNTIF(Dati!$B$2:$B$1216,A6) -> 2
A7: 6WRESEARCH-CYBERRO-2026 | B7: 6Wresearch | C7: Romania Cybersecurity Market e pagine di segmento | D7: 2026 | E7: 2026 | F7: https://www.6wresearch.com/industry-report/romania-cybersecurity-market | H7: RO | I7: Non determinabile | J7: Non dichiarato | K7: La pagina cita la banca dati interna dell'editore e approfondimenti di settore, senza altri dettagli. | L7: Non dichiarato | M7: Non dichiarato | N7: Non dichiarata | O7: Non dichiarata | P7: D | Q7: Estratto gratuito di report a pagamento | R7: =COUNTIF(Dati!$B$2:$B$1216,A7) -> 2
A8: 6WRESEARCH-CYBERSK-2026 | B8: 6Wresearch | C8: Slovakia Cyber Security Market e pagine di segmento | D8: 2026 | E8: 2026 | F8: https://www.6wresearch.com/industry-report/slovakia-cyber-security-market | H8: SK | I8: Non determinabile | J8: Non dichiarato | K8: Pagine prodotto con valore 2025, previsione 2032 e CAGR. Nessuna metodologia. | L8: Non dichiarato | M8: Non dichiarato | N8: Non dichiarata | O8: Non dichiarata | P8: D | Q8: Estratto gratuito di report a pagamento | R8: =COUNTIF(Dati!$B$2:$B$1216,A8) -> 3
A9: 6WRESEARCH-METODOLOGIA-2026 | B9: 6Wresearch | C9: FAQ e Research & Intelligence Methodology | D9: 2026 | E9: 2026 | F9: https://www.6wresearch.com/faqs | G9: https://www.6wresearch.com/proprietary-intelligence | H9: Tutti i paesi coperti dall'editore | I9: Non determinabile | J9: Modello previsionale o econometrico | K9: Metodologia generica 6Wresearch. Base dati interna e intelligence commerciale (dati di trade e manifest), ricerca primaria con interviste a esperti, panel e sondaggi, banche dati di bilanci; modelli previsionali proprietari (regressione, ARIMA, curve di adozione, dinamica dei sistemi), dimensionamento bottom-up e top-down, triangolazione delle fonti. | L9: Non applicabile | M9: Non dichiarata | N9: Non dichiarata | O9: Dollari USA correnti | P9: C | Q9: Estratto gratuito di report a pagamento | R9: =COUNTIF(Dati!$B$2:$B$1216,A9) -> 0
A10: ACN-BILANCIO-2024 | B10: Agenzia per la Cybersicurezza Nazionale (ACN) | C10: Bilancio d'esercizio 2023 | D10: 2024 | E10: 2024 | F10: https://www.acn.gov.it/portale/documents/d/guest/acn-bilancio-esercizio-2023 | H10: IT | I10: Domanda (end user) | J10: Non dichiarato | K10: Stanziamento di bilancio o di programma indicato dalla fonte, nessuna stima. | L10: Non dichiarato | M10: Non dichiarato | N10: Non dichiarata | O10: Non dichiarata | P10: B | Q10: Pubblico | R10: =COUNTIF(Dati!$B$2:$B$1216,A10) -> 1
A11: ACN-DPCMFONDI-2024 | B11: Agenzia per la Cybersicurezza Nazionale (ACN) | C11: Strategia nazionale di cybersicurezza, pubblicato il DPCM per la ripartizione dei fondi nel triennio 2024-2026 | D11: 2024 | E11: 09/2024 | F11: https://www.acn.gov.it/portale/w/strategia-nazionale-di-cybersicurezza.-pubblicato-il-dpcm-per-la-ripartizione-dei-fondi-nel-triennio-2024-2026 | H11: IT | I11: Domanda (end user) | J11: Non dichiarato | K11: Stanziamento di bilancio o di programma indicato dalla fonte, nessuna stima. | L11: Non dichiarato | M11: Non dichiarato | N11: Non dichiarata | O11: Non dichiarata | P11: B | Q11: Pubblico | R11: =COUNTIF(Dati!$B$2:$B$1216,A11) -> 1
A12: ACN-OBSERVATOIRE-2019 | B12: Alliance pour la Confiance Numérique (ACN), con DECISION Etudes & Conseil | C12: Observatoire de la filière de la Confiance Numérique | D12: 2019 (dati 2018) | E12: 2019 | F12: https://www.globalsecuritymag.fr/IMG/pdf/Observatoire_ACN_de_la_Confiance_numerique_2019.pdf | G12: https://www.confiance-numerique.fr/lobservatoire-de-la-confiance-numerique/ | H12: FR (con fatturato mondiale delle imprese francesi) | I12: Offerta (fornitori) | J12: Bottom-up | K12: Osservatorio annuale dell'associazione ACN realizzato da DECISION Etudes & Conseil dal 2017. Definisce il perimetro della filiera della confiance numérique (cybersecurity prodotti e servizi, sicurezza digitale con identità e sistemi elettronici di fiducia, dal 2025 IA di fiducia) e ne misura il peso economico in Francia e nel mondo, fatturato, valore aggiunto, occupati, export. Dati da una base di imprese della filiera e da questionari ai membri; il fatturato cyber è una quota del totale. | L12: Base dati di circa 765-2.100 imprese della filiera; questionari ai membri ACN (circa 5% del fatturato nel 2022) | M12: Circa 2.100 imprese della filiera francese della confiance numérique | N12: Cybersecurity (prodotti, software e servizi) e sicurezza digitale; dal 2025 IA di fiducia | O12: Prezzi correnti | P12: B | Q12: Pubblico | R12: =COUNTIF(Dati!$B$2:$B$1216,A12) -> 3
A13: ACN-OBSERVATOIRE-2020 | B13: Alliance pour la Confiance Numérique (ACN), con DECISION Etudes & Conseil | C13: Observatoire de la filière de la Confiance Numérique | D13: 2020 (dati 2019) | E13: 01/2021 | F13: http://www.decision.eu/wp-content/uploads/2021/01/Observatoire-ACN-2020.pdf | G13: https://www.confiance-numerique.fr/lobservatoire-de-la-confiance-numerique/ | H13: FR (con fatturato mondiale delle imprese francesi) | I13: Offerta (fornitori) | J13: Bottom-up | K13: Osservatorio annuale dell'associazione ACN realizzato da DECISION Etudes & Conseil dal 2017. Definisce il perimetro della filiera della confiance numérique (cybersecurity prodotti e servizi, sicurezza digitale con identità e sistemi elettronici di fiducia, dal 2025 IA di fiducia) e ne misura il peso economico in Francia e nel mondo, fatturato, valore aggiunto, occupati, export. Dati da una base di imprese della filiera e da questionari ai membri; il fatturato cyber è una quota del totale. | L13: Base dati di circa 765-2.100 imprese della filiera; questionari ai membri ACN (circa 5% del fatturato nel 2022) | M13: Circa 2.100 imprese della filiera francese della confiance numérique | N13: Cybersecurity (prodotti, software e servizi) e sicurezza digitale; dal 2025 IA di fiducia | O13: Prezzi correnti | P13: B | Q13: Pubblico | R13: =COUNTIF(Dati!$B$2:$B$1216,A13) -> 3
A14: ACN-OBSERVATOIRE-2021 | B14: Alliance pour la Confiance Numérique (ACN), con DECISION Etudes & Conseil | C14: Observatoire de la filière de la Confiance Numérique | D14: 2021 (dati 2020) | E14: 2021 | F14: https://www.confiance-numerique.fr/wp-content/uploads/2023/11/Observatoire-ACN-2021-de-la-confiance-numerique.pdf | G14: https://www.confiance-numerique.fr/lobservatoire-de-la-confiance-numerique/ | H14: FR (con fatturato mondiale delle imprese francesi) | I14: Offerta (fornitori) | J14: Bottom-up | K14: Osservatorio annuale dell'associazione ACN realizzato da DECISION Etudes & Conseil dal 2017. Definisce il perimetro della filiera della confiance numérique (cybersecurity prodotti e servizi, sicurezza digitale con identità e sistemi elettronici di fiducia, dal 2025 IA di fiducia) e ne misura il peso economico in Francia e nel mondo, fatturato, valore aggiunto, occupati, export. Dati da una base di imprese della filiera e da questionari ai membri; il fatturato cyber è una quota del totale. | L14: Base dati di circa 765-2.100 imprese della filiera; questionari ai membri ACN (circa 5% del fatturato nel 2022) | M14: Circa 2.100 imprese della filiera francese della confiance numérique | N14: Cybersecurity (prodotti, software e servizi) e sicurezza digitale; dal 2025 IA di fiducia | O14: Prezzi correnti | P14: B | Q14: Pubblico | R14: =COUNTIF(Dati!$B$2:$B$1216,A14) -> 3
A15: ACN-OBSERVATOIRE-2022 | B15: Alliance pour la Confiance Numérique (ACN), con DECISION Etudes & Conseil | C15: Observatoire de la filière de la Confiance Numérique | D15: 2022 (dati 2021) | E15: 05/2022 | F15: http://www.decision.eu/wp-content/uploads/2022/05/Observatoire-ACN-2022.pdf | G15: https://www.confiance-numerique.fr/lobservatoire-de-la-confiance-numerique/ | H15: FR (con fatturato mondiale delle imprese francesi) | I15: Offerta (fornitori) | J15: Bottom-up | K15: Osservatorio annuale dell'associazione ACN realizzato da DECISION Etudes & Conseil dal 2017. Definisce il perimetro della filiera della confiance numérique (cybersecurity prodotti e servizi, sicurezza digitale con identità e sistemi elettronici di fiducia, dal 2025 IA di fiducia) e ne misura il peso economico in Francia e nel mondo, fatturato, valore aggiunto, occupati, export. Dati da una base di imprese della filiera e da questionari ai membri; il fatturato cyber è una quota del totale. | L15: Base dati di circa 765-2.100 imprese della filiera; questionari ai membri ACN (circa 5% del fatturato nel 2022) | M15: Circa 2.100 imprese della filiera francese della confiance numérique | N15: Cybersecurity (prodotti, software e servizi) e sicurezza digitale; dal 2025 IA di fiducia | O15: Prezzi correnti | P15: B | Q15: Pubblico | R15: =COUNTIF(Dati!$B$2:$B$1216,A15) -> 4
A16: ACN-OBSERVATOIRE-2023 | B16: Alliance pour la Confiance Numérique (ACN), con DECISION Etudes & Conseil | C16: Observatoire de la filière de la Confiance Numérique | D16: 2023 (dati 2022) | E16: 06/2023 | F16: https://www.confiance-numerique.fr/wp-content/uploads/2023/11/Observatoire-ACN-2023-de-la-confiance-numerique-bd.pdf | G16: https://www.confiance-numerique.fr/lobservatoire-de-la-confiance-numerique/ | H16: FR (con fatturato mondiale delle imprese francesi) | I16: Offerta (fornitori) | J16: Bottom-up | K16: Osservatorio annuale dell'associazione ACN realizzato da DECISION Etudes & Conseil dal 2017. Definisce il perimetro della filiera della confiance numérique (cybersecurity prodotti e servizi, sicurezza digitale con identità e sistemi elettronici di fiducia, dal 2025 IA di fiducia) e ne misura il peso economico in Francia e nel mondo, fatturato, valore aggiunto, occupati, export. Dati da una base di imprese della filiera e da questionari ai membri; il fatturato cyber è una quota del totale. | L16: Base dati di circa 765-2.100 imprese della filiera; questionari ai membri ACN (circa 5% del fatturato nel 2022) | M16: Circa 2.100 imprese della filiera francese della confiance numérique | N16: Cybersecurity (prodotti, software e servizi) e sicurezza digitale; dal 2025 IA di fiducia | O16: Prezzi correnti | P16: B | Q16: Pubblico | R16: =COUNTIF(Dati!$B$2:$B$1216,A16) -> 4
A17: ACN-OBSERVATOIRE-2024 | B17: Alliance pour la Confiance Numérique (ACN), con DECISION Etudes & Conseil | C17: Observatoire de la filière de la Confiance Numérique | D17: 2024 (dati 2023) | E17: 06/2024 | F17: https://www.confiance-numerique.fr/wp-content/uploads/2024/05/ACN-Observatoire-de-la-filiere-de-la-confiance-numerique2024-bd.pdf | G17: https://www.confiance-numerique.fr/lobservatoire-de-la-confiance-numerique/ | H17: FR (con fatturato mondiale delle imprese francesi) | I17: Offerta (fornitori) | J17: Bottom-up | K17: Osservatorio annuale dell'associazione ACN realizzato da DECISION Etudes & Conseil dal 2017. Definisce il perimetro della filiera della confiance numérique (cybersecurity prodotti e servizi, sicurezza digitale con identità e sistemi elettronici di fiducia, dal 2025 IA di fiducia) e ne misura il peso economico in Francia e nel mondo, fatturato, valore aggiunto, occupati, export. Dati da una base di imprese della filiera e da questionari ai membri; il fatturato cyber è una quota del totale. | L17: Base dati di circa 765-2.100 imprese della filiera; questionari ai membri ACN (circa 5% del fatturato nel 2022) | M17: Circa 2.100 imprese della filiera francese della confiance numérique | N17: Cybersecurity (prodotti, software e servizi) e sicurezza digitale; dal 2025 IA di fiducia | O17: Prezzi correnti | P17: B | Q17: Pubblico | R17: =COUNTIF(Dati!$B$2:$B$1216,A17) -> 5
A18: ACN-OBSERVATOIRE-2025 | B18: Alliance pour la Confiance Numérique (ACN), con DECISION Etudes & Conseil | C18: Observatoire de la filière de la Confiance Numérique | D18: 2025 (dati 2024) | E18: 06/2025 | F18: https://www.confiance-numerique.fr/lobservatoire-de-la-confiance-numerique/ | G18: https://www.confiance-numerique.fr/lobservatoire-de-la-confiance-numerique/ | H18: FR (con fatturato mondiale delle imprese francesi) | I18: Offerta (fornitori) | J18: Bottom-up | K18: Osservatorio annuale dell'associazione ACN realizzato da DECISION Etudes & Conseil dal 2017. Definisce il perimetro della filiera della confiance numérique (cybersecurity prodotti e servizi, sicurezza digitale con identità e sistemi elettronici di fiducia, dal 2025 IA di fiducia) e ne misura il peso economico in Francia e nel mondo, fatturato, valore aggiunto, occupati, export. Dati da una base di imprese della filiera e da questionari ai membri; il fatturato cyber è una quota del totale. | L18: Base dati di circa 765-2.100 imprese della filiera; questionari ai membri ACN (circa 5% del fatturato nel 2022) | M18: Circa 2.100 imprese della filiera francese della confiance numérique | N18: Cybersecurity (prodotti, software e servizi) e sicurezza digitale; dal 2025 IA di fiducia | O18: Prezzi correnti | P18: B | Q18: Pubblico | R18: =COUNTIF(Dati!$B$2:$B$1216,A18) -> 3
A19: ACN-OBSERVATOIRE-2026 | B19: Alliance pour la Confiance Numérique (ACN), con DECISION Etudes & Conseil | C19: Observatoire de la filière de la Confiance Numérique | D19: 2026 (dati 2025) | E19: 06/2026 | F19: https://www.confiance-numerique.fr/https-www-confiance-numerique-fr-wp-content-uploads-2026-06-observatoire-acn-2026-de-la-confiance-numerique-bd-pdf/ | G19: https://www.confiance-numerique.fr/lobservatoire-de-la-confiance-numerique/ | H19: FR (con fatturato mondiale delle imprese francesi) | I19: Offerta (fornitori) | J19: Bottom-up | K19: Osservatorio annuale dell'associazione ACN realizzato da DECISION Etudes & Conseil dal 2017. Definisce il perimetro della filiera della confiance numérique (cybersecurity prodotti e servizi, sicurezza digitale con identità e sistemi elettronici di fiducia, dal 2025 IA di fiducia) e ne misura il peso economico in Francia e nel mondo, fatturato, valore aggiunto, occupati, export. Dati da una base di imprese della filiera e da questionari ai membri; il fatturato cyber è una quota del totale. | L19: Base dati di circa 765-2.100 imprese della filiera; questionari ai membri ACN (circa 5% del fatturato nel 2022) | M19: Circa 2.100 imprese della filiera francese della confiance numérique | N19: Cybersecurity (prodotti, software e servizi) e sicurezza digitale; dal 2025 IA di fiducia | O19: Prezzi correnti | P19: B | Q19: Pubblico | R19: =COUNTIF(Dati!$B$2:$B$1216,A19) -> 3
A20: ACN-RELAZIONE-2024 | B20: Agenzia per la Cybersicurezza Nazionale (ACN) | C20: Relazione annuale al Parlamento 2023 | D20: 2024 | E20: 2024 | F20: https://www.acn.gov.it/portale/relazione-annuale-2023 | H20: IT | I20: Domanda (end user) | J20: Non dichiarato | K20: Stanziamento di bilancio o di programma indicato dalla fonte, nessuna stima. | L20: Non dichiarato | M20: Non dichiarato | N20: Non dichiarata | O20: Non dichiarata | P20: B | Q20: Pubblico | R20: =COUNTIF(Dati!$B$2:$B$1216,A20) -> 2
A21: ACN-STORIAMISSIONE-2024 | B21: Agenzia per la Cybersicurezza Nazionale (ACN) | C21: L'Agenzia per la cybersicurezza nazionale, storia, missione, obiettivi | D21: 2024 | E21: 2024 | F21: https://www.acn.gov.it/portale/documents/20119/56212/testo_Frattasi_review_final.pdf/21228528-4473-702f-375a-d8b18ad1bce5?t=1715606273341 | H21: IT | I21: Domanda (end user) | J21: Non dichiarato | K21: Stanziamento di bilancio o di programma indicato dalla fonte, nessuna stima. | L21: Non dichiarato | M21: Non dichiarato | N21: Non dichiarata | O21: Non dichiarata | P21: B | Q21: Pubblico | R21: =COUNTIF(Dati!$B$2:$B$1216,A21) -> 1
A22: ACN-STRATEGIA-2022 | B22: Agenzia per la Cybersicurezza Nazionale (ACN) | C22: Strategia nazionale di cybersicurezza 2022-2026 | D22: 2022 | E22: 25/05/2022 | F22: https://giurisprudenza.unimc.it/it/ricerca/dirittoapplicato/site-news/ACN_Strategia.pdf | H22: IT | I22: Domanda (end user) | J22: Non dichiarato | K22: Stanziamento di bilancio o di programma indicato dalla fonte, nessuna stima. | L22: Non dichiarato | M22: Non dichiarato | N22: Non dichiarata | O22: Non dichiarata | P22: B | Q22: Pubblico | R22: =COUNTIF(Dati!$B$2:$B$1216,A22) -> 1
A23: AGORIA-CYBERNEWS-2025 | B23: Agoria | C23: Belgian cyber sector set to double in size within five years | D23: 02/10/2025 | E23: 02/10/2025 | F23: https://www.agoria.be/en/services/expertise/digitalisation/cybersecurity/belgian-cyber-sector-set-to-double-in-size-within-five-years-4000-experts-needed | H23: BE | I23: Offerta (fornitori) | J23: Bottom-up | K23: Comunicato di presentazione dell'aggiornamento 2025 dello studio socio-economico Agoria sul settore cyber. | L23: Non dichiarato | M23: Non dichiarato | N23: Non dichiarata | O23: Non dichiarata | P23: B | Q23: Pubblico | R23: =COUNTIF(Dati!$B$2:$B$1216,A23) -> 1
A24: AGORIA-CYBERSECTOR-2022 | B24: Agoria, con Ministero della Difesa e CCB | C24: Socio-economic study on the cybersecurity sector in Belgium (prima edizione), sintesi Agoria | D24: 2022 | E24: 16/11/2022 | F24: https://www.agoria.be/en/services/expertise/digitalisation/cybersecurity/first-step-taken-towards-israeli-cyber-reference-model-now-to-invest-in-a-number-of-experts | H24: BE | I24: Offerta (fornitori) | J24: Bottom-up | K24: Prima mappatura socio-economica del settore cyber belga, 441 imprese attive in cybersecurity, fatturato cyber, valore aggiunto, FTE, export, posti vacanti e attese di crescita delle imprese. | L24: Non dichiarato | M24: Imprese attive in cybersecurity con sede in Belgio | N24: Attività di cybersecurity delle imprese censite | O24: Prezzi correnti | P24: B | Q24: Pubblico | R24: =COUNTIF(Dati!$B$2:$B$1216,A24) -> 2
A25: AGORIA-CYBERSECTOR-2025 | B25: Agoria | C25: Socio-economic study on the cybersecurity sector in Belgium (aggiornamento) | D25: 2025 | E25: 10/2025 | F25: https://cdn.assets.prezly.com/243be490-ca27-4a42-aec1-1dc14b8d6a41/-/inline/no/Agoria_Socio-Economic-Study-Belgian-Cybersecurity-Sector.pdf | H25: BE | I25: Offerta (fornitori) | J25: Bottom-up | K25: Aggiornamento dello studio socio-economico con fatturato, valore aggiunto e FTE 2021-2024 del settore cyber belga (732 imprese e organizzazioni) e proiezione 2025-2030 ottenuta dal centro studi Agoria applicando previsioni Statista, Gartner e IDC. | L25: Non dichiarato | M25: Imprese e organizzazioni attive in cybersecurity in Belgio | N25: Attività di cybersecurity delle imprese censite | O25: Prezzi correnti | P25: B | Q25: Pubblico | R25: =COUNTIF(Dati!$B$2:$B$1216,A25) -> 3
A26: AGORIA-ICTTRENDS-2025 | B26: Agoria | C26: Trends en toekomst van de Belgische ICT-bedrijven | D26: 28/01/2025 | E26: 28/01/2025 | F26: https://www.agoria.be/nl/diensten/expertise/conjunctuur-prijzen/conjunctuur/trends-en-toekomst-van-de-belgische-ict-bedrijven | H26: BE | I26: Non determinabile | J26: Ripreso da altra fonte | K26: Pagina congiunturale Agoria sul settore ICT con stima del mercato cyber belga da cifre Statista, Gartner e IDC e calcoli del centro studi. | L26: Non dichiarato | M26: Non dichiarato | N26: Non dichiarata | O26: Non dichiarata | P26: C | Q26: Pubblico | R26: =COUNTIF(Dati!$B$2:$B$1216,A26) -> 2
A27: AIBOARD-CYBERRO-2026 | B27: AI Board | C27: Piața de securitate cibernetică - România 2026 | D27: 2026 | E27: 24/04/2026 | F27: https://virtualboard.ro/produs/piata-de-cybersecurity-romania-2026/ | H27: RO | I27: Non determinabile | J27: Non dichiarato | K27: Studio a pagamento con valore 2025, crescita storica 2018-2025 e previsione al 2030 per la Romania. La pagina prodotto non descrive il metodo. | L27: Non dichiarato | M27: Non dichiarato | N27: Non dichiarata | O27: Non dichiarata | P27: D | Q27: Estratto gratuito di report a pagamento | R27: =COUNTIF(Dati!$B$2:$B$1216,A27) -> 2
A28: ALLIEDICT-KYBER-2021 | B28: Allied ICT Finland | C28: Kyberturvallisuus Suomessa 2019-2029, visio ja tavoitteet | D28: 2019-2029 | E28: 06/2021 | F28: https://www.alliedict.fi/wp-content/uploads/2021/06/3.Kyberturvallisuus_Suomessa_2019-2029.pdf | H28: FI | I28: Offerta (fornitori) | J28: Non dichiarato | K28: Non dichiarata | L28: Non dichiarato | M28: Non dichiarato | N28: Non dichiarata | O28: Prezzi correnti | P28: D | Q28: Pubblico | R28: =COUNTIF(Dati!$B$2:$B$1216,A28) -> 1
A29: ANITEC-ILDIGITALE-2018 | B29: Anitec-Assinform | C29: Il Digitale in Italia 2018 | D29: 2018 | E29: 2018 | F29: https://www.anitec-assinform.it/kdocs/1920845/il_digitale_in_italia_2018.pdf | H29: IT | I29: Offerta (fornitori) | J29: Non dichiarato | K29: Nota metodologica generica del rapporto Il Digitale in Italia. Analisi primaria con interviste trimestrali dirette e telefoniche, condotte da NetConsulting cube con questionario approvato da Anitec-Assinform, a un panel di almeno 400 fornitori ICT classificati per segmento, e interviste ad almeno 5.000 aziende utenti (circa 1.000 grandi e 4.000 minori) rivolte ai responsabili SI e CIO per verificare strategie. Analisi secondaria su fonti bibliografiche. Il mercato è misurato come spesa dell'utente finale. Nessun dettaglio specifico per il mercato cybersecurity. | L29: Panel di almeno 400 fornitori ICT e almeno 5.000 aziende utenti | M29: Mercato digitale italiano, settori di utenza privati e pubblici | N29: Security hardware, security software, servizi MSS e cloud security, consulenza, altri servizi (system integration, risk assessment, penetration test, formazione) | O29: Prezzi correnti, spesa dell'utente finale (dichiarato per il mercato digitale) | P29: C | Q29: Pubblico | R29: =COUNTIF(Dati!$B$2:$B$1216,A29) -> 3
A30: ANITEC-ILDIGITALE-2019 | B30: Anitec-Assinform | C30: Il Digitale in Italia 2019 | D30: 2019 | E30: 2019 | F30: https://www.anitec-assinform.it/kdocs/1962491/il_digitale_in_italia_2019.pdf | H30: IT | I30: Offerta (fornitori) | J30: Non dichiarato | K30: Nota metodologica generica del rapporto Il Digitale in Italia. Analisi primaria con interviste trimestrali dirette e telefoniche, condotte da NetConsulting cube con questionario approvato da Anitec-Assinform, a un panel di almeno 400 fornitori ICT classificati per segmento, e interviste ad almeno 5.000 aziende utenti (circa 1.000 grandi e 4.000 minori) rivolte ai responsabili SI e CIO per verificare strategie. Analisi secondaria su fonti bibliografiche. Il mercato è misurato come spesa dell'utente finale. Nessun dettaglio specifico per il mercato cybersecurity. | L30: Panel di almeno 400 fornitori ICT e almeno 5.000 aziende utenti | M30: Mercato digitale italiano, settori di utenza privati e pubblici | N30: Security hardware, security software, servizi MSS e cloud security, consulenza, altri servizi (system integration, risk assessment, penetration test, formazione) | O30: Prezzi correnti, spesa dell'utente finale (dichiarato per il mercato digitale) | P30: C | Q30: Pubblico | R30: =COUNTIF(Dati!$B$2:$B$1216,A30) -> 3
A31: ANITEC-ILDIGITALE-2020 | B31: Anitec-Assinform | C31: Il Digitale in Italia 2020, volume I | D31: 2020 | E31: 2020 | F31: https://www.anitec-assinform.it/kdocs/1981743/il_digitale_in_italia_2020_vol_i.pdf | H31: IT | I31: Offerta (fornitori) | J31: Non dichiarato | K31: Nota metodologica generica del rapporto Il Digitale in Italia. Analisi primaria con interviste trimestrali dirette e telefoniche, condotte da NetConsulting cube con questionario approvato da Anitec-Assinform, a un panel di almeno 400 fornitori ICT classificati per segmento, e interviste ad almeno 5.000 aziende utenti (circa 1.000 grandi e 4.000 minori) rivolte ai responsabili SI e CIO per verificare strategie. Analisi secondaria su fonti bibliografiche. Il mercato è misurato come spesa dell'utente finale. Nessun dettaglio specifico per il mercato cybersecurity. | L31: Panel di almeno 400 fornitori ICT e almeno 5.000 aziende utenti | M31: Mercato digitale italiano, settori di utenza privati e pubblici | N31: Security hardware, security software, servizi MSS e cloud security, consulenza, altri servizi (system integration, risk assessment, penetration test, formazione) | O31: Prezzi correnti, spesa dell'utente finale (dichiarato per il mercato digitale) | P31: C | Q31: Pubblico | R31: =COUNTIF(Dati!$B$2:$B$1216,A31) -> 5
... A41: BDI-MISP63-2025 | B41: Banca d'Italia | C41: Mercati, infrastrutture, sistemi di pagamento n. 63, Indagine conoscitiva sul mercato italiano dei servizi di testing di cybersicurezza | D41: 2025 | E41: 09/2025 | F41: https://www.bancaditalia.it/pubblicazioni/mercati-infrastrutture-e-sistemi-di-pagamento/approfondimenti/2025-063/N.63-MISP.pdf | H41: IT | I41: Domanda (end user) | J41: Ripreso da altra fonte | K41: Ripreso dalla rilevazione CIPA sul 2023, media sui gruppi bancari rispondenti. | L41: Non dichiarato | M41: Non dichiarato | N41: Non dichiarata | O41: Non dichiarata | P41: C | Q41: Solo citato da terzi | R41: =COUNTIF(Dati!$B$2:$B$1216,A41) -> 1
